Workbook
Name cash: DCF!$C$24
Name debt: DCF!$C$25
Name ebi: CCA!$L$20:$L$24,CCA!$L$26:$L$30
Name fcff: DCF!$L$18
Name reve: CCA!$J$20:$J$23,CCA!$J$25:$J$30
Name tgr: DCF!$I$22
Name wacc: DCF!$I$21

Sheet DCF
B2: Discounted Cash Flow Analysis | F2: CSX Corp. (CSX)
B3: Perpetuity Approach
H4: 0.5 | I4: =H4+1 -> 1.5 | J4: =I4+1 -> 2.5 | K4: =J4+1 -> 3.5 | L4: =K4+1 -> 4.5
B5: $M | C5: 2018 | D5: 2019 | E5: 2020 | F5: 2021 | G5: 2022 | H5: 2023 | I5: 2024 | J5: 2025 | K5: 2026 | L5: 2027
B6: Revenue, Adj | C6: 12250 | D6: 11937 | E6: 10583 | F6: 12522 | G6: 14853 | H6: 14614.154 | I6: 14995.846 | J6: =1091.8*2025-2194100 -> 16795 | K6: =1092.6*2026-2194100 -> 19507.6 | L6: =1091.8*2027-2194100 -> 18978.6
B7: Growth %, YoY | C7: 7.3808 | D7: -2.5551 | E7: -11.3429 | F7: 18.3218 | G7: 18.6152 | H7: =(H6/G6-1)*100 -> -1.6080657 | I7: =(I6/H6-1)*100 -> 2.6117968 | J7: =(J6/I6-1)*100 -> 11.997683 | K7: =(K6/J6-1)*100 -> 16.151235 | L7: =(L6/K6-1)*100 -> -2.7117636
B8: Gross Profit, Adj | C8: — | D8: — | E8: — | F8: — | G8: — | H8: — | I8: — | J8: — | K8: — | L8: —
B9: Margin % | C9: — | D9: — | E9: — | F9: — | G9: — | H9: — | I9: — | J9: — | K9: — | L9: —
B10: EBITDA, Adj | C10: 6046 | D10: 6269 | E10: 5792 | F10: 6649 | G10: 7394 | H10: 7149.182 | I10: 7417.5 | J10: =J6*J11/100 -> 8598.7811 | K10: =K6*K11/100 -> 9849.8346 | L10: =L6*L11/100 -> 9483.8043
B11: Margin % | C11: 49.355102 | D11: 52.517383 | E11: 54.729283 | F11: 53.098547 | G11: 49.781189 | H11: =H10/H6*100 -> 48.919575 | I11: =I10/I6*100 -> 49.463698 | J11: =AVERAGE(E11:I11) -> 51.198458 | K11: =AVERAGE(F11:J11) -> 50.492293 | L11: =AVERAGE(G11:K11) -> 49.971043
B12: Net Income, Adj | C12: 3200.34 | D12: 3198.09 | E12: 2737.35 | F12: 3378.34 | G12: 3907.98 | H12: 3695.192 | I12: 3837.577 | J12: =145.59*2025-290817 -> 4002.75 | K12: =145.59*2026-290817 -> 4148.34 | L12: =145.59*2027-290817 -> 4293.93
B13: Margin % | C13: 26.125224 | D13: 26.791405 | E13: 25.865539 | F13: 26.979237 | G13: 26.311048 | H13: =H12/H6*100 -> 25.285022 | I13: =I12/I6*100 -> 25.590934 | J13: =J12/J6*100 -> 23.832986 | K13: =K12/K6*100 -> 21.26525 | L13: =L12/L6*100 -> 22.625115
B14: EPS, Adj | C14: 1.2383 | D14: 1.3345 | E14: 0.396 | F14: 1.5014 | G14: 1.8295 | H14: 1.833 | I14: 1.984 | J14: =J12/$C$27 -> 2.0256832 | K14: =K12/$C$27 -> 2.0993623 | L14: =L12/$C$27 -> 2.1730415
B15: Growth %, YoY | C15: 65.458561 | D15: 7.7673784 | E15: -70.326001 | F15: 279.1498 | G15: 21.849002 | H15: =((H14/G14)-1)*100 -> 0.1913091 | I15: =((I14/H14)-1)*100 -> 8.2378614 | J15: =((J14/I14)-1)*100 -> 2.1009677 | K15: =((K14/J14)-1)*100 -> 3.6372494 | L15: =((L14/K14)-1)*100 -> 3.5095966
B16: Cash from Operations | C16: 4641 | D16: 4850 | E16: 4263 | F16: 5099 | G16: 5619 | H16: 5768.1582 | I16: 5966.3163 | J16: 6653.8023 | K16: 7702.5743 | L16: 7446.8086
B17: Capital Expenditures | C17: -1745 | D17: -1657 | E17: -1626 | F17: -1791 | G17: -2133 | H17: -2108.9374 | I17: -2169.5937 | J17: -2449.6037 | K17: -2814.8542 | L17: -2743.3311
B18: Free Cash Flow | C18: 2896 | D18: 3193 | E18: 2637 | F18: 3308 | G18: 3486 | H18: 3130.927 | I18: 3480.17 | J18: =150.93*2025-301695 -> 3938.25 | K18: =190.51*2026-381967 -> 4006.26 | L18: =191.52*2027-384010 -> 4201.04 | P18: GOAL
B19: Present value of FCF | H19: =H18/(1+$F$26)^((1+$F$27)^H4) -> 2887.8597 | I19: =I18/(1+$F$26)^((1+$F$27)^I4) -> 3198.5698 | J19: =J18/(1+$F$26)^((1+$F$27)^J4) -> 3606.1404 | K19: =K18/(1+$F$26)^((1+$F$27)^K4) -> 3654.1905 | L19: =L18/(1+$F$26)^((1+$F$27)^L4) -> 3816.3409 | O19: Python -> | P19: 39.38 | Q19: 44.282
B21: Terminal Value in Y5 | C21: =fcff*(1+tgr)/(wacc-tgr) -> 80766.39 | E21: % Debt | F21: =C25/F30 -> 0.59572833 | H21: WACC (% Equity x Cost of Equity) + (% Debt x Cost of Debt x (1 -Tax rate)) | I21: =Summary!BC14/100 -> 0.073055 | J21: ← from Bloomberg | N21: Share Price on | O21: 45249 | P21: 31.63
B22: Present value of TV | C22: =C21/(1+$F$26)^((1+$F$27)^4.5) -> 73370.422 | E22: Cost of Debt | F22: =Summary!$BC$9/100 -> 0.041244 | H22: TGR | I22: 0.02 | O22: Upside in 2026 | P22: =P19/P21-1 -> 0.24502055
B23: Enterprise Value | C23: =SUM(H19:L19,C22) -> 90533.523 | E23: Tax Rate | F23: 0.2487
B24: + Cash | C24: =Summary!G6 -> 2087 | E24: Equity Value | F24: =BS!G72 -> 12625
B25: - Debt | C25: =Summary!G8 -> 18604 | E25: % Equity | F25: =F24/F30 -> 0.40427167 | P25: Terminal Growth Rate
B26: Equity Value | C26: =C23+C24-C25 -> 74016.523 | E26: Cost of Equity Risk Free Rate + (Beta x (Expected Market Return - Risk Free Rate)) | F26: =Summary!$BC$6/100 -> 0.0823 | P26: =Q26-0.005 -> 0.01 | Q26: =R26-0.005 -> 0.015 | R26: =tgr -> 0.02 | S26: =R26+0.005 -> 0.025 | T26: =S26+0.005 -> 0.03
B27: Shares | C27: 1976 | E27: Risk Free Rate | F27: 0.0441 | G27: from US10Y | N27: WACC | O27: =O28+0.005 -> 0.083055 | P27: =TEXT(((((((fcff*(1+P$26))/ABS($O27-P$26))/(1+$F$26)^((1+$F$27)^4.5))+SUM($H$19:$L$19)-$C$25+$C$24)/$C$27/$P$21)-1),"0.0%") &" / "& TEXT(((((fcff*(1+P$26))/ABS($O27-P$26))/(1+$F$26)^((1+$F$27)^4.5))+SUM($H$19:$L$19)-$C$25+$C$24)/$C$27,"$0.00") -> -14.5% / $27.03 | Q27: =TEXT(((((((fcff*(1+Q$26))/ABS($O27-Q$26))/(1+$F$26)^((1+$F$27)^4.5))+SUM($H$19:$L$19)-$C$25+$C$24)/$C$27/$P$21)-1),"0.0%") &" / "& TEXT(((((fcff*(1+Q$26))/ABS($O27-Q$26))/(1+$F$26)^((1+$F$27)^4.5))+SUM($H$19:$L$19)-$C$25+$C$24)/$C$27,"$0.00") -> -7.9% / $29.13 | R27: =TEXT(((((((fcff*(1+R$26))/ABS($O27-R$26))/(1+$F$26)^((1+$F$27)^4.5))+SUM($H$19:$L$19)-$C$25+$C$24)/$C$27/$P$21)-1),"0.0%") &" / "& TEXT(((((fcff*(1+R$26))/ABS($O27-R$26))/(1+$F$26)^((1+$F$27)^4.5))+SUM($H$19:$L$19)-$C$25+$C$24)/$C$27,"$0.00") -> -0.2% / $31.57 | S27: =TEXT(((((((fcff*(1+S$26))/ABS($O27-S$26))/(1+$F$26)^((1+$F$27)^4.5))+SUM($H$19:$L$19)-$C$25+$C$24)/$C$27/$P$21)-1),"0.0%") &" / "& TEXT(((((fcff*(1+S$26))/ABS($O27-S$26))/(1+$F$26)^((1+$F$27)^4.5))+SUM($H$19:$L$19)-$C$25+$C$24)/$C$27,"$0.00") -> 8.8% / $34.43 | T27: =TEXT(((((((fcff*(1+T$26))/ABS($O27-T$26))/(1+$F$26)^((1+$F$27)^4.5))+SUM($H$19:$L$19)-$C$25+$C$24)/$C$27/$P$21)-1),"0.0%") &" / "& TEXT(((((fcff*(1+T$26))/ABS($O27-T$26))/(1+$F$26)^((1+$F$27)^4.5))+SUM($H$19:$L$19)-$C$25+$C$24)/$C$27,"$0.00") -> 19.6% / $37.82
B28: Share Price | C28: =C26/C27 -> 37.457755 | E28: Beta | F28: 0.986 | O28: =O29+0.005 -> 0.078055 | P28: =TEXT(((((((fcff*(1+P$26))/ABS($O28-P$26))/(1+$F$26)^((1+$F$27)^4.5))+SUM($H$19:$L$19)-$C$25+$C$24)/$C$27/$P$21)-1),"0.0%") &" / "& TEXT(((((fcff*(1+P$26))/ABS($O28-P$26))/(1+$F$26)^((1+$F$27)^4.5))+SUM($H$19:$L$19)-$C$25+$C$24)/$C$27,"$0.00") -> -8.3% / $28.99 | Q28: =TEXT(((((((fcff*(1+Q$26))/ABS($O28-Q$26))/(1+$F$26)^((1+$F$27)^4.5))+SUM($H$19:$L$19)-$C$25+$C$24)/$C$27/$P$21)-1),"0.0%") &" / "& TEXT(((((fcff*(1+Q$26))/ABS($O28-Q$26))/(1+$F$26)^((1+$F$27)^4.5))+SUM($H$19:$L$19)-$C$25+$C$24)/$C$27,"$0.00") -> -0.7% / $31.42 | R28: =TEXT(((((((fcff*(1+R$26))/ABS($O28-R$26))/(1+$F$26)^((1+$F$27)^4.5))+SUM($H$19:$L$19)-$C$25+$C$24)/$C$27/$P$21)-1),"0.0%") &" / "& TEXT(((((fcff*(1+R$26))/ABS($O28-R$26))/(1+$F$26)^((1+$F$27)^4.5))+SUM($H$19:$L$19)-$C$25+$C$24)/$C$27,"$0.00") -> 8.3% / $34.26 | S28: =TEXT(((((((fcff*(1+S$26))/ABS($O28-S$26))/(1+$F$26)^((1+$F$27)^4.5))+SUM($H$19:$L$19)-$C$25+$C$24)/$C$27/$P$21)-1),"0.0%") &" / "& TEXT(((((fcff*(1+S$26))/ABS($O28-S$26))/(1+$F$26)^((1+$F$27)^4.5))+SUM($H$19:$L$19)-$C$25+$C$24)/$C$27,"$0.00") -> 19.0% / $37.64 | T28: =TEXT(((((((fcff*(1+T$26))/ABS($O28-T$26))/(1+$F$26)^((1+$F$27)^4.5))+SUM($H$19:$L$19)-$C$25+$C$24)/$C$27/$P$21)-1),"0.0%") &" / "& TEXT(((((fcff*(1+T$26))/ABS($O28-T$26))/(1+$F$26)^((1+$F$27)^4.5))+SUM($H$19:$L$19)-$C$25+$C$24)/$C$27,"$0.00") -> 31.9% / $41.72
E29: Market Risk Premium = Market return - Risk free return | F29: =G29-F27 -> 0.0323 | G29: 0.0764 | O29: =wacc -> 0.073055 | P29: =TEXT(((((((fcff*(1+P$26))/ABS($O29-P$26))/(1+$F$26)^((1+$F$27)^4.5))+SUM($H$19:$L$19)-$C$25+$C$24)/$C$27/$P$21)-1),"0.0%") &" / "& TEXT(((((fcff*(1+P$26))/ABS($O29-P$26))/(1+$F$26)^((1+$F$27)^4.5))+SUM($H$19:$L$19)-$C$25+$C$24)/$C$27,"$0.00") -> -1.2% / $31.26 | Q29: =TEXT(((((((fcff*(1+Q$26))/ABS($O29-Q$26))/(1+$F$26)^((1+$F$27)^4.5))+SUM($H$19:$L$19)-$C$25+$C$24)/$C$27/$P$21)-1),"0.0%") &" / "& TEXT(((((fcff*(1+Q$26))/ABS($O29-Q$26))/(1+$F$26)^((1+$F$27)^4.5))+SUM($H$19:$L$19)-$C$25+$C$24)/$C$27,"$0.00") -> 7.8% / $34.09 | R29: =TEXT(((((((fcff*(1+R$26))/ABS($O29-R$26))/(1+$F$26)^((1+$F$27)^4.5))+SUM($H$19:$L$19)-$C$25+$C$24)/$C$27/$P$21)-1),"0.0%") &" / "& TEXT(((((fcff*(1+R$26))/ABS($O29-R$26))/(1+$F$26)^((1+$F$27)^4.5))+SUM($H$19:$L$19)-$C$25+$C$24)/$C$27,"$0.00") -> 18.4% / $37.46 | S29: =TEXT(((((((fcff*(1+S$26))/ABS($O29-S$26))/(1+$F$26)^((1+$F$27)^4.5))+SUM($H$19:$L$19)-$C$25+$C$24)/$C$27/$P$21)-1),"0.0%") &" / "& TEXT(((((fcff*(1+S$26))/ABS($O29-S$26))/(1+$F$26)^((1+$F$27)^4.5))+SUM($H$19:$L$19)-$C$25+$C$24)/$C$27,"$0.00") -> 31.3% / $41.52 | T29: =TEXT(((((((fcff*(1+T$26))/ABS($O29-T$26))/(1+$F$26)^((1+$F$27)^4.5))+SUM($H$19:$L$19)-$C$25+$C$24)/$C$27/$P$21)-1),"0.0%") &" / "& TEXT(((((fcff*(1+T$26))/ABS($O29-T$26))/(1+$F$26)^((1+$F$27)^4.5))+SUM($H$19:$L$19)-$C$25+$C$24)/$C$27,"$0.00") -> 47.1% / $46.53
E30: Debt + Equity | F30: =C25+F24 -> 31229 | O30: =O29-0.005 -> 0.068055 | P30: =TEXT(((((((fcff*(1+P$26))/ABS($O30-P$26))/(1+$F$26)^((1+$F$27)^4.5))+SUM($H$19:$L$19)-$C$25+$C$24)/$C$27/$P$21)-1),"0.0%") &" / "& TEXT(((((fcff*(1+P$26))/ABS($O30-P$26))/(1+$F$26)^((1+$F$27)^4.5))+SUM($H$19:$L$19)-$C$25+$C$24)/$C$27,"$0.00") -> 7.3% / $33.93 | Q30: =TEXT(((((((fcff*(1+Q$26))/ABS($O30-Q$26))/(1+$F$26)^((1+$F$27)^4.5))+SUM($H$19:$L$19)-$C$25+$C$24)/$C$27/$P$21)-1),"0.0%") &" / "& TEXT(((((fcff*(1+Q$26))/ABS($O30-Q$26))/(1+$F$26)^((1+$F$27)^4.5))+SUM($H$19:$L$19)-$C$25+$C$24)/$C$27,"$0.00") -> 17.8% / $37.28 | R30: =TEXT(((((((fcff*(1+R$26))/ABS($O30-R$26))/(1+$F$26)^((1+$F$27)^4.5))+SUM($H$19:$L$19)-$C$25+$C$24)/$C$27/$P$21)-1),"0.0%") &" / "& TEXT(((((fcff*(1+R$26))/ABS($O30-R$26))/(1+$F$26)^((1+$F$27)^4.5))+SUM($H$19:$L$19)-$C$25+$C$24)/$C$27,"$0.00") -> 30.6% / $41.32 | S30: =TEXT(((((((fcff*(1+S$26))/ABS($O30-S$26))/(1+$F$26)^((1+$F$27)^4.5))+SUM($H$19:$L$19)-$C$25+$C$24)/$C$27/$P$21)-1),"0.0%") &" / "& TEXT(((((fcff*(1+S$26))/ABS($O30-S$26))/(1+$F$26)^((1+$F$27)^4.5))+SUM($H$19:$L$19)-$C$25+$C$24)/$C$27,"$0.00") -> 46.4% / $46.31 | T30: =TEXT(((((((fcff*(1+T$26))/ABS($O30-T$26))/(1+$F$26)^((1+$F$27)^4.5))+SUM($H$19:$L$19)-$C$25+$C$24)/$C$27/$P$21)-1),"0.0%") &" / "& TEXT(((((fcff*(1+T$26))/ABS($O30-T$26))/(1+$F$26)^((1+$F$27)^4.5))+SUM($H$19:$L$19)-$C$25+$C$24)/$C$27,"$0.00") -> 66.3% / $52.60
O31: =O30-0.005 -> 0.063055 | P31: =TEXT(((((((fcff*(1+P$26))/ABS($O31-P$26))/(1+$F$26)^((1+$F$27)^4.5))+SUM($H$19:$L$19)-$C$25+$C$24)/$C$27/$P$21)-1),"0.0%") &" / "& TEXT(((((fcff*(1+P$26))/ABS($O31-P$26))/(1+$F$26)^((1+$F$27)^4.5))+SUM($H$19:$L$19)-$C$25+$C$24)/$C$27,"$0.00") -> 17.3% / $37.09 | Q31: =TEXT(((((((fcff*(1+Q$26))/ABS($O31-Q$26))/(1+$F$26)^((1+$F$27)^4.5))+SUM($H$19:$L$19)-$C$25+$C$24)/$C$27/$P$21)-1),"0.0%") &" / "& TEXT(((((fcff*(1+Q$26))/ABS($O31-Q$26))/(1+$F$26)^((1+$F$27)^4.5))+SUM($H$19:$L$19)-$C$25+$C$24)/$C$27,"$0.00") -> 30.0% / $41.12 | R31: =TEXT(((((((fcff*(1+R$26))/ABS($O31-R$26))/(1+$F$26)^((1+$F$27)^4.5))+SUM($H$19:$L$19)-$C$25+$C$24)/$C$27/$P$21)-1),"0.0%") &" / "& TEXT(((((fcff*(1+R$26))/ABS($O31-R$26))/(1+$F$26)^((1+$F$27)^4.5))+SUM($H$19:$L$19)-$C$25+$C$24)/$C$27,"$0.00") -> 45.7% / $46.08 | S31: =TEXT(((((((fcff*(1+S$26))/ABS($O31-S$26))/(1+$F$26)^((1+$F$27)^4.5))+SUM($H$19:$L$19)-$C$25+$C$24)/$C$27/$P$21)-1),"0.0%") &" / "& TEXT(((((fcff*(1+S$26))/ABS($O31-S$26))/(1+$F$26)^((1+$F$27)^4.5))+SUM($H$19:$L$19)-$C$25+$C$24)/$C$27,"$0.00") -> 65.5% / $52.35 | T31: =TEXT(((((((fcff*(1+T$26))/ABS($O31-T$26))/(1+$F$26)^((1+$F$27)^4.5))+SUM($H$19:$L$19)-$C$25+$C$24)/$C$27/$P$21)-1),"0.0%") &" / "& TEXT(((((fcff*(1+T$26))/ABS($O31-T$26))/(1+$F$26)^((1+$F$27)^4.5))+SUM($H$19:$L$19)-$C$25+$C$24)/$C$27,"$0.00") -> 91.3% / $60.51

Sheet CCA
C2: Comparable Company Analysis | G2: CSX Corp. (CSX)
H4: Revenue (in million USDs) | K4: EBITDA (in million USDs) | M4: Net Income (in millions)
B5: Ticker | C5: Company | D5: Share Price | E5: nbr of Shares | F5: Enterprise Value | G5: Market Cap | H5: 2021 | I5: 2022 | J5: 2023 | K5: 2022 | L5: 2023 | M5: 2022 | N5: 2023
B6: WAB | C6: WAB Tech | D6: =DCF!P21 -> 31.63 | E6: =DCF!C27 -> 1976 | F6: =Summary!G9 -> 80543.05 | G6: =Summary!G5 -> 64016.05 | H6: =Summary!F11 -> 12522 | I6: =Summary!G11 -> 14853 | J6: =Summary!I11 -> 14614.154 | K6: =Summary!G15 -> 7394 | L6: =Summary!I15 -> 7149.182 | M6: =Summary!G17 -> 3907.98 | N6: =Summary!I17 -> 3695.192
B7: JBHT | C7: `J.B. Hunt | D7: 183.05 | E7: 103.14 | F7: 20250 | G7: 18800 | H7: 12168 | I7: 12341 | J7: 10900 | K7: 1331 | L7: 1778 | M7: 969 | N7: 776
B8: KTK | C8: KTK Group | D8: 1.31 | E8: 783 | F8: 1132 | G8: 1028 | H8: 588 | I8: 525.6 | J8: 523.7 | K8: 47.5 | L8: 52.9 | M8: 26.3 | N8: 35.2
B9: ODFL | C9: Old Dominion Freight Line | D9: 404.32 | E9: 109.11 | F9: 43990 | G9: 44120 | H9: 5256 | I9: 6260 | J9: 5862 | K9: 1842 | L9: 1655 | M9: 1377 | N9: 1240
B10: SRAIL | C10: Stadler Rail | D10: 35.92 | E10: 100 | F10: 3815 | G10: 3592 | H10: 3976 | I10: 3930 | J10: 4317 | K10: 322 | L10: 367 | M10: 75 | N10: 163
B11: CP | C11: Canadian Pacific | D11: 72.19 | E11: 932 | F11: 83310 | G11: 66540 | H11: 7995 | I11: 8814 | J11: 11241 | K11: 5650 | L11: -937 | M11: 3517 | N11: 4163
B12: CNR | C12: Canadian National Railways | D12: 157.24 | E12: 647.7 | F12: 120040 | G12: 101840 | H12: 14477 | I12: 17107 | J12: 16899 | K12: 9040 | L12: 8978 | M12: 5118 | N12: 4915
B13: NSC | C13: Norfolk Southern | D13: 199.07 | E13: 226.14 | F13: 60090 | G13: 45017 | H13: 11142 | I13: 12745 | J13: 12320 | K13: 6043 | L13: 4688 | M13: 3270 | N13: 2090
B14: TRN | C14: Trinity Industres | D14: 23.32 | E14: 81.87 | F14: 7580 | G14: 1909 | H14: 1516 | I14: 1977 | J14: 2451 | K14: 334 | L14: 658 | M14: 86 | N14: 94
B15: UNP | C15: Union Pacific | D15: 215.33 | E15: 609.6 | F15: 161370 | G15: 127650 | H15: 21804 | I15: 24875 | J15: 24140 | K15: 12589 | L15: 11860 | M15: 6998 | N15: 6365
B16: GET | C16: Getlink | D16: 16.09 | E16: 540 | F16: 12620 | G16: 8490 | H16: 774 | I16: 1606 | J16: 1962 | K16: 460 | L16: 617 | M16: 252 | N16: 358
B18: Ticker | C18: Revenue Growth | E18: EBITDA Margin | G18: Profit Margin | I18: EV / Revenue | K18: EV / EBITDA | M18: P / E
C19: 2022 | D19: 2023 | E19: 2022 | F19: 2023 | G19: 2022 | H19: 2023 | I19: 2022 | J19: 2023 | K19: 2022 | L19: 2023 | M19: 2022 | N19: 2023
B20: WAB | C20: =I6/H6-1 -> 0.18615237 | D20: =J6/I6-1 -> -0.016080657 | E20: =K6/I6 -> 0.49781189 | F20: =L6/J6 -> 0.48919575 | G20: =M6/I6 -> 0.26311048 | H20: =N6/J6 -> 0.25285022 | I20: =$F6/I6 -> 5.4226789 | J20: =$F6/J6 -> 5.5113043 | K20: =$F6/K6 -> 10.893028 | L20: =$F6/L6 -> 11.266051 | M20: =$G6/M6 -> 16.380854 | N20: =$G6/N6 -> 17.324147
B21: JBHT | C21: =I7/H7-1 -> 0.01421762 | D21: =J7/I7-1 -> -0.11676525 | E21: =K7/I7 -> 0.10785188 | F21: =L7/J7 -> 0.16311927 | G21: =M7/I7 -> 0.078518759 | H21: =N7/J7 -> 0.071192661 | I21: =$F7/I7 -> 1.6408719 | J21: =$F7/J7 -> 1.8577982 | K21: =$F7/K7 -> 15.214125 | L21: =$F7/L7 -> 11.389201 | M21: =$G7/M7 -> 19.401445 | N21: =$G7/N7 -> 24.226804
B22: KTK | C22: =I8/H8-1 -> -0.10612245 | D22: =J8/I8-1 -> -0.0036149163 | E22: =K8/I8 -> 0.090372907 | F22: =L8/J8 -> 0.10101203 | G22: =M8/I8 -> 0.050038052 | H22: =N8/J8 -> 0.067214054 | I22: =$F8/I8 -> 2.1537291 | J22: =$F8/J8 -> 2.1615429 | K22: =$F8/K8 -> 23.831579 | L22: =$F8/L8 -> 21.398866 | M22: =$G8/M8 -> 39.087452 | N22: =$G8/N8 -> 29.204545
B23: ODFL | C23: =I9/H9-1 -> 0.19101979 | D23: =J9/I9-1 -> -0.063578275 | E23: =K9/I9 -> 0.2942492 | F23: =L9/J9 -> 0.28232685 | G23: =M9/I9 -> 0.21996805 | H23: =N9/J9 -> 0.2115319 | I23: =$F9/I9 -> 7.0271565 | J23: =$F9/J9 -> 7.5042648 | K23: =$F9/K9 -> 23.88165 | L23: =$F9/L9 -> 26.58006 | M23: =$G9/M9 -> 32.040668 | N23: =$G9/N9 -> 35.580645
B24: SRAIL | C24: =I10/H10-1 -> -0.011569416 | D24: =J10/I10-1 -> 0.098473282 | E24: =K10/I10 -> 0.081933842 | F24: =L10/J10 -> 0.08501274 | G24: =M10/I10 -> 0.019083969 | H24: =N10/J10 -> 0.037757702 | I24: =$F10/I10 -> 0.97073791 | J24: =$F10/J10 -> 0.88371554 | K24: =$F10/K10 -> 11.847826 | L24: =$F10/L10 -> 10.395095 | M24: =$G10/M10 -> 47.893333 | N24: =$G10/N10 -> 22.03681
B25: CP | C25: =I11/H11-1 -> 0.10243902 | D25: =J11/I11-1 -> 0.27535739 | E25: =K11/I11 -> 0.64102564 | F25: =L11/J11 -> -0.083355573 | G25: =M11/I11 -> 0.39902428 | H25: =N11/J11 -> 0.37034072 | I25: =$F11/I11 -> 9.4520082 | J25: =$F11/J11 -> 7.4112623 | K25: =$F11/K11 -> 14.745133 | L25: =$F11/L11 -> -88.911419 | M25: =$G11/M11 -> 18.919534 | N25: =$G11/N11 -> 15.983666
B26: CNR | C26: =I12/H12-1 -> 0.18166747 | D26: =J12/I12-1 -> -0.012158765 | E26: =K12/I12 -> 0.52843865 | F26: =L12/J12 -> 0.53127404 | G26: =M12/I12 -> 0.29917578 | H26: =N12/J12 -> 0.29084561 | I26: =$F12/I12 -> 7.0170106 | J26: =$F12/J12 -> 7.1033789 | K26: =$F12/K12 -> 13.278761 | L26: =$F12/L12 -> 13.370461 | M26: =$G12/M12 -> 19.898398 | N26: =$G12/N12 -> 20.720244
B27: NSC | C27: =I13/H13-1 -> 0.14387004 | D27: =J13/I13-1 -> -0.03334641 | E27: =K13/I13 -> 0.47414672 | F27: =L13/J13 -> 0.38051948 | G27: =M13/I13 -> 0.2565712 | H27: =N13/J13 -> 0.16964286 | I27: =$F13/I13 -> 4.7147901 | J27: =$F13/J13 -> 4.8774351 | K27: =$F13/K13 -> 9.9437366 | L27: =$F13/L13 -> 12.817833 | M27: =$G13/M13 -> 13.766667 | N27: =$G13/N13 -> 21.539234
B28: TRN | C28: =I14/H14-1 -> 0.30408971 | D28: =J14/I14-1 -> 0.23975721 | E28: =K14/I14 -> 0.16894284 | F28: =L14/J14 -> 0.26846185 | G28: =M14/I14 -> 0.043500253 | H28: =N14/J14 -> 0.038351693 | I28: =$F14/I14 -> 3.8340921 | J28: =$F14/J14 -> 3.0926153 | K28: =$F14/K14 -> 22.694611 | L28: =$F14/L14 -> 11.519757 | M28: =$G14/M14 -> 22.197674 | N28: =$G14/N14 -> 20.308511
B29: UNP | C29: =I15/H15-1 -> 0.14084572 | D29: =J15/I15-1 -> -0.029547739 | E29: =K15/I15 -> 0.50609045 | F29: =L15/J15 -> 0.49130075 | G29: =M15/I15 -> 0.28132663 | H29: =N15/J15 -> 0.26367026 | I29: =$F15/I15 -> 6.4872362 | J29: =$F15/J15 -> 6.6847556 | K29: =$F15/K15 -> 12.818333 | L29: =$F15/L15 -> 13.606239 | M29: =$G15/M15 -> 18.240926 | N29: =$G15/N15 -> 20.054988
B30: GET | C30: =I16/H16-1 -> 1.0749354 | D30: =J16/I16-1 -> 0.22166874 | E30: =K16/I16 -> 0.2864259 | F30: =L16/J16 -> 0.31447503 | G30: =M16/I16 -> 0.15691158 | H30: =N16/J16 -> 0.18246687 | I30: =$F16/I16 -> 7.8580324 | J30: =$F16/J16 -> 6.432212 | K30: =$F16/K16 -> 27.434783 | L30: =$F16/L16 -> 20.453809 | M30: =$G16/M16 -> 33.690476 | N30: =$G16/N16 -> 23.715084
D32: 2023 Trading Multiple | G32: Enterprise Value | J32: Equity Value | M32: Implied Share Price
D33: Revenue | E33: EBITDA | F33: P/E | G33: Revenue | H33: EBITDA | I33: Net Income | J33: Revenue | K33: EBITDA | L33: Net Income | M33: Share Price
C34: Minimum | D34: =MIN(reve) -> 1.8577982 | E34: =MIN(ebi) -> 10.395095 | F34: =MIN(N20:N30) -> 15.983666 | G34: =D34*$J$6 -> 27150.148 | H34: =E34*$L$6 -> 74316.429 | I34: =N$6*F34 -> 59062.713 | J34: =G34+cash-debt -> 10633.148 | K34: =H34+cash-debt -> 57799.429 | L34: =I34+cash-debt -> 42545.713 | M34: =K34/E$6 -> 29.250723
C35: 1st Quartile | D35: =QUARTILE(reve,1) -> 3.5388202 | E35: =QUARTILE(ebi,1) -> 11.42184 | F35: =QUARTILE(N20:N30,1) -> 20.181749 | G35: =D35*$J$6 -> 51716.864 | H35: =E35*$L$6 -> 81656.815 | I35: =N$6*F35 -> 74575.439 | J35: =G35+cash-debt -> 35199.864 | K35: =H35+cash-debt -> 65139.815 | L35: =I35+cash-debt -> 58058.439 | M35: =K35/E$6 -> 32.965493
C36: Lower Limit 75% | D36: =D37-0.674*_xlfn.STDEV.S(reve)/SQRT(11) -> 4.8217943 | E36: =E37-0.674*_xlfn.STDEV.S(ebi)/SQRT(11) -> 14.15914 | F36: =F37-0.674*_xlfn.STDEV.S(N20:N30)/SQRT(11) -> 21.670098 | G36: =D36*$J$6 -> 70466.445 | H36: =E36*$L$6 -> 101226.27 | I36: =N$6*F36 -> 80075.172 | J36: =G36+cash-debt -> 53949.445 | K36: =H36+cash-debt -> 84709.268 | L36: =I36+cash-debt -> 63558.172 | M36: =K36/E$6 -> 42.869063
C37: Mean | D37: =AVERAGE(reve) -> 5.2636569 | E37: =AVERAGE(ebi) -> 15.279737 | F37: =AVERAGE(N20:N30) -> 22.790425 | G37: =D37*$J$6 -> 76923.893 | H37: =E37*$L$6 -> 109237.62 | I37: =N$6*F37 -> 84214.997 | J37: =G37+cash-debt -> 60406.893 | K37: =H37+cash-debt -> 92720.623 | L37: =I37+cash-debt -> 67697.997 | M37: =K37/E$6 -> 46.923392
C38: Upper Limit 75% | D38: =D37+0.674*_xlfn.STDEV.S(reve)/SQRT(11) -> 5.7055195 | E38: =E37+0.674*_xlfn.STDEV.S(ebi)/SQRT(11) -> 16.400335 | F38: =F37+0.674*_xlfn.STDEV.S(N20:N30)/SQRT(11) -> 23.910753 | G38: =D38*$J$6 -> 83381.341 | H38: =E38*$L$6 -> 117248.98 | I38: =N$6*F38 -> 88354.823 | J38: =G38+cash-debt -> 66864.341 | K38: =H38+cash-debt -> 100731.98 | L38: =I38+cash-debt -> 71837.823 | M38: =K38/E$6 -> 50.977721
C39: 3rd Quartile | D39: =QUARTILE(reve,3) -> 6.9987231 | E39: =QUARTILE(ebi,3) -> 18.741916 | F39: =QUARTILE(N20:N30,3) -> 23.970944 | G39: =D39*$J$6 -> 102280.42 | H39: =E39*$L$6 -> 133989.37 | I39: =N$6*F39 -> 88577.24 | J39: =G39+cash-debt -> 85763.417 | K39: =H39+cash-debt -> 117472.37 | L39: =I39+cash-debt -> 72060.24 | M39: =K39/E$6 -> 59.449581
C40: Maximum | D40: =MAX(J21:J30) -> 7.5042648 | E40: =MAX(L21:L30) -> 26.58006 | F40: =MAX(N20:N30) -> 35.580645 | G40: =D40*$J$6 -> 109668.48 | H40: =E40*$L$6 -> 190025.69 | I40: =N$6*F40 -> 131477.32 | J40: =G40+cash-debt -> 93151.481 | K40: =H40+cash-debt -> 173508.69 | L40: =I40+cash-debt -> 114960.32 | M40: =K40/E$6 -> 87.808041

Sheet Summary
A1: CSX Corp (CSX US) - BBG Adj Highlights | O1: CSX Corp (CSX US) - Growth | BA1: CSX Corp (CSX US) - L#1518025
A3: In Millions of USD | C3: FY 2018 | D3: FY 2019 | E3: FY 2020 | F3: FY 2021 | G3: FY 2022 | H3: Current/LTM | I3: FY 2023 Est | J3: FY 2024 Est | O3: In Millions of USD except Per Share | Q3: FY 1988 | R3: FY 1989 | S3: FY 1990 | T3: FY 1991 | U3: FY 1992 | V3: FY 1993 | W3: FY 1994 | X3: FY 1995 | Y3: FY 1996 | Z3: FY 1997 | AA3: FY 1998 | AB3: FY 1999 | AC3: FY 2000 | AD3: FY 2001 | AE3: FY 2002 | AF3: FY 2003 | AG3: FY 2004 | AH3: FY 2005 | AI3: FY 2006 | AJ3: FY 2007 | AK3: FY 2008 | AL3: FY 2009 | AM3: FY 2010 | AN3: FY 2011 | AO3: FY 2012 | AP3: FY 2013 | AQ3: FY 2014 | AR3: FY 2015 | AS3: FY 2016 | AT3: FY 2017 | AU3: FY 2018 | AV3: FY 2019 | AW3: FY 2020 | AX3: FY 2021 | AY3: FY 2022 | BA3: WACC History | BC3: FY 2022 | BD3: FY 2021 | BE3: FY 2020 | BF3: FY 2019 | BG3: FY 2018 | BH3: FY 2017 | BI3: FY 2016 | BJ3: FY 2015 | BK3: FY 2014 | BL3: FY 2013 | BM3: FY 2012 | BN3: FY 2011 | BO3: FY 2010 | BP3: FY 2009 | BQ3: FY 2008 | BR3: FY 2007 | BS3: FY 2006 | BT3: FY 2005 | BU3: FY 2004 | BV3: FY 2003
A4: 12 Months Ending | C4: 12/31/2018 | D4: 12/31/2019 | E4: 12/31/2020 | F4: 12/31/2021 | G4: 12/31/2022 | H4: 09/30/2023 | I4: 12/31/2023 | J4: 12/31/2024 | O4: 12 Months Ending | Q4: 12/31/1988 | R4: 12/31/1989 | S4: 12/31/1990 | T4: 12/31/1991 | U4: 12/31/1992 | V4: 12/31/1993 | W4: 12/30/1994 | X4: 12/30/1995 | Y4: 12/31/1996 | Z4: 12/26/1997 | AA4: 12/31/1998 | AB4: 12/31/1999 | AC4: 12/29/2000 | AD4: 12/28/2001 | AE4: 12/27/2002 | AF4: 12/26/2003 | AG4: 12/31/2004 | AH4: 12/30/2005 | AI4: 12/29/2006 | AJ4: 12/28/2007 | AK4: 12/26/2008 | AL4: 12/25/2009 | AM4: 12/31/2010 | AN4: 12/30/2011 | AO4: 12/28/2012 | AP4: 12/27/2013 | AQ4: 12/26/2014 | AR4: 12/25/2015 | AS4: 12/30/2016 | AT4: 12/31/2017 | AU4: 12/31/2018 | AV4: 12/31/2019 | AW4: 12/31/2020 | AX4: 12/31/2021 | AY4: 12/31/2022 | BA4: 12 Months Ending | BC4: 12/31/2022 | BD4: 12/31/2021 | BE4: 12/31/2020 | BF4: 12/31/2019 | BG4: 12/31/2018 | BH4: 12/31/2017 | BI4: 12/30/2016 | BJ4: 12/25/2015 | BK4: 12/26/2014 | BL4: 12/27/2013 | BM4: 12/28/2012 | BN4: 12/30/2011 | BO4: 12/31/2010 | BP4: 12/25/2009 | BQ4: 12/26/2008 | BR4: 12/28/2007 | BS4: 12/29/2006 | BT4: 12/30/2005 | BU4: 12/31/2004 | BV4: 12/26/2003
A5: Market Capitalization | B5: HISTORICAL_MARKET_CAP | C5: 50833.523 | D5: 55968.362 | E5: 207598.52 | F5: 82787.191 | G5: 64016.05 | H5: 63866.579 | O5: 1 Year Growth | Q5: {=GEOMEAN(Q6:AY6/100+1)-1} -> 0.017680203 | BA5: Equity
A6: - Cash & Equivalents | B6: CASH_AND_MARKETABLE_SECURITIES | C6: 1111 | D6: 1954 | E6: 3131 | F6: 2316 | G6: 2087 | H6: 1439 | O6: Revenue | P6: SALES_GROWTH | Q6: -5.6074 | R6: 2.0153 | S6: 5.9393 | T6: 5.2529 | U6: 1.1348 | V6: 2.3586 | W6: 7.472 | X6: 9.3256 | Y6: 0.3046 | Z6: 0.8068 | AA6: -7.0897 | AB6: 5.1378 | AC6: -21.0506 | AD6: -0.9889 | AE6: 0.5179 | AF6: -7.1884 | AG6: 6.2649 | AH6: 7.1891 | AI6: 11.0002 | AJ6: 4.8505 | AK6: 12.2134 | AL6: -19.6713 | AM6: 17.6419 | AN6: 10.897 | AO6: -0.3306 | AP6: 2.2967 | AQ6: 5.3467 | AR6: -6.7724 | AS6: -6.2823 | AT6: 3.0626 | AU6: 7.3808 | AV6: -2.5551 | AW6: -11.3429 | AX6: 18.3218 | AY6: 18.6152 | BA6: Cost of Equity | BB6: WACC_COST_EQUITY | BC6: 8.23 | BD6: 9.9753 | BE6: 8.8113 | BF6: 9.0663 | BG6: 11.8505 | BH6: 10.1221 | BI6: 10.5031 | BJ6: 10.7549 | BK6: 9.9474 | BL6: 11.2585 | BM6: 12.3654 | BN6: 13.0941 | BO6: 15.0257 | BP6: 11.5097 | BQ6: 11.7515 | BR6: 11.9134 | BS6: 11.6332 | BT6: 10.9957 | BU6: 9.3144 | BV6: 9.0797
A7: + Preferred & Other | B7: PFD_EQTY_MINORTY_INTEREST | C7: 17 | D7: 15 | E7: 9 | F7: 10 | G7: 10 | H7: 4 | O7: EBITDA | P7: EBITDA_GROWTH | Q7: -4.378 | R7: -4.3605 | S7: -2.1277 | T7: 5.2019 | U7: 10.1107 | V7: -0.4692 | W7: 21.8182 | X7: 12.1614 | Y7: 5.5692 | Z7: 6.0224 | AA7: -22.5011 | AB7: -32.1591 | AC7: 17.6717 | AD7: 12.3843 | AE7: 12.4763 | AF7: -34.5158 | AG7: 48.7532 | AH7: 37.7457 | AI7: 26.1016 | AJ7: 4.6922 | AK7: 17.1647 | AL7: -13.9175 | AM7: 26.6309 | AN7: 10.6521 | AO7: 1.5744 | AP7: 1.3508 | AQ7: 4.0856 | AR7: 0.5877 | AS7: -2.1285 | AT7: 7.3561 | AU7: 23.138 | AV7: 3.1935 | AW7: -8.9247 | AX7: 21.8981 | AY7: 7.4476 | BA7: Weight of Equity | BB7: WACC_WEIGHT_OF_EQUITY | BC7: 77.4825 | BD7: 83.0403 | BE7: 92.3467 | BF7: 76.9257 | BG7: 77.5013 | BH7: 80.5644 | BI7: 74.7035 | BJ7: 70.5429 | BK7: 78.8739 | BL7: 74.9184 | BM7: 66.851 | BN7: 70.5102 | BO7: 73.3986 | BP7: 71.21 | BQ7: 61.0998 | BR7: 71.3311 | BS7: 71.6557 | BT7: 64.7537 | BU7: 54.0901 | BV7: 51.1861
A8: + Total Debt | B8: SHORT_AND_LONG_TERM_DEBT | C8: 14757 | D8: 16788 | E8: 17205 | F8: 16908 | G8: 18604 | H8: 18949 | O8: Operating Income | P8: OPER_INC_GROWTH | Q8: 1.5642 | R8: -4.4004 | S8: -6.214 | T8: 4.7853 | U8: 12.9977 | V8: -5.3886 | W8: 34.9398 | X8: 15.9903 | Y8: 6.508 | Z8: 4.0079 | AA8: -28.6166 | AB8: -49.292 | AC8: 40.4887 | AD8: 18.882 | AE8: 17.7638 | AF8: -53.8598 | AG8: 92.3077 | AH8: 55 | AI8: 37.9355 | AJ8: 5.5192 | AK8: 22.695 | AL8: -17.9913 | AM8: 35.2863 | AN8: 12.9925 | AO8: -0.3746 | AP8: 0.4628 | AQ8: 4.0311 | AR8: -0.8027 | AS8: -5.4408 | AT8: 9.7669 | AU8: 30.8871 | AV8: 1.9717 | AW8: -12.145 | AX8: 28.2439 | AY8: 7.6689 | BA8: + Debt
A9: Enterprise Value | B9: ENTERPRISE_VALUE | C9: 64496.523 | D9: 70817.362 | E9: 221681.52 | F9: 97389.191 | G9: 80543.05 | H9: 81380.579 | O9: Net Income to Common | P9: EARN_FOR_COM_GROWTH | Q9: 0.7353 | R9: 220.438 | S9: -7.2893 | T9: — | U9: — | V9: 1695 | W9: 81.6156 | X9: -5.2147 | Y9: 38.3495 | Z9: -6.5497 | AA9: -32.791 | AB9: -99.6276 | AC9: 28150 | AD9: -48.1416 | AE9: 44.7099 | AF9: -41.9811 | AG9: 37.8049 | AH9: 237.7581 | AI9: 14.4105 | AJ9: 1.9847 | AK9: 2.1707 | AL9: -16.2637 | AM9: 36.7454 | AN9: 18.682 | AO9: 0.2156 | AP9: 0.2152 | AQ9: 3.3816 | AR9: 2.1288 | AS9: -12.9131 | AT9: 219.3228 | AU9: -39.5247 | AV9: 0.6953 | AW9: -16.9919 | AX9: 36.745 | AY9: 10.1825 | BA9: Cost of Debt | BB9: WACC_COST_DEBT | BC9: 4.1244 | BD9: 1.5807 | BE9: 0.9397 | BF9: 2.0369 | BG9: 2.8496 | BH9: 3.3206 | BI9: 2.079 | BJ9: 1.9388 | BK9: 1.936 | BL9: 2.5144 | BM9: 1.4206 | BN9: 1.6093 | BO9: 2.8116 | BP9: 3.5887 | BQ9: 1.9549 | BR9: 3.7171 | BS9: 4.7908 | BT9: 4.3609 | BU9: 3.7945 | BV9: 4.0281
O10: EPS Diluted | P10: DILUTED_EPS_AFT_XO_ITEMS_GROWTH | Q10: 5.6818 | R10: 366.6667 | S10: -4.3779 | T10: — | U10: — | V10: 1721.0526 | W10: 80.0578 | X10: -5.618 | Y10: 34.6939 | Z10: -6.0606 | AA10: -32.5269 | AB10: -99.6016 | AC10: 26600 | AD10: -48.3146 | AE10: 44.2029 | AF10: -44.2211 | AG10: 36.9369 | AH10: 231.5789 | AI10: 11.9048 | AJ10: 6.0284 | AK10: 11.7057 | AL10: -13.4731 | AM10: 40.1384 | AN10: 25.9259 | AO10: 5.2941 | AP10: 2.2346 | AQ10: 4.918 | AR10: 4.1667 | AS10: -9.5 | AT10: 230.9392 | AU10: -35.8932 | AV10: 8.5938 | AW10: -71.223 | AX10: 320 | AY10: 16.0714 | BA10: Weight of Debt | BB10: WACC_WEIGHT_OF_DEBT | BC10: 22.5175 | BD10: 16.9597 | BE10: 7.6533 | BF10: 23.0743 | BG10: 22.4987 | BH10: 19.4356 | BI10: 25.2965 | BJ10: 29.4571 | BK10: 21.1261 | BL10: 25.0816 | BM10: 33.149 | BN10: 29.4898 | BO10: 26.6014 | BP10: 28.79 | BQ10: 38.9002 | BR10: 28.6689 | BS10: 28.3443 | BT10: 35.2463 | BU10: 45.9099 | BV10: 48.8139
A11: Revenue, Adj | B11: SALES_REV_TURN | C11: 12250 | D11: 11937 | E11: 10583 | F11: 12522 | G11: 14853 | H11: 14707 | I11: 14614.154 | J11: 14995.846 | O11: EPS Diluted before XO | P11: DILUTED_EPS_BEF_XO_ITEMS_GROWTH | Q11: — | R11: — | S11: -11.2469 | T11: — | U11: — | V11: 1721.0526 | W11: 80.0578 | X11: -5.618 | Y11: 34.6939 | Z11: -6.0606 | AA11: -32.5269 | AB11: -90.4382 | AC11: 265.1921 | AD11: 57.4514 | AE11: 58.6957 | AF11: -71.2329 | AG11: 196.8254 | AH11: 69.5187 | AI11: 77.918 | AJ11: -2.8369 | AK11: 33.5766 | AL11: -22.1311 | AM11: 42.1053 | AN11: 25.9259 | AO11: 5.2941 | AP11: 2.2346 | AQ11: 4.918 | AR11: 4.1667 | AS11: -9.5 | AT11: 230.9392 | AU11: -35.8932 | AV11: 8.5938 | AW11: -71.223 | AX11: 320 | AY11: 16.0714 | BA11: + Preferred Equity
A12: Growth %, YoY | B12: SALES_GROWTH | C12: 7.3808 | D12: -2.5551 | E12: -11.3429 | F12: 18.3218 | G12: 18.6152 | H12: 1.0790378 | I12: -1.6080657 | J12: 2.6117968 | O12: EPS Diluted before Abnormal | P12: RR_DIL_EPS_CONT_OPS_GROWTH | Q12: — | R12: — | S12: -11.2469 | T12: — | U12: — | V12: 1721.0526 | W12: 80.0578 | X12: -5.618 | Y12: 34.6939 | Z12: 5.303 | AA12: -52.0384 | AB12: -92.5 | AC12: 486.6667 | AD12: 56.8182 | AE12: 44.2029 | AF12: -42.7136 | AG12: 64.0351 | AH12: 69.5187 | AI12: 77.918 | AJ12: -4.2553 | AK12: 35.5556 | AL12: -22.1311 | AM12: 45.3434 | AN12: 23.1204 | AO12: -0.625 | AP12: 5.0118 | AQ12: 10.2385 | AR12: -0.7736 | AS12: -7.2455 | AT12: 24.7399 | AU12: 65.4584 | AV12: 7.7674 | AW12: -70.326 | AX12: 279.1495 | AY12: 21.849 | BA12: Cost of Pref. Equity | BB12: WACC_COST_PFD | BC12: 0 | BD12: 0 | BE12: 0 | BF12: 0 | BG12: 0 | BH12: 0 | BI12: 0 | BJ12: 0 | BK12: 0 | BL12: 0 | BM12: 0 | BN12: 0 | BO12: 0 | BP12: 0 | BQ12: 0 | BR12: 0 | BS12: 0 | BT12: 0 | BU12: 0 | BV12: 0
A13: Gross Profit, Adj | B13: GROSS_PROFIT | C13: — | D13: — | E13: — | F13: — | G13: — | I13: 5557.1782 | J13: 5787.6468 | O13: Dividend per Share | P13: DIVIDEND_PER_SHARE_1_YEAR_GROWTH | Q13: 11.2069 | R13: -0.7752 | S13: 9.375 | T13: 2.1429 | U13: 6.2937 | V13: 3.9474 | W13: 11.3924 | X13: 4.5455 | Y13: 13.0435 | Z13: 3.8462 | AA13: 11.1111 | AB13: 0 | AC13: 0 | AD13: -33.3333 | AE13: -50 | AF13: 0 | AG13: 0 | AH13: 7.5 | AI13: 53.4884 | AJ13: 63.6364 | AK13: 42.5926 | AL13: 14.2857 | AM13: 12.5 | AN13: 36.3636 | AO13: 20 | AP13: 9.2593 | AQ13: 6.7797 | AR13: 11.1111 | AS13: 2.8571 | AT13: 8.3333 | AU13: 12.8205 | AV13: 227.2727 | AW13: -87.9167 | AX13: 220.6896 | AY13: 7.5269 | BA13: Weight of Pref. Equity | BB13: WACC_WEIGHT_OF_PREFERRED_EQUITY | BC13: 0 | BD13: 0 | BE13: 0 | BF13: 0 | BG13: 0 | BH13: 0 | BI13: 0 | BJ13: 0 | BK13: 0 | BL13: 0 | BM13: 0 | BN13: 0 | BO13: 0 | BP13: 0 | BQ13: 0 | BR13: 0 | BS13: 0 | BT13: 0 | BU13: 0 | BV13: 0
A14: Margin % | B14: GROSS_PROFIT | C14: — | D14: — | E14: — | F14: — | G14: — | I14: 38.026 | J14: 38.595 | BA14: WACC | BB14: WACC | BC14: 7.3055 | BD14: 8.5516 | BE14: 8.2089 | BF14: 7.4443 | BG14: 9.8254 | BH14: 8.8002 | BI14: 8.3721 | BJ14: 8.158 | BK14: 8.2549 | BL14: 9.0653 | BM14: 8.7373 | BN14: 9.7072 | BO14: 11.7766 | BP14: 9.2292 | BQ14: 7.9406 | BR14: 9.5636 | BS14: 9.6938 | BT14: 8.6572 | BU14: 6.7802 | BV14: 6.6139
A15: EBITDA, Adj | B15: EBITDA | C15: 6046 | D15: 6269 | E15: 5792 | F15: 6649 | G15: 7394 | H15: 7206 | I15: 7149.182 | J15: 7417.5 | O15: Accounts Receivable | P15: ACCOUNTS_RECEIVABLE_GROWTH | Q15: 2.2831 | R15: -28.0134 | S15: 12.8682 | T15: 0 | U15: -16.8956 | V15: 10.4132 | W15: 5.6886 | X15: 17.847 | Y15: 7.4519 | Z15: 10.4027 | AA15: -9.0172 | AB15: 26.392 | AC15: -25.1101 | AD15: 3.2941 | AE15: -8.9977 | AF15: 45.5569 | AG15: -0.3439 | AH15: 3.7101 | AI15: -2.3295 | AJ15: 0 | AK15: -5.707 | AL15: -10.1174 | AM15: -0.201 | AN15: 0.7049 | AO15: -3.8 | AP15: 9.3555 | AQ15: 7.3194 | AR15: -13.0204 | AS15: -4.4807 | AT15: 3.4115 | AU15: 4.1237 | AV15: -2.3762 | AW15: -7.5051 | AX15: 25.8772 | AY15: 14.3728
A16: Margin % | B16: EBITDA | C16: 49.355102 | D16: 52.517383 | E16: 54.729283 | F16: 53.098547 | G16: 49.781189 | H16: 48.997076 | I16: 48.919575 | J16: 49.463698 | O16: Inventory | P16: INVENTORY_GROWTH | Q16: -33.6088 | R16: -1.6598 | S16: 8.4388 | T16: -19.8444 | U16: -8.2524 | V16: 5.291 | W16: 6.0302 | X16: 4.2654 | Y16: 4.0909 | Z16: -0.8734 | AA16: -0.8811 | AB16: -2.2222 | AC16: 11.3636 | AD16: -15.9184 | AE16: -12.6214 | AF16: -5.5556 | AG16: -2.9412 | AH16: 20.6061 | AI16: 2.5126 | AJ16: 17.6471 | AK16: -9.5833 | AL16: -6.4516 | AM16: 7.3892 | AN16: 10.0917 | AO16: 14.1667 | AP16: -8.0292 | AQ16: 8.3333 | AR16: 28.2051 | AS16: 16.2857 | AT16: -8.5995 | AU16: -29.3011 | AV16: -0.7605 | AW16: 15.7088 | AX16: 12.2517 | AY16: 0.59 | BA16: Capital Structure | BV16: {=GEOMEAN(BC15:BR15/100+1)-1} -> 0
A17: Net Income, Adj | B17: EARN_FOR_COMMON | C17: 3200.34 | D17: 3198.09 | E17: 2737.35 | F17: 3378.34 | G17: 3907.98 | H17: 3750.01 | I17: 3695.192 | J17: 3837.577 | O17: Fixed Assets | P17: NET_FIXED_ASSETS_1_YEAR_GROWTH | Q17: -5.2253 | R17: 0.218 | S17: 3.5122 | T17: 1.8617 | U17: 4.5102 | V17: 1.4291 | W17: 2.373 | X17: 2.2908 | Y17: 5.3908 | Z17: 4.1996 | AA17: 1.9265 | AB17: -3.0684 | AC17: 3.1411 | AD17: 2.6103 | AE17: 2.4206 | AF17: 3.3419 | AG17: 45.2658 | AH17: 1.093 | AI17: 3.7693 | AJ17: 4.096 | AK17: 4.169 | AL17: 1.6573 | AM17: 3.1868 | AN17: 4.9372 | AO17: 4.3085 | AP17: 4.7639 | AQ17: 4.7378 | AR17: 5.5626 | AS17: 3.2346 | AT17: 1.9711 | AU17: 0.7367 | AV17: 2.1939 | AW17: 0.6606 | AX17: 1.8228 | AY17: 3.6729 | BA17: + Historical Market Cap | BB17: HISTORICAL_MARKET_CAP | BC17: 64016.05 | BD17: 82787.191 | BE17: 207598.52 | BF17: 55968.362 | BG17: 50833.523 | BH17: 48950.704 | BI17: 33349.507 | BJ17: 25228.881 | BK17: 36371.558 | BL17: 28540.649 | BM17: 19828.024 | BN17: 22095.246 | BO17: 23905.7 | BP17: 19807.2 | BQ17: 12301.569 | BR17: 18056.139 | BS17: 15072.215 | BT17: 11078.166 | BU17: 8638.4023 | BV17: 7669.4319
A18: Margin % | B18: EARN_FOR_COMMON | C18: 26.125224 | D18: 26.791405 | E18: 25.865539 | F18: 26.979237 | G18: 26.311048 | H18: 25.49813 | I18: 25.285022 | J18: 25.590934 | O18: Total Assets | P18: ASSET_GROWTH | Q18: -1.5494 | R18: -5.5888 | S18: 4.1145 | T18: -0.0469 | U18: 1.9612 | V18: 2.8431 | W18: 2.2653 | X18: 4.0659 | Y18: 18.7859 | Z18: 17.6363 | AA18: 2.3551 | AB18: 1.4344 | AC18: -1.1052 | AD18: 1.5129 | AE18: 0.7211 | AF18: 3.8614 | AG18: 13.0744 | AH18: -1.516 | AI18: 3.7017 | AJ18: 1.6117 | AK18: 2.9529 | AL18: 2.2786 | AM18: 4.664 | AN18: 4.2749 | AO18: 4.1814 | AP18: 3.9613 | AQ18: 3.9991 | AR18: 5.1191 | AS18: 1.9255 | AT18: 0.9177 | AU18: 2.7701 | AV18: 4.1602 | AW18: 4.015 | AX18: 1.8546 | AY18: 3.4073 | BA18: + Short Term Debt | BB18: BS_ST_BORROW | BC18: 220 | BD18: 245 | BE18: 446 | BF18: 302 | BG18: 18 | BH18: 19 | BI18: 331 | BJ18: 20 | BK18: 228 | BL18: 533 | BM18: 780 | BN18: 507 | BO18: 613 | BP18: 113 | BQ18: 320 | BR18: 787 | BS18: 600 | BT18: 937 | BU18: 1084 | BV18: 428
A19: EPS, Adj | B19: IS_DIL_EPS_CONT_OPS | C19: 1.2383 | D19: 1.3345 | E19: 0.396 | F19: 1.5014 | G19: 1.8295 | H19: 1.83146 | I19: 1.833 | J19: 1.984 | O19: Modified Working Capital | P19: MODIFIED_WORK_CAP_GROWTH | Q19: -30.4167 | R19: -92.8144 | S19: — | T19: — | U19: — | V19: 53.271 | W19: 82 | X19: -666.6667 | Y19: 4.3478 | Z19: — | AA19: — | AB19: — | AC19: -89.8734 | AD19: 637.5 | AE19: 50 | AF19: 185.8757 | AG19: -10.2767 | AH19: -1.5419 | AI19: -9.6197 | AJ19: 8.4158 | AK19: -19.863 | AL19: -34.188 | AM19: -28.5714 | AN19: 34.5455 | AO19: 0 | AP19: 56.3063 | AQ19: 60.5187 | AR19: 1.9749 | AS19: -5.1056 | AT19: -8.1633 | AU19: -34.5455 | AV19: -37.037 | AW19: 98.5294 | AX19: 29.3827 | AY19: 0 | BA19: + Long Term Debt | BB19: BS_LT_BORROW | BC19: 18384 | BD19: 16663 | BE19: 16759 | BF19: 16486 | BG19: 14739 | BH19: 11790 | BI19: 10962 | BJ19: 10515 | BK19: 9514 | BL19: 9022 | BM19: 9052 | BN19: 8734 | BO19: 8051 | BP19: 7895 | BQ19: 7512 | BR19: 6470 | BS19: 5362 | BT19: 5093 | BU19: 6248 | BV19: 6886
A20: Growth %, YoY | B20: IS_DIL_EPS_CONT_OPS | C20: 65.458561 | D20: 7.7673784 | E20: -70.326001 | F20: 279.1498 | G20: 21.849002 | H20: 3.2091622 | I20: 0.19207581 | J20: 8.2378614 | O20: Working Capital | P20: WORK_CAP_GROWTH | Q20: — | R20: 0.9585 | S20: 6.7742 | T20: -62.9758 | U20: 8.811 | V20: 18.0442 | W20: -19.3182 | X20: -25.7143 | Y20: 35.1326 | Z20: 22.3358 | AA20: -15.7895 | AB20: -47.7273 | AC20: -35.6044 | AD20: 0.4052 | AE20: 45.891 | AF20: 53.8346 | AG20: -2.2801 | AH20: -93.3121 | AI20: — | AJ20: — | AK20: 92.7778 | AL20: — | AM20: -54.8936 | AN20: -22.0126 | AO20: -29.8387 | AP20: 2.2989 | AQ20: 161.236 | AR20: 90.9677 | AS20: -49.6622 | AT20: -95.302 | AU20: 2995.2381 | AV20: 73.3846 | AW20: 114.9068 | AX20: -32.2874 | AY20: -15.9756 | BA20: + Preferred Equity and Hybrid Capital | BB20: PFD_EQTY_HYBRID_CAPITAL | BC20: 0 | BD20: 0 | BE20: 0 | BF20: 0 | BG20: 0 | BH20: 0 | BI20: 0 | BJ20: 0 | BK20: 0 | BL20: 0 | BM20: 0 | BN20: 0 | BO20: 0 | BP20: 0 | BQ20: 0 | BR20: — | BS20: 0 | BT20: 0 | BU20: 0 | BV20: 0
O21: Employees | P21: EMPL_GROWTH | Q21: -3.3611 | R21: -1.6139 | S21: -3.1264 | T21: -2.9162 | U21: -4.6839 | V21: -1.124 | W21: -9.738 | X21: 10.6403 | Y21: 0.6681 | Z21: -0.8518 | AA21: -1.6286 | AB21: — | AC21: — | AD21: -3.8717 | AE21: — | AF21: — | AG21: -4.4488 | AH21: -2.3628 | AI21: 2.8571 | AJ21: -2.7778 | AK21: -2.8571 | AL21: -11.5059 | AM21: -0.2925 | AN21: 3.3333 | AO21: 3.2258 | AP21: -3.125 | AQ21: 3.2258 | AR21: -9.375 | AS21: -6.8966 | AT21: -11.1111 | AU21: -6.25 | AV21: -6.6667 | AW21: -8.181 | AX21: 8.4898 | AY21: 7.7585 | BA21: Total Capital | BB21: WACC_TOTAL_CAPITAL | BC21: 82620.05 | BD21: 99695.191 | BE21: 224803.52 | BF21: 72756.362 | BG21: 65590.523 | BH21: 60759.704 | BI21: 44642.507 | BJ21: 35763.881 | BK21: 46113.558 | BL21: 38095.649 | BM21: 29660.024 | BN21: 31336.246 | BO21: 32569.7 | BP21: 27815.2 | BQ21: 20133.569 | BR21: 25313.139 | BS21: 21034.214 | BT21: 17108.166 | BU21: 15970.402 | BV21: 14983.432
A22: Cash from Operations | B22: CF_CASH_FROM_OPER | C22: 4641 | D22: 4850 | E22: 4263 | F22: 5099 | G22: 5619 | H22: 5413 | O22: Accounts Payable | P22: ACCOUNTS_PAYABLE_GROWTH_1YR | Q22: 5.7971 | R22: 6.8493 | S22: 20.2797 | T22: -10.2713 | U22: -2.6998 | V22: 1.7758 | W22: 0.9815 | X22: 21.0583 | Y22: 6.066 | Z22: -0.841 | AA22: 3.1383 | AB22: -1.5625 | AC22: -9.858 | AD22: -10.4727 | AE22: -16.9772 | AF22: 3.1172 | AG22: 5.1995 | AH22: 9.6552 | AI22: 2.0964 | AJ22: 0.2053 | AK22: -0.3074 | AL22: -0.6166 | AM22: 8.1696 | AN22: -2.6769 | AO22: -0.3929 | AP22: -5.6213 | AQ22: -11.7032 | AR22: -9.5858 | AS22: 5.4974 | AT22: 5.0868 | AU22: 12.0425 | AV22: 9.9052 | AW22: -22.4353 | AX22: 19.0358 | AY22: 17.3416
A23: Capital Expenditures | B23: CAPITAL_EXPEND | C23: -1745 | D23: -1657 | E23: -1626 | F23: -1791 | G23: -2133 | H23: -2286 | I23: -2279.619 | J23: -2244.048 | O23: Short-Term Debt | P23: SHORT_TERM_DEBT_1_YEAR_GROWTH | Q23: 270.2786 | R23: -61.204 | S23: -23.0603 | T23: 11.4846 | U23: -46.2312 | V23: 44.8598 | W23: 65.4839 | X23: 23.5867 | Y23: -31.2303 | Z23: -18.578 | AA23: -19.1549 | AB23: 221.6028 | AC23: -0.2167 | AD23: 37.785 | AE23: -57.9196 | AF23: -19.8502 | AG23: 153.271 | AH23: -13.5609 | AI23: -35.9658 | AJ23: 31.1667 | AK23: -59.3393 | AL23: -64.6875 | AM23: 442.4779 | AN23: -17.292 | AO23: 53.8462 | AP23: -31.6667 | AQ23: -57.2233 | AR23: -91.2281 | AS23: 1555 | AT23: -94.2598 | AU23: -5.2632 | AV23: 1577.7778 | AW23: 47.6821 | AX23: -45.0673 | AY23: -10.2041 | BA23: EVA
A24: Free Cash Flow | B24: CF_FREE_CASH_FLOW | C24: 2896 | D24: 3193 | E24: 2637 | F24: 3308 | G24: 3486 | H24: 3127 | I24: 3130.927 | J24: 3480.17 | O24: Total Debt | P24: TOTAL_DEBT_1_YEAR_GROWTH | Q24: 21.3199 | R24: -24.527 | S24: 5.9856 | T24: -5.3223 | U24: 8.0262 | V24: -0.4626 | W24: -9.0619 | X24: -8.7831 | Y24: 66.9118 | Z24: 42.039 | AA24: -0.768 | AB24: 5.9533 | AC24: -5.4502 | AD24: 5.601 | AE24: -0.7738 | AF24: 3.7006 | AG24: 0.2461 | AH24: -17.7578 | AI24: -1.1277 | AJ24: 21.7209 | AK24: 7.9234 | AL24: 2.2472 | AM24: 8.1918 | AN24: 6.6597 | AO24: 6.3954 | AP24: -2.8173 | AQ24: 1.9571 | AR24: 8.14 | AS24: 7.1951 | AT24: 4.5692 | AU24: 24.964 | AV24: 13.763 | AW24: 2.4839 | AX24: -1.7262 | AY24: 10.0308 | BA24: + Net Op. Profit | BB24: WACC_NET_OPER_PROFIT | BC24: 5949 | BD24: 5536 | BE24: 4322 | BF24: 4927 | BG24: 4825 | BH24: 3753 | BI24: 3398 | BJ24: 3613 | BK24: 3693 | BL24: 3517 | BM24: 3496 | BN24: 3503 | BO24: 3086 | BP24: 2273 | BQ24: 2767 | BR24: 2287 | BS24: 2164 | BT24: 1562 | BU24: 1005 | BV24: 513
A25: Source: Bloomberg | O25: Total Equity | P25: TOTAL_EQUITY_1_YEAR_GROWTH | Q25: -32.3563 | R25: 0.3706 | S25: 0.568 | T25: -10.1384 | U25: -6.5053 | V25: 6.8908 | W25: 17.327 | X25: 13.6961 | Y25: 17.7511 | Z25: 15.4354 | AA25: 1.9771 | AB25: -2.1088 | AC25: 4.5344 | AD25: 1.7118 | AE25: 1.9771 | AF25: 3.3969 | AG25: 5.5478 | AH25: 16.7817 | AI25: 12.4214 | AJ25: -2.8741 | AK25: -7.3345 | AL25: 8.9463 | AM25: -0.7755 | AN25: -2.6667 | AO25: 6.3061 | AP25: 16.6852 | AQ25: 6.3976 | AR25: 4.4023 | AS25: 0.2228 | AT25: 25.8851 | AU25: -14.5438 | AV25: -5.6995 | AW25: 10.5117 | AX25: 2.9748 | AY25: -6.4815 | BA25: - Cash Op. Taxes | BB25: WACC_CASH_OPER_TAXES | BC25: 1202.3827 | BD25: 1106.9511 | BE25: 829.6816 | BF25: 862.1152 | BG25: 853.6169 | BH25: 849 | BI25: 852.7931 | BJ25: 874.2906 | BK25: 1115.7953 | BL25: 727.5065 | BM25: 730.7939 | BN25: 723.7755 | BO25: 694.7003 | BP25: 465.4708 | BQ25: 816.3312 | BR25: 841.3975 | BS25: 615.6638 | BT25: 625.7799 | BU25: -2051.2009 | BV25: -22.3333
O26: Capital | P26: GROWTH_IN_CAP | Q26: -10.7831 | R26: -13.2368 | S26: 3.1436 | T26: -7.7856 | U26: 0.7832 | V26: 2.9375 | W26: 3.6086 | X26: 3.4392 | Y26: 37.5317 | Z26: 28.4266 | AA26: 0.4945 | AB26: 2.1907 | AC26: -0.9864 | AD26: 3.7653 | AE26: 0.4989 | AF26: 3.558 | AG26: 2.7312 | AH26: -1.1242 | AI26: 6.5789 | AJ26: 6.9646 | AK26: -0.3889 | AL26: 5.6423 | AM26: 3.505 | AN26: 1.9869 | AO26: 6.3527 | AP26: 6.5042 | AQ26: 4.2824 | AR26: 6.143 | AS26: 3.5311 | AT26: 15.4131 | AU26: 3.0418 | AV26: 4.8067 | AW26: 5.8078 | AX26: 0.3068 | AY26: 2.6999 | BA26: + NOPAT | BB26: WACC_NOPAT | BC26: 4746.6173 | BD26: 4429.0489 | BE26: 3492.3184 | BF26: 4064.8848 | BG26: 3971.3831 | BH26: 2904 | BI26: 2545.2069 | BJ26: 2738.7094 | BK26: 2577.2047 | BL26: 2789.4935 | BM26: 2765.2061 | BN26: 2779.2245 | BO26: 2391.2997 | BP26: 1807.5292 | BQ26: 1950.6688 | BR26: 1445.6025 | BS26: 1548.3362 | BT26: 936.2201 | BU26: 3056.2009 | BV26: 535.3333
O27: Book Value per Share | P27: BVPS_GROWTH | Q27: -2.7611 | R27: 9.3674 | S27: 8.1205 | T27: -13.5072 | U27: -7.4974 | V27: 6.1532 | W27: 16.7366 | X27: 13.1284 | Y27: 14.2818 | Z27: 14.6819 | AA27: 2.5365 | AB27: -2.7026 | AC27: 7.3382 | AD27: 1.2596 | AE27: 1.5026 | AF27: 3.2123 | AG27: 5.3235 | AH27: 15.3506 | AI27: 12.0727 | AJ27: 4.2461 | AK27: -3.2205 | AL27: 8.0876 | AM27: 5.3911 | AN27: 2.9855 | AO27: 9.2907 | AP27: 17.9772 | AQ27: 8.2344 | AR27: 7.3054 | AS27: 4.2633 | AT27: 31.3331 | AU27: -7.0827 | AV27: -0.24 | AW27: -62.6126 | AX27: 220.9453 | AY27: -0.3578 | BA27: Total Invested Capital | BB27: WACC_TOTAL_INV_CAPITAL | BC27: 38983 | BD27: 37959 | BE27: 37841 | BF27: 36008 | BG27: 34486 | BH27: 33300 | BI27: 33077 | BJ27: 32078 | BK27: 30337 | BL27: 28869 | BM27: 27592 | BN27: 26118 | BO27: 24984 | BP27: 23919 | BQ27: 22849 | BR27: 22431 | BS27: 21523 | BT27: 20594 | BU27: 20902 | BV27: 18042
BA28: WACC | BB28: WACC | BC28: 7.3055 | BD28: 8.5516 | BE28: 8.2089 | BF28: 7.4443 | BG28: 9.8254 | BH28: 8.8002 | BI28: 8.3721 | BJ28: 8.158 | BK28: 8.2549 | BL28: 9.0653 | BM28: 8.7373 | BN28: 9.7072 | BO28: 11.7766 | BP28: 9.2292 | BQ28: 7.9406 | BR28: 9.5636 | BS28: 9.6938 | BT28: 8.6572 | BU28: 6.7802 | BV28: 6.6139
O29: Cash From Operations | P29: CASH_FLOW_GROWTH | Q29: -32.9198 | R29: 24.1677 | S29: -11.718 | T29: -2.5872 | U29: 8.4296 | V29: 2.4494 | W29: 37.8378 | X29: 18.175 | Y29: -8.1047 | Z29: 8.1944 | AA29: -35.8151 | AB29: 7.1 | AC29: -33.7068 | AD29: 16.4789 | AE29: 36.2757 | AF29: -28.6602 | AG29: 79.8507 | AH29: -23.2365 | AI29: 85.4054 | AJ29: 6.1224 | AK29: 33.4249 | AL29: -30.0275 | AM29: 59.9313 | AN29: 7.0531 | AO29: -15.6116 | AP29: 10.8961 | AQ29: 2.3263 | AR29: 0.8077 | AS29: -9.7626 | AT29: 14.173 | AU29: 33.6694 | AV29: 4.5033 | AW29: -12.1031 | AX29: 19.6106 | AY29: 10.1981 | BA29: - Capital Charge | BB29: WACC_CAPITAL_CHARGE | BC29: 2847.8995 | BD29: 3246.1049 | BE29: 3106.3292 | BF29: 2680.559 | BG29: 3388.3884 | BH29: 2930.4646 | BI29: 2769.2336 | BJ29: 2616.9094 | BK29: 2504.2848 | BL29: 2617.0651 | BM29: 2410.7886 | BN29: 2535.3354 | BO29: 2942.2646 | BP29: 2207.5388 | BQ29: 1814.3501 | BR29: 2145.2112 | BS29: 2086.3874 | BT29: 1782.8579 | BU29: 1417.1948 | BV29: 1193.2711
O30: Capital Expenditures | P30: TOT_CAP_EXPEND_GROWTH | Q30: 49.5695 | R30: 7.2368 | S30: -9.0491 | T30: -27.1501 | U30: 20.4861 | V30: -26.2248 | W30: 13.9323 | X30: 32.1143 | Y30: 5.7958 | Z30: -8.0131 | AA30: 31.4667 | AB30: 2.5693 | AC30: -39.8154 | AD30: 1.862 | AE30: 16.129 | AF30: -1.9444 | AG30: -2.7384 | AH30: 10.2913 | AI30: 44.2782 | AJ30: 8.1757 | AK30: -1.8613 | AL30: -18.046 | AM30: 29.0323 | AN30: 24.837 | AO30: 1.9155 | AP30: -1.1961 | AQ30: 5.8798 | AR30: 4.6141 | AS30: -6.4012 | AT30: -14.9291 | AU30: -14.4608 | AV30: -5.043 | AW30: -1.8709 | AX30: 10.1476 | AY30: 19.0955 | BA30: Economic Value Added | BB30: WACC_ECON_VALUE_ADDED | BC30: 1898.7178 | BD30: 1182.944 | BE30: 385.9893 | BF30: 1384.3258 | BG30: 582.9947 | BH30: -26.4646 | BI30: -224.0267 | BJ30: 121.7999 | BK30: 72.9199 | BL30: 172.4284 | BM30: 354.4175 | BN30: 243.8891 | BO30: -550.965 | BP30: -400.0096 | BQ30: 136.3186 | BR30: -699.6087 | BS30: -538.0512 | BT30: -846.6378 | BU30: 1639.0061 | BV30: -657.9377
O31: Net Change In Cash | P31: NET_CHANGE_IN_CASH_1_YEAR_GROWTH | Q31: — | R31: — | S31: — | T31: 88.8889 | U31: — | V31: — | W31: 56.5789 | X31: — | Y31: -12.7273 | Z31: — | AA31: -24.7863 | AB31: — | AC31: — | AD31: 66.3934 | AE31: 91.8699 | AF31: — | AG31: 33.7278 | AH31: — | AI31: — | AJ31: — | AK31: — | AL31: 19.6013 | AM31: -26.9444 | AN31: — | AO31: — | AP31: — | AQ31: — | AR31: — | AS31: 39.0244 | AT31: -708 | AU31: — | AV31: -78.1182 | AW31: 2071 | AX31: — | AY31: 68.427 | BA31: ROIC | BB31: WACC_RETURN_ON_INV_CAPITAL | BC31: 12.1761 | BD31: 11.668 | BE31: 9.2289 | BF31: 11.2888 | BG31: 11.5159 | BH31: 8.7207 | BI31: 7.6948 | BJ31: 8.5377 | BK31: 8.4953 | BL31: 9.6626 | BM31: 10.0218 | BN31: 10.641 | BO31: 9.5713 | BP31: 7.5569 | BQ31: 8.5372 | BR31: 6.4447 | BS31: 7.1939 | BT31: 4.5461 | BU31: 14.6216 | BV31: 2.9672
O32: Free Cash Flow | P32: FREE_CASH_FLOW_1_YEAR_GROWTH | Q32: — | R32: 26.6667 | S32: 0 | T32: — | U32: — | V32: — | W32: 132.4742 | X32: -8.8692 | Y32: -47.2019 | Z32: 99.5392 | AA32: — | AB32: 6.8894 | AC32: 54.4843 | AD32: 49.2611 | AE32: — | AF32: — | AG32: — | AH32: — | AI32: — | AJ32: -1.9093 | AK32: 185.6448 | AL32: -47.7853 | AM32: 131.8108 | AN32: -15.9747 | AO32: -49.33 | AP32: 57.686 | AQ32: -6.2893 | AR32: -9.6197 | AS32: -20.4208 | AT32: 122.7061 | AU32: 102.2346 | AV32: 10.2555 | AW32: -17.4131 | AX32: 25.4456 | AY32: 5.3809 | BA32: EVA Spread | BB32: WACC_EVA_SPREAD | BC32: 4.8706 | BD32: 3.1164 | BE32: 1.02 | BF32: 3.8445 | BG32: 1.6905 | BH32: -0.0795 | BI32: -0.6773 | BJ32: 0.3797 | BK32: 0.2404 | BL32: 0.5973 | BM32: 1.2845 | BN32: 0.9338 | BO32: -2.2053 | BP32: -1.6724 | BQ32: 0.5966 | BR32: -3.1189 | BS32: -2.4999 | BT32: -4.1111 | BU32: 7.8414 | BV32: -3.6467
O33: Cash Flow to Firm | P33: CASH_FLOW_TO_FIRM_1_YEAR_GROWTH | Q33: — | R33: — | S33: -9.3578 | T33: — | U33: — | V33: — | W33: 33.0147 | X33: 15.2637 | Y33: -7.6995 | Z33: 16.394 | AA33: -27.2717 | AB33: -9.3432 | AC33: -12.7258 | AD33: 8.4837 | AE33: 21.3293 | AF33: -22.395 | AG33: 57.7382 | AH33: -18.9131 | AI33: 66.4511 | AJ33: 4.779 | AK33: 32.4957 | AL33: -26.04 | AM33: 50.1543 | AN33: 6.5545 | AO33: -14.0165 | AP33: 9.831 | AQ33: 1.7239 | AR33: 0.6279 | AS33: -8.3022 | AT33: — | AU33: — | AV33: 5.5828 | AW33: -10.7219 | AX33: 16.7964 | AY33: 9.5494 | BA33: Source: Bloomberg | BC33: Right click to show data transparency (not supported for all values)
O34: Free Cash Flow to Firm | P34: FCF_TO_FIRM_1_YEAR_GROWTH | Q34: — | R34: — | S34: 4.3852 | T34: — | U34: — | V34: — | W34: 73.0784 | X34: -8.0246 | Y34: -34.4903 | Z34: 94.6433 | AA34: — | AB34: -136.5158 | AC34: — | AD34: 45.8919 | AE34: 41.8409 | AF34: -88.4367 | AG34: 1713.8476 | AH34: -61.7966 | AI34: 160.4462 | AJ34: -3.1976 | AK34: 122.6573 | AL34: -35.2864 | AM34: 81.0944 | AN34: -12.5271 | AO34: -37.7477 | AP34: 36.7211 | AQ34: -5.5999 | AR34: -7.251 | AS34: -12.5404 | AT34: — | AU34: — | AV34: 11.0568 | AW34: -14.6206 | AX34: 20.1624 | AY34: 5.1195
O36: 5 Year Growth
O37: Revenue | P37: GEO_GROW_NET_SALES | Q37: — | R37: — | S37: — | T37: — | U37: 1.6621 | V37: 3.3228 | W37: 4.4052 | X37: 5.0643 | Y37: 4.0573 | Z37: 3.9897 | AA37: 1.9949 | AB37: 1.5479 | AC37: -4.8527 | AD37: -5.0994 | AE37: -5.1538 | AF37: -5.174 | AG37: -4.9716 | AH37: 1.0215 | AI37: 3.3575 | AJ37: 4.2335 | AK37: 8.2669 | AL37: 2.3746 | AM37: 4.2976 | AN37: 4.2782 | AO37: 3.2266 | AP37: 1.334 | AQ37: 6.9806 | AR37: 2.1179 | AS37: -1.2625 | AT37: -0.5992 | AU37: 0.3698 | AV37: -1.1832 | AW37: -2.1717 | AX37: 2.4975 | AY37: 5.4195
O38: EBITDA | P38: GEO_GROW_EBITDA | Q38: — | R38: — | S38: — | T38: — | U38: 0.726 | V38: 1.5364 | W38: 6.5704 | X38: 9.5149 | Y38: 9.5913 | Z38: 8.7651 | AA38: 3.4564 | AB38: -7.9734 | AC38: -7.0865 | AD38: -5.9167 | AE38: -4.7982 | AF38: -7.9522 | AG38: 7.6982 | AH38: 11.1449 | AI38: 13.7346 | AJ38: 12.1149 | AK38: 25.9491 | AL38: 12.8976 | AM38: 11.0139 | AN38: 8.1496 | AO38: 7.4977 | AP38: 4.4252 | AQ38: 8.4677 | AR38: 3.5861 | AS38: 1.0743 | AT38: 2.1996 | AU38: 6.2581 | AV38: 6.0754 | AW38: 3.9886 | AX38: 8.656 | AY38: 8.6745
O39: Operating Income | P39: GEO_GROW_OPER_INC | Q39: — | R39: — | S39: — | T39: — | U39: 1.5175 | V39: 0.0879 | W39: 7.2305 | X39: 11.8858 | Y39: 12.2513 | Z39: 10.4055 | AA39: 4.357 | AB39: -14.1958 | AC39: -10.8436 | AD39: -8.862 | AE39: -6.5695 | AF39: -14.3781 | AG39: 11.7813 | AH39: 14.0006 | AI39: 17.4408 | AJ39: 14.8902 | AK39: 39.7116 | AL39: 17.8162 | AM39: 14.6541 | AN39: 10.1703 | AO39: 8.9111 | AP39: 4.6424 | AQ39: 9.7409 | AR39: 3.1377 | AS39: -0.4713 | AT39: 1.4773 | AU39: 6.9909 | AV39: 6.5639 | AW39: 4.0072 | AX39: 10.5427 | AY39: 10.1169
O40: Net Income to Common | P40: NET_INCOME_TO_COMMON_5_YR_GROWTH | Q40: — | R40: — | S40: — | T40: — | U40: -31.8449 | V40: 21.2481 | W40: 8.2322 | X40: 8.7123 | Y40: — | Z40: 109.0756 | AA40: 8.3867 | AB40: -68.5691 | AC40: -1.7773 | AD40: -19.2802 | AE40: -11.9025 | AF40: -14.4555 | AG40: 179.1476 | AH40: 15.1732 | AI40: 34.9214 | AJ40: 25.8022 | AK40: 40.8768 | AL40: 27.5174 | AM40: 6.4218 | AN40: 7.2049 | AO40: 6.8303 | AP40: 6.4182 | AQ40: 10.9998 | AR40: 4.7054 | AS40: -1.5802 | AT40: 24.0914 | AU40: 12.1684 | AV40: 11.5793 | AW40: 7.0479 | AX40: 17.1574 | AY40: -5.3008
O41: EPS Diluted | P41: 5Y_GEO_GROWTH_DILUTED_EPS | Q41: — | R41: — | S41: — | T41: — | U41: -26.404 | V41: 30.0525 | W41: 7.4978 | X41: 7.2175 | Y41: — | Z41: 108.2399 | AA41: 7.7272 | AB41: -68.2818 | AC41: -1.9082 | AD41: -19.009 | AE41: -11.7607 | AF41: -15.0566 | AG41: 173.1296 | AH41: 13.5491 | AI41: 32.5196 | AJ41: 24.6148 | AK41: 43.1827 | AL41: 30.6222 | AM41: 9.954 | AN41: 12.5808 | AO41: 12.4244 | AP41: 10.4499 | AQ41: 14.7902 | AR41: 8.1781 | AS41: 1.2619 | AT41: 27.3253 | AU41: 15.9781 | AV41: 16.7796 | AW41: -9.712 | AX41: 22.7299 | AY41: -0.4719
O42: EPS Diluted before XO | P42: 5Y_GEO_GROWTH_DILUTED_EPS_BEF_XO | Q42: — | R42: — | S42: — | T42: — | U42: — | V42: — | W42: 8.781 | X42: 10.1271 | Y42: — | Z42: 108.2399 | AA42: 7.7272 | AB42: -40.1105 | AC42: -21.4987 | AD42: -19.009 | AE42: -10.0543 | AF42: -24.1539 | AG42: 50.7739 | AH42: 29.3199 | AI42: 32.5196 | AJ42: 20.1344 | AK42: 63.318 | AL42: 24.9703 | AM42: 20.6383 | AN42: 12.5808 | AO42: 14.4049 | AP42: 8.4472 | AQ42: 15.1107 | AR42: 8.1781 | AS42: 1.2619 | AT42: 27.3253 | AU42: 15.9781 | AV42: 16.7796 | AW42: -9.712 | AX42: 22.7299 | AY42: -0.4719
O43: EPS Diluted before Abnormal | P43: GEO_GROW_DILUTED_EPS_CONT_OPS | Q43: — | R43: — | S43: — | T43: — | U43: — | V43: — | W43: 8.781 | X43: 10.1271 | Y43: — | Z43: 113.0505 | AA43: 2.943 | AB43: -45.4837 | AC43: -21.4354 | AD43: -19.009 | AE43: -13.7531 | AF43: -10.6335 | AG43: 65.6342 | AH43: 29.2157 | AI43: 32.5196 | AJ43: 22.0979 | AK43: 45.0512 | AL43: 24.9703 | AM43: 21.1831 | AN43: 12.5808 | AO43: 13.4218 | AP43: 7.7757 | AQ43: 15.5353 | AR43: 7.0437 | AS43: 1.1491 | AT43: 5.8541 | AU43: 15.9306 | AV43: 15.4061 | AW43: -9.3477 | AX43: 20.1362 | AY43: 19.5741
O44: Dividend per Share | P44: GEO_GROW_DVD_PER_SH | Q44: — | R44: — | S44: — | T44: — | U44: 5.5546 | V44: 4.139 | W44: 6.5763 | X44: 5.618 | Y44: 7.7818 | Z44: 7.2808 | AA44: 8.7203 | AB44: 6.3995 | AC44: 5.4578 | AD44: -5.112 | AE44: -18.0164 | AF44: -19.7258 | AG44: -19.7258 | AH44: -18.5563 | AI44: -3.7744 | AJ44: 21.9755 | AK44: 30.946 | AL44: 34.4902 | AM44: 35.7186 | AN44: 32.5452 | AO44: 24.5731 | AP44: 18.1127 | AQ44: 16.5188 | AR44: 16.2296 | AS44: 9.8561 | AT44: 7.6317 | AU44: 8.3244 | AV44: 35.5222 | AW44: -13.0447 | AX44: 9.1607 | AY44: 8.9977
O46: Accounts Receivable | P46: ACCOUNTS_RECEIVABLE_5_YR_GROWTH | Q46: — | R46: — | S46: — | T46: — | U46: -7.1354 | V46: -5.7039 | W46: 1.8237 | X46: 2.7066 | Y46: 4.1936 | Z46: 10.284 | AA46: 6.0962 | AB46: 9.9609 | AC46: 0.429 | AD46: -0.3605 | AE46: -4.1381 | AF46: 5.3078 | AG46: 0.4194 | AH46: 7.1759 | AI46: 5.9826 | AJ46: 8.0001 | AK46: -0.9821 | AL46: -3.0053 | AM46: -3.7482 | AN46: -3.1574 | AO46: -3.9049 | AP46: -1.014 | AQ46: 2.5591 | AR46: -0.2225 | AS46: -1.2719 | AT46: 0.1658 | AU46: -0.8115 | AV46: -2.6723 | AW46: -1.4681 | AX46: 4.1233 | AY46: 6.2426
O47: Inventory | P47: INVENTORY_5_YEAR_GROWTH | Q47: — | R47: — | S47: — | T47: — | U47: -12.2371 | V47: -3.7574 | W47: -2.2972 | X47: -3.0611 | Y47: 2.1395 | Z47: 3.732 | AA47: 2.4863 | AB47: 0.8389 | AC47: 2.1759 | AD47: -2.0947 | AE47: -4.5339 | AF47: -5.4518 | AG47: -5.5912 | AH47: -4.0738 | AI47: -0.1949 | AJ47: 5.9224 | AK47: 5.0031 | AL47: 4.2323 | AM47: 1.8405 | AN47: 3.3038 | AO47: 2.6852 | AP47: 3.0358 | AQ47: 6.1044 | AR47: 9.9315 | AS47: 11.1416 | AT47: 6.3062 | AU47: 0.8582 | AV47: -0.895 | AW47: -2.907 | AX47: -3.5902 | AY47: -1.7252
O48: Fixed Assets | P48: NET_FIXED_ASSETS_5_YEAR_GROWTH | Q48: — | R48: — | S48: — | T48: — | U48: 0.916 | V48: 2.2949 | W48: 2.7311 | X48: 2.4875 | Y48: 3.188 | Z48: 3.1266 | AA48: 3.2275 | AB48: 2.1061 | AC48: 2.2752 | AD48: 1.7298 | AE48: 1.38 | AF48: 1.6601 | AG48: 10.2275 | AH48: 9.7862 | AI48: 10.0331 | AJ48: 10.3908 | AK48: 10.5669 | AL48: 2.9485 | AM48: 3.3715 | AN48: 3.6031 | AO48: 3.6454 | AP48: 3.7635 | AQ48: 4.3849 | AR48: 4.8612 | AS48: 4.5187 | AT48: 4.046 | AU48: 3.2335 | AV48: 2.7271 | AW48: 1.7548 | AX48: 1.4749 | AY48: 1.8114
O49: Total Assets | P49: GEO_GROW_TOT_ASSET | Q49: — | R49: — | S49: — | T49: — | U49: -0.2766 | V49: 0.5978 | W49: 2.2184 | X49: 2.2089 | Y49: 5.7992 | Z49: 8.8688 | AA49: 8.7653 | AB49: 8.588 | AC49: 7.4867 | AD49: 4.1612 | AE49: 0.9769 | AF49: 1.2723 | AG49: 3.4968 | AH49: 3.4106 | AI49: 3.8528 | AJ49: 4.0358 | AK49: 3.8532 | AL49: 1.7897 | AM49: 3.0363 | AN49: 3.1499 | AO49: 3.6664 | AP49: 3.8687 | AQ49: 4.2158 | AR49: 4.3063 | AS49: 3.832 | AT49: 3.1731 | AU49: 2.9356 | AV49: 2.9675 | AW49: 2.7502 | AX49: 2.736 | AY49: 3.2379
O50: Modified Working Capital | P50: MODIFIED_WORKING_CPTL_5YR_GRWTH | Q50: — | R50: — | S50: — | T50: — | U50: — | V50: — | W50: — | X50: — | Y50: — | Z50: — | AA50: — | AB50: — | AC50: — | AD50: — | AE50: 38.2869 | AF50: — | AG50: 23.5036 | AH50: 94.6424 | AI50: 27.9086 | AJ50: 19.8671 | AK50: -7.0539 | AL50: -12.6403 | AM50: -18.0714 | AN50: -11.2856 | AO50: -12.7077 | AP50: -0.229 | AQ50: 19.2473 | AR50: 28.048 | AS50: 19.4118 | AT50: 17.3952 | AU50: -1.3623 | AV50: -18.1997 | AW50: -6.541 | AX50: -0.5629 | AY50: 1.1452
O51: Working Capital | P51: WORKING_CAPITAL_5_YEAR_GROWTH | Q51: — | R51: — | S51: — | T51: — | U51: — | V51: — | W51: — | X51: — | Y51: — | Z51: — | AA51: — | AB51: — | AC51: — | AD51: — | AE51: — | AF51: — | AG51: — | AH51: — | AI51: — | AJ51: — | AK51: — | AL51: — | AM51: — | AN51: — | AO51: — | AP51: — | AQ51: -7.9862 | AR51: 22.7997 | AS51: 12.5048 | AT51: -34.486 | AU51: 29.5683 | AV51: 19.3697 | AW51: 22.2228 | AX51: 29.6902 | AY51: 130.8905
O52: Employees | P52: EMPLOYEES_5_YEAR_GROWTH | Q52: — | R52: — | S52: — | T52: — | U52: -3.1453 | V52: -2.7009 | W52: -4.3637 | X52: -1.788 | Y52: -1.0733 | Z52: -0.2903 | AA52: -0.3923 | AB52: — | AC52: — | AD52: — | AE52: — | AF52: — | AG52: — | AH52: — | AI52: — | AJ52: — | AK52: -1.9489 | AL52: -3.442 | AM52: -3.036 | AN52: -2.9464 | AO52: -1.7763 | AP52: -1.8305 | AQ52: 1.2398 | AR52: -0.6757 | AS52: -2.7252 | AT52: -5.5912 | AU52: -6.2084 | AV52: -8.0792 | AW52: -7.8382 | AX52: -4.9755 | AY52: -1.2456
O53: Accounts Payable | P53: ACCOUNTS_PAYABLE_5_YEAR_GROWTH | Q53: — | R53: — | S53: — | T53: — | U53: 3.4896 | V53: 2.6906 | W53: 1.5371 | X53: 1.6682 | Y53: 5.127 | Z53: 5.5256 | AA53: 5.8066 | AB53: 5.2681 | AC53: -0.7608 | AD53: -4.069 | AE53: -7.4168 | AF53: -7.4206 | AG53: -6.1822 | AH53: -2.4325 | AI53: 0.1651 | AJ53: 4.0052 | AK53: 3.305 | AL53: 2.1366 | AM53: 1.8584 | AN53: 0.8876 | AO53: 0.7668 | AP53: -0.3311 | AQ53: -2.6612 | AR53: -6.0899 | AS53: -4.5629 | AT53: -3.5352 | AU53: -0.1678 | AV53: 4.3003 | AW53: 1.1512 | AX53: 3.6235 | AY53: 5.9349
O54: Short-Term Debt | P54: SHORT_TERM_DEBT_5_YEAR_GROWTH | Q54: — | R54: — | S54: — | T54: — | U54: -7.9037 | V54: -23.6646 | W54: 2.0281 | X54: 12.1719 | Y54: 1.8405 | Z54: 10.6529 | AA54: -1.53 | AB54: 12.4649 | AC54: 7.7542 | AD54: 23.8212 | AE54: 8.5082 | AF54: 8.3209 | AG54: 3.2679 | AH54: 0.3451 | AI54: -13.9129 | AJ54: 8.0654 | AK54: -5.6501 | AL54: -36.3776 | AM54: -8.1362 | AN54: -3.3123 | AO54: -0.1785 | AP54: 10.7428 | AQ54: 15.0724 | AR54: -49.5671 | AS54: -8.1744 | AT54: -52.4301 | AU54: -49.2181 | AV54: 5.7826 | AW54: 86.0634 | AX54: -5.8397 | AY54: 63.2051
O55: Total Debt | P55: TOTAL_DEBT_5_YEAR_GROWTH | Q55: — | R55: — | S55: — | T55: — | U55: -0.1497 | V55: -4.0245 | W55: -0.3789 | X55: -3.3244 | Y55: 8.2841 | Z55: 14.3775 | AA55: 14.3072 | AB55: 17.8548 | AC55: 18.7037 | AD55: 8.318 | AE55: 0.8194 | AF55: 1.7115 | AG55: 0.5914 | AH55: -2.1755 | AI55: -3.4552 | AJ55: 0.5719 | AK55: 1.378 | AL55: 1.7795 | AM55: 7.5178 | AN55: 9.1605 | AO55: 6.2617 | AP55: 4.0571 | AQ55: 3.998 | AR55: 3.988 | AS55: 4.0922 | AT55: 3.7324 | AU55: 9.0821 | AV55: 11.4988 | AW55: 10.3072 | AX55: 8.4068 | AY55: 9.5163
O56: Total Equity | P56: GEO_GROW_TOT_SHRHLDR_EQY | Q56: — | R56: — | S56: — | T56: — | U56: -10.519 | V56: -1.9442 | W56: 1.1654 | X56: 3.6786 | Y56: 9.4377 | Z56: 14.1504 | AA56: 13.0811 | AB56: 9.0584 | AC56: 7.2413 | AD56: 4.1461 | AE56: 1.5958 | AF56: 1.8772 | AG56: 3.4232 | AH56: 5.7404 | AI56: 7.8789 | AJ56: 6.8324 | AK56: 4.5166 | AL56: 5.1812 | AM56: 1.8091 | AN56: -1.0834 | AO56: 0.7196 | AP56: 5.4711 | AQ56: 4.9729 | AR56: 6.0463 | AS56: 6.6686 | AT56: 10.3366 | AU56: 3.6729 | AV56: 1.2003 | AW56: 2.3579 | AX56: 2.9139 | AY56: -3.0252
O57: Total Capital 5 Year Growth | P57: TOTAL_CAPITAL_5_YEAR_GROWTH | Q57: — | R57: — | S57: — | T57: — | U57: -5.7932 | V57: -3.059 | W57: 0.443 | X57: 0.5005 | Y57: 8.8652 | Z57: 14.2727 | AA57: 13.7251 | AB57: 13.4121 | AC57: 12.4246 | AD57: 6.2652 | AE57: 1.1795 | AF57: 1.789 | AG57: 1.8964 | AH57: 1.868 | AI57: 2.4146 | AJ57: 3.6997 | AK57: 2.8969 | AL57: 3.4736 | AM57: 4.4248 | AN57: 3.509 | AO57: 3.3903 | AP57: 4.7832 | AQ57: 4.512 | AR57: 5.0394 | AS57: 5.3556 | AT57: 7.0925 | AU57: 6.3869 | AV57: 6.4937 | AW57: 6.4264 | AX57: 5.755 | AY57: 3.3152
O58: Book Value per Share | P58: GEO_GROW_BOOK_VAL | Q58: — | R58: — | S58: — | T58: — | U58: -1.6546 | V58: 0.0858 | W58: 1.3996 | X58: 2.322 | Y58: 8.1854 | Z58: 12.9371 | AA58: 12.1569 | AB58: 8.1446 | AC58: 7.0142 | AD58: 4.4559 | AE58: 1.9364 | AF58: 2.0705 | AG58: 3.7015 | AH58: 5.2054 | AI58: 7.362 | AJ58: 7.9362 | AK58: 6.5559 | AL58: 7.1094 | AM58: 5.1925 | AN58: 3.4284 | AO58: 4.4106 | AP58: 8.6295 | AQ58: 8.6589 | AR58: 9.0508 | AS58: 9.3201 | AT58: 13.4118 | AU58: 8.123 | AV58: 6.3742 | AW58: -13.8497 | AX58: 7.874 | AY58: 2.0776
O60: Cash From Operations | P60: GEO_GROW_CASH_OPER_ACT | Q60: — | R60: — | S60: — | T60: — | U60: -4.929 | V60: 3.4739 | W60: 5.6581 | X60: 12.004 | Y60: 10.7054 | Z60: 10.6574 | AA60: 0.7778 | AB60: -4.1815 | AC60: -14.6433 | AD60: -10.4989 | AE60: -6.2716 | AF60: -4.2693 | AG60: 6.1881 | AH60: 9.3485 | AI60: 20.0019 | AJ60: 14.1473 | AK60: 29.3739 | AL60: 7.1149 | AM60: 24.0525 | AN60: 11.1478 | AO60: 6.1686 | AP60: 2.3133 | AQ60: 10.3936 | AR60: 0.6597 | AS60: -2.7223 | AT60: 3.3402 | AU60: 7.2735 | AV60: 7.7261 | AW60: 4.8135 | AX60: 10.8903 | AY60: 10.1072
O61: Free Cash Flow | P61: FREE_CASH_FLOW_5_YEAR_GROWTH | Q61: — | R61: — | S61: — | T61: — | U61: — | V61: — | W61: — | X61: — | Y61: 155.3207 | Z61: — | AA61: — | AB61: — | AC61: — | AD61: — | AE61: — | AF61: — | AG61: — | AH61: — | AI61: — | AJ61: — | AK61: — | AL61: 8.0621 | AM61: — | AN61: 23.2986 | AO61: 8.0395 | AP61: -4.0652 | AQ61: 7.8389 | AR61: -10.677 | AS61: -11.6429 | AT61: 18.8058 | AU61: 24.8677 | AV61: 28.9948 | AW61: 26.6892 | AX61: 38.7621 | AY61: 19.475
O62: Cash Flow to Firm | P62: CASH_FLOW_TO_FIRM_5_YEAR_GROWTH | Q62: — | R62: — | S62: — | T62: — | U62: — | V62: — | W62: — | X62: — | Y62: — | Z62: — | AA62: 3.6779 | AB62: -3.9746 | AC62: -9.1709 | AD62: -6.1883 | AE62: -5.4059 | AF62: -4.1701 | AG62: 7.0554 | AH62: 5.4925 | AI62: 14.9227 | AJ62: 11.6009 | AK62: 24.2024 | AL62: 6.7437 | AM62: 20.7423 | AN62: 10.4375 | AO62: 6.156 | AP62: 2.2467 | AQ62: 8.9769 | AR62: 0.5937 | AS62: -2.3824 | AT62: — | AU62: — | AV62: — | AW62: — | AX62: — | AY62: —
O63: Free Cash Flow to Firm | P63: FCF_TO_FIRM_5_YEAR_GROWTH | Q63: — | R63: — | S63: — | T63: — | U63: — | V63: — | W63: — | X63: — | Y63: — | Z63: — | AA63: — | AB63: — | AC63: — | AD63: — | AE63: — | AF63: — | AG63: — | AH63: 10.643 | AI63: 24.2399 | AJ63: 15.1007 | AK63: 107.9643 | AL63: 6.7745 | AM63: 45.7566 | AN63: 17.1816 | AO63: 7.2786 | AP63: -2.691 | AQ63: 4.9418 | AR63: -8.2029 | AS63: -8.2056 | AT63: — | AU63: — | AV63: — | AW63: — | AX63: — | AY63: —
O65: Sequential Growth
O66: Revenue | P66: REVENUE_SEQUENTIAL_GROWTH | Q66: -5.6074 | R66: 2.0153 | S66: 5.9393 | T66: 5.2529 | U66: 1.1348 | V66: 2.3586 | W66: 7.472 | X66: 9.3256 | Y66: 0.3046 | Z66: 0.8068 | AA66: -7.0897 | AB66: 5.1378 | AC66: -21.0506 | AD66: -0.9889 | AE66: 0.5179 | AF66: -7.1884 | AG66: 6.2649 | AH66: 7.1891 | AI66: 11.0002 | AJ66: 4.8505 | AK66: 12.2134 | AL66: -19.6713 | AM66: 17.6419 | AN66: 10.897 | AO66: -0.3306 | AP66: 2.2967 | AQ66: 5.3467 | AR66: -6.7724 | AS66: -6.2823 | AT66: 3.0626 | AU66: 7.3808 | AV66: -2.5551 | AW66: -11.3429 | AX66: 18.3218 | AY66: 18.6152
O67: EBITDA | P67: EBITDA_SEQUENTIAL_GROWTH | Q67: -4.378 | R67: -4.3605 | S67: -2.1277 | T67: 5.2019 | U67: 10.1107 | V67: -0.4692 | W67: 21.8182 | X67: 12.1614 | Y67: 5.5692 | Z67: 6.0224 | AA67: -22.5011 | AB67: -32.1591 | AC67: 17.6717 | AD67: 12.3843 | AE67: 12.4763 | AF67: -34.5158 | AG67: 48.7532 | AH67: 37.7457 | AI67: 26.1016 | AJ67: 4.6922 | AK67: 17.1647 | AL67: -13.9175 | AM67: 26.6309 | AN67: 10.6521 | AO67: 1.5744 | AP67: 1.3508 | AQ67: 4.0856 | AR67: 0.5877 | AS67: -2.1285 | AT67: 7.3561 | AU67: 23.138 | AV67: 3.1935 | AW67: -8.9247 | AX67: 21.8981 | AY67: 7.4476
O68: Operating Income | P68: OPERATING_INCOME_SEQ_GROWTH | Q68: 1.5642 | R68: -4.4004 | S68: -6.214 | T68: 4.7853 | U68: 12.9977 | V68: -5.3886 | W68: 34.9398 | X68: 15.9903 | Y68: 6.508 | Z68: 4.0079 | AA68: -28.6166 | AB68: -49.292 | AC68: 40.4887 | AD68: 18.882 | AE68: 17.7638 | AF68: -53.8598 | AG68: 92.3077 | AH68: 55 | AI68: 37.9355 | AJ68: 5.5192 | AK68: 22.695 | AL68: -17.9913 | AM68: 35.2863 | AN68: 12.9925 | AO68: -0.3746 | AP68: 0.4628 | AQ68: 4.0311 | AR68: -0.8027 | AS68: -5.4408 | AT68: 9.7669 | AU68: 30.8871 | AV68: 1.9717 | AW68: -12.145 | AX68: 28.2439 | AY68: 7.6689
O69: Net Income to Common | P69: NET_INCOME_TO_COMMON_SEQ_GROWTH | Q69: 0.7353 | R69: 220.438 | S69: -7.2893 | T69: -166.8305 | U69: — | V69: 1695 | W69: 81.6156 | X69: -5.2147 | Y69: 38.3495 | Z69: -6.5497 | AA69: -32.791 | AB69: -99.6276 | AC69: 28150 | AD69: -48.1416 | AE69: 44.7099 | AF69: -41.9811 | AG69: 37.8049 | AH69: 237.7581 | AI69: 14.4105 | AJ69: 1.9847 | AK69: 2.1707 | AL69: -16.2637 | AM69: 36.7454 | AN69: 18.682 | AO69: 0.2156 | AP69: 0.2152 | AQ69: 3.3816 | AR69: 2.1288 | AS69: -12.9131 | AT69: 219.3228 | AU69: -39.5247 | AV69: 0.6953 | AW69: -16.9919 | AX69: 36.745 | AY69: 10.1825
O70: EPS Diluted | P70: EPS_DILUTED_SEQUENTIAL_GROWTH | Q70: 5.6818 | R70: 366.6667 | S70: -4.3779 | T70: -165.0602 | U70: — | V70: 1721.0526 | W70: 80.0578 | X70: -5.618 | Y70: 34.6939 | Z70: -6.0606 | AA70: -32.5269 | AB70: -99.6016 | AC70: 26600 | AD70: -48.3146 | AE70: 44.2029 | AF70: -44.2211 | AG70: 36.9369 | AH70: 231.5789 | AI70: 11.9048 | AJ70: 6.0284 | AK70: 11.7057 | AL70: -13.4731 | AM70: 40.1384 | AN70: 25.9259 | AO70: 5.2941 | AP70: 2.2346 | AQ70: 4.918 | AR70: 4.1667 | AS70: -9.5 | AT70: 230.9392 | AU70: -35.8932 | AV70: 8.5938 | AW70: -71.223 | AX70: 320 | AY70: 16.0714
O71: EPS Diluted before XO | P71: EPS_DIL_BEF_EXTRAORD_SEQ_GRWTH | Q71: -111.8705 | R71: — | S71: -11.2469 | T71: -120.6612 | U71: — | V71: 1721.0526 | W71: 80.0578 | X71: -5.618 | Y71: 34.6939 | Z71: -6.0606 | AA71: -32.5269 | AB71: -90.4382 | AC71: 265.1921 | AD71: 57.4514 | AE71: 58.6957 | AF71: -71.2329 | AG71: 196.8254 | AH71: 69.5187 | AI71: 77.918 | AJ71: -2.8369 | AK71: 33.5766 | AL71: -22.1311 | AM71: 42.1053 | AN71: 25.9259 | AO71: 5.2941 | AP71: 2.2346 | AQ71: 4.918 | AR71: 4.1667 | AS71: -9.5 | AT71: 230.9392 | AU71: -35.8932 | AV71: 8.5938 | AW71: -71.223 | AX71: 320 | AY71: 16.0714
O72: EPS Diluted before Abnormal | P72: EPS_DILUTED_BEF_ABNRML_SEQ_GRWTH | Q72: -111.8705 | R72: — | S72: -11.2469 | T72: -120.6612 | U72: — | V72: 1721.0526 | W72: 80.0578 | X72: -5.618 | Y72: 34.6939 | Z72: 5.303 | AA72: -52.0384 | AB72: -92.5 | AC72: 486.6667 | AD72: 56.8182 | AE72: 44.2029 | AF72: -42.7136 | AG72: 64.0351 | AH72: 69.5187 | AI72: 77.918 | AJ72: -4.2553 | AK72: 35.5556 | AL72: -22.1311 | AM72: 45.3434 | AN72: 23.1204 | AO72: -0.625 | AP72: 5.0118 | AQ72: 10.2385 | AR72: -0.7736 | AS72: -7.2455 | AT72: 24.7399 | AU72: 65.4584 | AV72: 7.7674 | AW72: -70.326 | AX72: 279.1495 | AY72: 21.849
O73: Dividend per Share | P73: DPS_SEQUENTIAL_GROWTH | Q73: 11.2069 | R73: -0.7752 | S73: 9.375 | T73: 2.1429 | U73: 6.2937 | V73: 3.9474 | W73: 11.3924 | X73: 4.5455 | Y73: 13.0435 | Z73: 3.8462 | AA73: 11.1111 | AB73: 0 | AC73: 0 | AD73: -33.3333 | AE73: -50 | AF73: 0 | AG73: 0 | AH73: 7.5 | AI73: 53.4884 | AJ73: 63.6364 | AK73: 42.5926 | AL73: 14.2857 | AM73: 12.5 | AN73: 36.3636 | AO73: 20 | AP73: 9.2593 | AQ73: 6.7797 | AR73: 11.1111 | AS73: 2.8571 | AT73: 8.3333 | AU73: 12.8205 | AV73: 227.2727 | AW73: -87.9167 | AX73: 220.6896 | AY73: 7.5269
O75: Accounts Receivable | P75: ACCOUNTS_RECEIVABLE_SEQ_GROWTH | Q75: 2.2831 | R75: -28.0134 | S75: 12.8682 | T75: 0 | U75: -16.8956 | V75: 10.4132 | W75: 5.6886 | X75: 17.847 | Y75: 7.4519 | Z75: 10.4027 | AA75: -9.0172 | AB75: 26.392 | AC75: -25.1101 | AD75: 3.2941 | AE75: -8.9977 | AF75: 45.5569 | AG75: -0.3439 | AH75: 3.7101 | AI75: -2.3295 | AJ75: 0 | AK75: -5.707 | AL75: -10.1174 | AM75: -0.201 | AN75: 0.7049 | AO75: -3.8 | AP75: 9.3555 | AQ75: 7.3194 | AR75: -13.0204 | AS75: -4.4807 | AT75: 3.4115 | AU75: 4.1237 | AV75: -2.3762 | AW75: -7.5051 | AX75: 25.8772 | AY75: 14.3728
O76: Inventory | P76: INVENTORY_SEQUENTIAL_GROWTH | Q76: -33.6088 | R76: -1.6598 | S76: 8.4388 | T76: -19.8444 | U76: -8.2524 | V76: 5.291 | W76: 6.0302 | X76: 4.2654 | Y76: 4.0909 | Z76: -0.8734 | AA76: -0.8811 | AB76: -2.2222 | AC76: 11.3636 | AD76: -15.9184 | AE76: -12.6214 | AF76: -5.5556 | AG76: -2.9412 | AH76: 20.6061 | AI76: 2.5126 | AJ76: 17.6471 | AK76: -9.5833 | AL76: -6.4516 | AM76: 7.3892 | AN76: 10.0917 | AO76: 14.1667 | AP76: -8.0292 | AQ76: 8.3333 | AR76: 28.2051 | AS76: 16.2857 | AT76: -8.5995 | AU76: -29.3011 | AV76: -0.7605 | AW76: 15.7088 | AX76: 12.2517 | AY76: 0.59
O77: Fixed Assets | P77: FIXED_ASSETS_SEQUENTIAL_GROWTH | Q77: -5.2253 | R77: 0.218 | S77: 3.5122 | T77: 1.8617 | U77: 4.5102 | V77: 1.4291 | W77: 2.373 | X77: 2.2908 | Y77: 5.3908 | Z77: 4.1996 | AA77: 1.9265 | AB77: -3.0684 | AC77: 3.1411 | AD77: 2.6103 | AE77: 2.4206 | AF77: 3.3419 | AG77: 45.2658 | AH77: 1.093 | AI77: 3.7693 | AJ77: 4.096 | AK77: 4.169 | AL77: 1.6573 | AM77: 3.1868 | AN77: 4.9372 | AO77: 4.3085 | AP77: 4.7639 | AQ77: 4.7378 | AR77: 5.5626 | AS77: 3.2346 | AT77: 1.9711 | AU77: 0.7367 | AV77: 2.1939 | AW77: 0.6606 | AX77: 1.8228 | AY77: 3.6729
O78: Total Assets | P78: TOTAL_ASSETS_SEQUENTIAL_GROWTH | Q78: -1.5494 | R78: -5.5888 | S78: 4.1145 | T78: -0.0469 | U78: 1.9612 | V78: 2.8431 | W78: 2.2653 | X78: 4.0659 | Y78: 18.7859 | Z78: 17.6363 | AA78: 2.3551 | AB78: 1.4344 | AC78: -1.1052 | AD78: 1.5129 | AE78: 0.7211 | AF78: 3.8614 | AG78: 13.0744 | AH78: -1.516 | AI78: 3.7017 | AJ78: 1.6117 | AK78: 2.9529 | AL78: 2.2786 | AM78: 4.664 | AN78: 4.2749 | AO78: 4.1814 | AP78: 3.9613 | AQ78: 3.9991 | AR78: 5.1191 | AS78: 1.9255 | AT78: 0.9177 | AU78: 2.7701 | AV78: 4.1602 | AW78: 4.015 | AX78: 1.8546 | AY78: 3.4073
O79: Modified Working Capital | P79: MODIFIED_WORKING_CPTL_SEQ_GRWTH | Q79: -30.4167 | R79: -92.8144 | S79: -295.8333 | T79: — | U79: -1437.5 | V79: — | W79: — | X79: — | Y79: — | Z79: — | AA79: -365.7143 | AB79: — | AC79: -89.8734 | AD79: 637.5 | AE79: 50 | AF79: 185.8757 | AG79: -10.2767 | AH79: -1.5419 | AI79: -9.6197 | AJ79: 8.4158 | AK79: -19.863 | AL79: -34.188 | AM79: -28.5714 | AN79: 34.5455 | AO79: 0 | AP79: 56.3063 | AQ79: 60.5187 | AR79: 1.9749 | AS79: -5.1056 | AT79: -8.1633 | AU79: -34.5455 | AV79: -37.037 | AW79: 98.5294 | AX79: 29.3827 | AY79: 0
O80: Working Capital | P80: WORKING_CAPITAL_SEQ_GROWTH | Q80: -227.2358 | R80: — | S80: — | T80: — | U80: — | V80: — | W80: — | X80: — | Y80: — | Z80: — | AA80: — | AB80: — | AC80: — | AD80: — | AE80: — | AF80: — | AG80: — | AH80: — | AI80: — | AJ80: -220 | AK80: — | AL80: — | AM80: -54.8936 | AN80: -22.0126 | AO80: -29.8387 | AP80: 2.2989 | AQ80: 161.236 | AR80: 90.9677 | AS80: -49.6622 | AT80: -95.302 | AU80: 2995.2381 | AV80: 73.3846 | AW80: 114.9068 | AX80: -32.2874 | AY80: -15.9756
O81: Employees | P81: EMPLOYEES_SEQUENTIAL_GROWTH | Q81: -3.3611 | R81: -1.6139 | S81: -3.1264 | T81: -2.9162 | U81: -4.6839 | V81: -1.124 | W81: -9.738 | X81: 10.6403 | Y81: 0.6681 | Z81: -0.8518 | AA81: -1.6286 | AB81: — | AC81: — | AD81: -3.8717 | AE81: — | AF81: — | AG81: -4.4488 | AH81: -2.3628 | AI81: 2.8571 | AJ81: -2.7778 | AK81: -2.8571 | AL81: -11.5059 | AM81: -0.2925 | AN81: 3.3333 | AO81: 3.2258 | AP81: -3.125 | AQ81: 3.2258 | AR81: -9.375 | AS81: -6.8966 | AT81: -11.1111 | AU81: -6.25 | AV81: -6.6667 | AW81: -8.181 | AX81: 8.4898 | AY81: 7.7585
O82: Accounts Payable | P82: ACCOUNTS_PAYABLE_SEQ_GROWTH | Q82: 5.7971 | R82: 6.8493 | S82: 20.2797 | T82: -10.2713 | U82: -2.6998 | V82: 1.7758 | W82: 0.9815 | X82: 21.0583 | Y82: 6.066 | Z82: -0.841 | AA82: 3.1383 | AB82: -1.5625 | AC82: -9.858 | AD82: -10.4727 | AE82: -16.9772 | AF82: 3.1172 | AG82: 5.1995 | AH82: 9.6552 | AI82: 2.0964 | AJ82: 0.2053 | AK82: -0.3074 | AL82: -0.6166 | AM82: 8.1696 | AN82: -2.6769 | AO82: -0.3929 | AP82: -5.6213 | AQ82: -11.7032 | AR82: -9.5858 | AS82: 5.4974 | AT82: 5.0868 | AU82: 12.0425 | AV82: 9.9052 | AW82: -22.4353 | AX82: 19.0358 | AY82: 17.3416
O83: Short-Term Debt | P83: ST_DEBT_SEQUENTIAL_GROWTH | Q83: 270.2786 | R83: -61.204 | S83: -23.0603 | T83: 11.4846 | U83: -46.2312 | V83: 44.8598 | W83: 65.4839 | X83: 23.5867 | Y83: -31.2303 | Z83: -18.578 | AA83: -19.1549 | AB83: 221.6028 | AC83: -0.2167 | AD83: 37.785 | AE83: -57.9196 | AF83: -19.8502 | AG83: 153.271 | AH83: -13.5609 | AI83: -35.9658 | AJ83: 31.1667 | AK83: -59.3393 | AL83: -64.6875 | AM83: 442.4779 | AN83: -17.292 | AO83: 53.8462 | AP83: -31.6667 | AQ83: -57.2233 | AR83: -91.2281 | AS83: 1555 | AT83: -94.2598 | AU83: -5.2632 | AV83: 1577.7778 | AW83: 47.6821 | AX83: -45.0673 | AY83: -10.2041
O84: Total Debt | P84: TOTAL_DEBT_SEQUENTIAL_GROWTH | Q84: 21.3199 | R84: -24.527 | S84: 5.9856 | T84: -5.3223 | U84: 8.0262 | V84: -0.4626 | W84: -9.0619 | X84: -8.7831 | Y84: 66.9118 | Z84: 42.039 | AA84: -0.768 | AB84: 5.9533 | AC84: -5.4502 | AD84: 5.601 | AE84: -0.7738 | AF84: 3.7006 | AG84: 0.2461 | AH84: -17.7578 | AI84: -1.1277 | AJ84: 21.7209 | AK84: 7.9234 | AL84: 2.2472 | AM84: 8.1918 | AN84: 6.6597 | AO84: 6.3954 | AP84: -2.8173 | AQ84: 1.9571 | AR84: 8.14 | AS84: 7.1951 | AT84: 4.5692 | AU84: 24.964 | AV84: 13.763 | AW84: 2.4839 | AX84: -1.7262 | AY84: 10.0308
O85: Total Equity | P85: TOTAL_EQUITY_SEQUENTIAL_GROWTH | Q85: -32.3563 | R85: 0.3706 | S85: 0.568 | T85: -10.1384 | U85: -6.5053 | V85: 6.8908 | W85: 17.327 | X85: 13.6961 | Y85: 17.7511 | Z85: 15.4354 | AA85: 1.9771 | AB85: -2.1088 | AC85: 4.5344 | AD85: 1.7118 | AE85: 1.9771 | AF85: 3.3969 | AG85: 5.5478 | AH85: 16.7817 | AI85: 12.4214 | AJ85: -2.8741 | AK85: -7.3345 | AL85: 8.9463 | AM85: -0.7755 | AN85: -2.6667 | AO85: 6.3061 | AP85: 16.6852 | AQ85: 6.3976 | AR85: 4.4023 | AS85: 0.2228 | AT85: 25.8851 | AU85: -14.5438 | AV85: -5.6995 | AW85: 10.5117 | AX85: 2.9748 | AY85: -6.4815
O86: Capital | P86: TOTAL_CAPITAL_SEQUENTIAL_GROWTH | Q86: -10.7831 | R86: -13.2368 | S86: 3.1436 | T86: -7.7856 | U86: 0.7832 | V86: 2.9375 | W86: 3.6086 | X86: 3.4392 | Y86: 37.5317 | Z86: 28.4266 | AA86: 0.4945 | AB86: 2.1907 | AC86: -0.9864 | AD86: 3.7653 | AE86: 0.4989 | AF86: 3.558 | AG86: 2.7312 | AH86: -1.1242 | AI86: 6.5789 | AJ86: 6.9646 | AK86: -0.3889 | AL86: 5.6423 | AM86: 3.505 | AN86: 1.9869 | AO86: 6.3527 | AP86: 6.5042 | AQ86: 4.2824 | AR86: 6.143 | AS86: 3.5311 | AT86: 15.4131 | AU86: 3.0418 | AV86: 4.8067 | AW86: 5.8078 | AX86: 0.3068 | AY86: 2.6999
O87: Book Value per Share | P87: BPS_SEQUENTIAL_GROWTH | Q87: -2.7611 | R87: 9.3674 | S87: 8.1205 | T87: -13.5072 | U87: -7.4974 | V87: 6.1532 | W87: 16.7366 | X87: 13.1284 | Y87: 14.2818 | Z87: 14.6819 | AA87: 2.5365 | AB87: -2.7026 | AC87: 7.3382 | AD87: 1.2596 | AE87: 1.5026 | AF87: 3.2123 | AG87: 5.3235 | AH87: 15.3506 | AI87: 12.0727 | AJ87: 4.2461 | AK87: -3.2205 | AL87: 8.0876 | AM87: 5.3911 | AN87: 2.9855 | AO87: 9.2907 | AP87: 17.9772 | AQ87: 8.2344 | AR87: 7.3054 | AS87: 4.2633 | AT87: 31.3331 | AU87: -7.0827 | AV87: -0.24 | AW87: -62.6126 | AX87: 220.9453 | AY87: -0.3578
O89: Cash From Operations | P89: CFO_SEQUENTIAL_GROWTH | Q89: -32.9198 | R89: 24.1677 | S89: -11.718 | T89: -2.5872 | U89: 8.4296 | V89: 2.4494 | W89: 37.8378 | X89: 18.175 | Y89: -8.1047 | Z89: 8.1944 | AA89: -35.8151 | AB89: 7.1 | AC89: -33.7068 | AD89: 16.4789 | AE89: 36.2757 | AF89: -28.6602 | AG89: 79.8507 | AH89: -23.2365 | AI89: 85.4054 | AJ89: 6.1224 | AK89: 33.4249 | AL89: -30.0275 | AM89: 59.9313 | AN89: 7.0531 | AO89: -15.6116 | AP89: 10.8961 | AQ89: 2.3263 | AR89: 0.8077 | AS89: -9.7626 | AT89: 14.173 | AU89: 33.6694 | AV89: 4.5033 | AW89: -12.1031 | AX89: 19.6106 | AY89: 10.1981
O90: Capital Expenditures | P90: CAPEX_SEQUENTIAL_GROWTH | Q90: 49.5695 | R90: 7.2368 | S90: -9.0491 | T90: -27.1501 | U90: 20.4861 | V90: -26.2248 | W90: 13.9323 | X90: 32.1143 | Y90: 5.7958 | Z90: -8.0131 | AA90: 31.4667 | AB90: 2.5693 | AC90: -39.8154 | AD90: 1.862 | AE90: 16.129 | AF90: -1.9444 | AG90: -2.7384 | AH90: 10.2913 | AI90: 44.2782 | AJ90: 8.1757 | AK90: -1.8613 | AL90: -18.046 | AM90: 29.0323 | AN90: 24.837 | AO90: 1.9155 | AP90: -1.1961 | AQ90: 5.8798 | AR90: 4.6141 | AS90: -6.4012 | AT90: -14.9291 | AU90: -14.4608 | AV90: -5.043 | AW90: -1.8709 | AX90: 10.1476 | AY90: 19.0955
O91: Net Change In Cash | P91: NET_CHANGE_IN_CASH_SEQ_GROWTH | Q91: -155.1167 | R91: — | S91: -307.6923 | T91: — | U91: — | V91: -190.4762 | W91: — | X91: — | Y91: -12.7273 | Z91: -343.75 | AA91: — | AB91: — | AC91: -170.2495 | AD91: — | AE91: — | AF91: — | AG91: 33.7278 | AH91: -194.2478 | AI91: — | AJ91: -161.1842 | AK91: — | AL91: 19.6013 | AM91: -26.9444 | AN91: -293.5361 | AO91: — | AP91: -19300 | AQ91: — | AR91: -153.2468 | AS91: — | AT91: — | AU91: — | AV91: -78.1182 | AW91: 2071 | AX91: -140.9949 | AY91: —
O92: Free Cash Flow | P92: FREE_CASH_FLOW_SEQUENTIAL_GROWTH | Q92: -202.2727 | R92: — | S92: — | T92: — | U92: -5200 | V92: — | W92: 132.4742 | X92: -8.8692 | Y92: -47.2019 | Z92: 99.5392 | AA92: -210.6236 | AB92: — | AC92: — | AD92: — | AE92: — | AF92: -642.5532 | AG92: — | AH92: -106.25 | AI92: — | AJ92: -1.9093 | AK92: 185.6448 | AL92: -47.7853 | AM92: 131.8108 | AN92: -15.9747 | AO92: -49.33 | AP92: 57.686 | AQ92: -6.2893 | AR92: -9.6197 | AS92: -20.4208 | AT92: 122.7061 | AU92: 102.2346 | AV92: 10.2555 | AW92: -17.4131 | AX92: 25.4456 | AY92: 5.3809
O93: Cash Flow to Firm | P93: CF_TO_FIRM_SEQUENTIAL_GROWTH | Q93: — | R93: — | S93: -9.3578 | T93: — | U93: — | V93: — | W93: 33.0147 | X93: 15.2637 | Y93: -7.6995 | Z93: 16.394 | AA93: -27.2717 | AB93: -9.3432 | AC93: -12.7258 | AD93: 8.4837 | AE93: 21.3293 | AF93: -22.395 | AG93: 57.7382 | AH93: -18.9131 | AI93: 66.4511 | AJ93: 4.779 | AK93: 32.4957 | AL93: -26.04 | AM93: 50.1543 | AN93: 6.5545 | AO93: -14.0165 | AP93: 9.831 | AQ93: 1.7239 | AR93: 0.6279 | AS93: -8.3022 | AT93: — | AU93: — | AV93: 5.5828 | AW93: -10.7219 | AX93: 16.7964 | AY93: 9.5494
O94: Free Cash Flow to Firm | P94: FCF_TO_FIRM_SEQUENTIAL_GROWTH | Q94: — | R94: — | S94: — | T94: — | U94: — | V94: — | W94: 73.0784 | X94: -8.0246 | Y94: -34.4903 | Z94: 94.6433 | AA94: -116.2681 | AB94: — | AC94: — | AD94: 45.8919 | AE94: 41.8409 | AF94: -88.4367 | AG94: 1713.8476 | AH94: -61.7966 | AI94: 160.4462 | AJ94: -3.1976 | AK94: 122.6573 | AL94: -35.2864 | AM94: 81.0944 | AN94: -12.5271 | AO94: -37.7477 | AP94: 36.7211 | AQ94: -5.5999 | AR94: -7.251 | AS94: -12.5404 | AT94: — | AU94: — | AV94: 11.0568 | AW94: -14.6206 | AX94: 20.1624 | AY94: 5.1195
O95: Source: Bloomberg | Q95: Right click to show data transparency (not supported for all values)

Sheet IS
A1: CSX Corp (CSX US) - BBG Adjusted
A3: In Millions of USD except Per Share | C3: FY 2018 | D3: FY 2019 | E3: FY 2020 | F3: FY 2021 | G3: FY 2022 | H3: Last 12M | I3: FY 2023 Est | J3: FY 2024 Est
A4: 12 Months Ending | C4: 12/31/2018 | D4: 12/31/2019 | E4: 12/31/2020 | F4: 12/31/2021 | G4: 12/31/2022 | H4: 09/30/2023 | I4: 12/31/2023 | J4: 12/31/2024
A5: Revenue | B5: SALES_REV_TURN | C5: 12250 | D5: 11937 | E5: 10583 | F5: 12522 | G5: 14853 | H5: 14707 | I5: 14614.154 | J5: 14995.846
A6: + Sales & Services Revenue | B6: IS_SALES_AND_SERVICES_REVENUES | C6: 11668 | D6: 10809 | E6: 9810 | F6: 11120 | G6: 12430 | H6: 12692
A7: + Other Revenue | B7: IS_OTHER_REVENUE | C7: 582 | D7: 1128 | E7: 773 | F7: 1402 | G7: 2423 | H7: 2015
A8: Gross Profit | B8: GROSS_PROFIT | C8: — | D8: — | E8: — | F8: — | G8: — | I8: 5557.1782 | J8: 5787.6468
A9: + Other Operating Income | B9: IS_OTHER_OPER_INC | C9: 96 | D9: 0 | E9: 0 | F9: 0 | G9: 0 | H9: 0
A10: - Operating Expenses | B10: IS_OPERATING_EXPN | C10: 7631 | D10: 7101 | E10: 6256 | F10: 7382 | G10: 9068 | H10: 9088
A11: + Research & Development | B11: IS_OPERATING_EXPENSES_RD | C11: 0 | D11: 0 | E11: 0 | F11: 0 | G11: 0
A12: + Depreciation & Amortization | B12: IS_DEPRECIATION_AND_AMORTIZATION | C12: 1331 | D12: 1349 | E12: 1383 | F12: 1420 | G12: 1500 | H12: 1587
A13: + Other Operating Expense | B13: IS_OTHER_OPERATING_EXPENSES | C13: 6300 | D13: 5752 | E13: 4873 | F13: 5962 | G13: 7568 | H13: 7501
A14: Operating Income (Loss) | B14: IS_OPER_INC | C14: 4715 | D14: 4836 | E14: 4327 | F14: 5140 | G14: 5785 | H14: 5619 | I14: 5555.68 | J14: 5758.5
A15: - Non-Operating (Income) Loss | B15: IS_NONOP_INCOME_LOSS | C15: 565 | D15: 649 | E15: 735 | F15: 643 | G15: 609 | H15: 654
A16: + Interest Expense, Net | B16: IS_NET_INTEREST_EXPENSE | C16: 607 | D16: 689 | E16: 754 | F16: 722 | G16: 742
A17: + Interest Expense | B17: IS_INT_EXPENSE | C17: 639 | D17: 737 | E17: 754 | F17: 722 | G17: 742 | H17: 804
A18: - Interest Income | B18: IS_INT_INC | C18: 32 | D18: 48 | E18: 0 | F18: 0 | G18: 0
A19: + Foreign Exch (Gain) Loss | B19: IS_FOREIGN_EXCH_LOSS | C19: 0 | D19: 0 | E19: 0 | F19: 0 | G19: 0
A20: + Other Non-Op (Income) Loss | B20: IS_OTHER_NON_OPERATING_INC_LOSS | C20: -42 | D20: -40 | E20: -19 | F20: -79 | G20: -133 | H20: -150
A21: Pretax Income (Loss), Adjusted | B21: PRETAX_INC | C21: 4150 | D21: 4187 | E21: 3592 | F21: 4497 | G21: 5176 | H21: 4965 | I21: 4886.12 | J21: 5064.36
A22: - Abnormal Losses (Gains) | B22: IS_ABNORMAL_ITEM | C22: -154 | D22: -129 | E22: -35 | F22: -454 | G22: -238 | H22: -81
A23: + Disposal of Assets | B23: IS_GAIN_LOSS_DISPOSAL_ASSETS | C23: -154 | D23: -151 | E23: -35 | F23: -454 | G23: -238 | H23: -81
A24: + Early Extinguishment of Debt | B24: IS_G_L_ON_EXT_DBT_OR_SETTLE_DBT | C24: — | D24: — | E24: — | F24: — | G24: —
A25: + Asset Write-Down | B25: IS_IMPAIRMENT_ASSETS | C25: — | D25: 22 | E25: — | F25: — | G25: —
A26: + Restructuring | B26: IS_RESTRUCTURING_EXPENSES | C26: — | D26: — | E26: — | F26: — | G26: —
A27: + Other Abnormal Items | B27: IS_OTHER_ONE_TIME_ITEMS | C27: — | D27: — | E27: — | F27: — | G27: —
A28: Pretax Income (Loss), GAAP | B28: PRETAX_INC | C28: 4304 | D28: 4316 | E28: 3627 | F28: 4951 | G28: 5414 | H28: 5046 | I28: 4886.12 | J28: 5064.36
A29: - Income Tax Expense (Benefit) | B29: IS_INC_TAX_EXP | C29: 995 | D29: 985 | E29: 862 | F29: 1170 | G29: 1248 | H29: 1199
A30: + Current Income Tax | B30: IS_CURRENT_INCOME_TAX_BENEFIT | C30: 716 | D30: 712 | E30: 682 | F30: 1003 | G30: 1131
A31: + Deferred Income Tax | B31: IS_DEFERRED_INCOME_TAX_BENEFIT | C31: 279 | D31: 273 | E31: 180 | F31: 167 | G31: 117
A32: + Tax Allowance/Credit | B32: IS_TAX_VALN_ALLOWNCE_CREDITS | C32: — | D32: — | E32: — | F32: — | G32: —
A33: Income (Loss) from Cont Ops | B33: IS_INC_BEF_XO_ITEM | C33: 3309 | D33: 3331 | E33: 2765 | F33: 3781 | G33: 4166 | H33: 3847 | I33: 3699.095 | J33: 3857.476
A34: - Net Extraordinary Losses (Gains) | B34: XO_GL_NET_OF_TAX | C34: 0 | D34: 0 | E34: 0 | F34: 0 | G34: 0 | H34: 0
A35: + Discontinued Operations | B35: IS_DISCONTINUED_OPERATIONS | C35: 0 | D35: 0 | E35: 0 | F35: 0 | G35: 0 | H35: 0
A36: + XO & Accounting Changes | B36: EXTRAORD_ITEMS_ACCOUNTING_CHANGS | C36: 0 | D36: 0 | E36: 0 | F36: 0 | G36: 0 | H36: 0
A37: Income (Loss) Incl. MI | B37: NI_INCLUDING_MINORITY_INT_RATIO | C37: 3309 | D37: 3331 | E37: 2765 | F37: 3781 | G37: 4166 | H37: 3847
A38: Net Income, GAAP | B38: NET_INCOME | C38: 3309 | D38: 3331 | E38: 2765 | F38: 3781 | G38: 4166 | H38: 3847 | I38: 3699.095 | J38: 3857.476
A39: - Preferred Dividends | B39: IS_TOT_CASH_PFD_DVD | C39: 0 | D39: 0 | E39: 0 | F39: 0 | G39: 0 | H39: 0
A40: - Other Adjustments | B40: OTHER_ADJUSTMENTS | C40: 1 | D40: 0 | E40: 0 | F40: 0 | G40: 0 | H40: 0
A41: Net Income Avail to Common, GAAP | B41: EARN_FOR_COMMON | C41: 3308 | D41: 3331 | E41: 2765 | F41: 3781 | G41: 4166 | H41: 3847 | I41: 3699.095 | J41: 3857.476
A43: Net Income Avail to Common, Adj | B43: EARN_FOR_COMMON | C43: 3200.34 | D43: 3198.09 | E43: 2737.35 | F43: 3378.34 | G43: 3907.98 | H43: 3750.01 | I43: 3695.192 | J43: 3837.577
A44: Net Abnormal Losses (Gains) | B44: IS_NET_ABNORMAL_ITEMS | C44: -107.66 | D44: -132.91 | E44: -27.65 | F44: -402.66 | G44: -258.02 | H44: -96.99
A45: Net Extraordinary Losses (Gains) | B45: XO_GL_NET_OF_TAX | C45: 0 | D45: 0 | E45: 0 | F45: 0 | G45: 0 | H45: 0
A47: Basic Weighted Avg Shares | B47: IS_AVG_NUM_SH_FOR_EPS | C47: 2571 | D47: 2389 | E47: 6900 | F47: 2250 | G47: 2136 | H47: 1994
A48: Basic EPS, GAAP | B48: IS_EPS | C48: 1.2867 | D48: 1.39 | E48: 0.4 | F48: 1.68 | G48: 1.95 | H48: 1.88 | I48: 1.833 | J48: 1.989
A49: Basic EPS from Cont Ops, GAAP | B49: IS_EARN_BEF_XO_ITEMS_PER_SH | C49: 1.2867 | D49: 1.39 | E49: 0.4 | F49: 1.68 | G49: 1.95 | H49: 1.88 | I49: 1.833 | J49: 1.989
A50: Basic EPS from Cont Ops, Adjusted | B50: IS_BASIC_EPS_CONT_OPS | C50: 1.2448 | D50: 1.3387 | E50: 0.3967 | F50: 1.5015 | G50: 1.8296 | H50: 1.839304 | I50: 1.833 | J50: 1.984
A52: Diluted Weighted Avg Shares | B52: IS_SH_FOR_DILUTED_EPS | C52: 2583 | D52: 2395 | E52: 6915 | F52: 2255 | G52: 2141 | H52: 1999
A53: Diluted EPS, GAAP | B53: IS_DILUTED_EPS | C53: 1.28 | D53: 1.39 | E53: 0.4 | F53: 1.68 | G53: 1.95 | H53: 1.88 | I53: 1.833 | J53: 1.989
A54: Diluted EPS from Cont Ops, GAAP | B54: IS_DIL_EPS_BEF_XO | C54: 1.28 | D54: 1.39 | E54: 0.4 | F54: 1.68 | G54: 1.95 | H54: 1.88 | I54: 1.833 | J54: 1.989
A55: Diluted EPS from Cont Ops, Adjusted | B55: IS_DIL_EPS_CONT_OPS | C55: 1.2383 | D55: 1.3345 | E55: 0.396 | F55: 1.5014 | G55: 1.8295 | H55: 1.83146 | I55: 1.833 | J55: 1.984
A57: Reference Items
A58: Accounting Standard | B58: ACCOUNTING_STANDARD | C58: US GAAP | D58: US GAAP | E58: US GAAP | F58: US GAAP | G58: US GAAP
A59: EBITDA | B59: EBITDA | C59: 6046 | D59: 6269 | E59: 5792 | F59: 6649 | G59: 7394 | H59: 7206 | I59: 7149.182 | J59: 7417.5
A60: EBITDA Margin (T12M) | B60: EBITDA_MARGIN | C60: 49.3551 | D60: 52.5174 | E60: 54.7293 | F60: 53.0985 | G60: 49.7812 | H60: 48.997076 | I60: 48.919575 | J60: 49.463698
A61: EBITA | B61: EBITA | C61: 4715 | D61: 4920 | E61: 4409 | F61: 5229 | G61: 5894
A62: EBIT | B62: EBIT | C62: 4715 | D62: 4836 | E62: 4327 | F62: 5140 | G62: 5785 | H62: 5619 | I62: 5555.68 | J62: 5758.5
A63: Gross Margin | B63: GROSS_MARGIN | C63: — | D63: — | E63: — | F63: — | G63: — | I63: 38.026 | J63: 38.595
A64: Operating Margin | B64: OPER_MARGIN | C64: 38.4898 | D64: 40.5127 | E64: 40.8863 | F64: 41.0478 | G64: 38.9484 | H64: 38.206296 | I64: 38.015748 | J64: 38.400634
A65: Profit Margin | B65: PROF_MARGIN | C65: 26.1334 | D65: 26.7914 | E65: 25.8655 | F65: 26.9792 | G65: 26.311 | H65: 25.49813 | I65: 25.285022 | J65: 25.590934
A66: Sales per Employee | B66: ACTUAL_SALES_PER_EMPL | C66: 544444.44 | D66: 568428.57 | E66: 548853.85 | F66: 598594.58 | G66: 658903.38 | H66: 646997.52
A67: Dividends per Share | B67: EQY_DPS | C67: 0.2933 | D67: 0.96 | E67: 0.116 | F67: 0.372 | G67: 0.4 | H67: 0.43 | I67: 0.442 | J67: 0.468
A68: Total Cash Common Dividends | B68: IS_TOT_CASH_COM_DVD | C68: 751 | D68: 2293.44 | E68: 800.4 | F68: 837 | G68: 854.4 | H68: 875.98
A69: Personnel Expenses | B69: IS_PERSONNEL_EXP | C69: 2738 | D69: 2616 | E69: 2275 | F69: 2550 | G69: 2861 | H69: 2942
A70: Depreciation Expense | B70: IS_DEPR_EXP | C70: 1331 | D70: 1349 | E70: 1383 | F70: 1420 | G70: 1500
A71: Rental Expense | B71: BS_CURR_RENTAL_EXPENSE | C71: 66 | D71: 84 | E71: 82 | F71: 89 | G71: 109
A72: Source: Bloomberg | C72: Right click to show data transparency (not supported for all values)

Sheet BS
A1: CSX Corp (CSX US) - Standardized
A3: In Millions of USD except Per Share | C3: FY 2018 | D3: FY 2019 | E3: FY 2020 | F3: FY 2021 | G3: FY 2022
A4: 12 Months Ending | C4: 12/31/2018 | D4: 12/31/2019 | E4: 12/31/2020 | F4: 12/31/2021 | G4: 12/31/2022
A5: Total Assets
A6: + Cash, Cash Equivalents & STI | B6: CASH_CASH_EQTY_STI_DETAILED | C6: 1111 | D6: 1954 | E6: 3131 | F6: 2316 | G6: 2087
A7: + Cash & Cash Equivalents | B7: BS_CASH_NEAR_CASH_ITEM | C7: 858 | D7: 958 | E7: 3129 | F7: 2239 | G7: 1958
A8: + ST Investments | B8: BS_MKT_SEC_OTHER_ST_INVEST | C8: 253 | D8: 996 | E8: 2 | F8: 77 | G8: 129
A9: + Accounts & Notes Receiv | B9: BS_ACCT_NOTE_RCV | C9: 1010 | D9: 986 | E9: 912 | F9: 1148 | G9: 1313
A10: + Accounts Receivable, Net | B10: BS_ACCTS_REC_EXCL_NOTES_REC | C10: 1010 | D10: 986 | E10: 912 | F10: 1148 | G10: 1313
A11: + Notes Receivable, Net | B11: NOTES_RECEIVABLE | C11: 0 | D11: 0 | E11: 0 | F11: 0 | G11: 0
A12: + Inventories | B12: BS_INVENTORIES | C12: 263 | D12: 261 | E12: 302 | F12: 339 | G12: 341
A13: + Other ST Assets | B13: OTHER_CURRENT_ASSETS_DETAILED | C13: 181 | D13: 77 | E13: 96 | F13: 70 | G13: 108
A14: + Derivative & Hedging Assets | B14: BS_DERIV_HEDGING_ASST_ST | C14: 0 | D14: 0 | E14: 0 | F14: 0 | G14: 0
A15: + Misc ST Assets | B15: BS_OTHER_CUR_ASSET_LESS_PREPAY | C15: 181 | D15: 77 | E15: 96 | F15: 70 | G15: 108
A16: Total Current Assets | B16: BS_CUR_ASSET_REPORT | C16: 2565 | D16: 3278 | E16: 4441 | F16: 3873 | G16: 3849
A17: + Property, Plant & Equip, Net | B17: BS_NET_FIX_ASSET | C17: 31998 | D17: 32700 | E17: 32916 | F17: 33516 | G17: 34747
... A30: Total Assets | B30: BS_TOT_ASSET | C30: 36729 | D30: 38257 | E30: 39793 | F30: 40531 | G30: 41912
A32: Liabilities & Shareholders' Equity
A33: + Payables & Accruals | B33: ACCT_PAYABLE_ACCRUALS_DETAILED | C33: 1718 | D33: 1701 | E33: 1454 | F33: 1845 | G33: 2092
A34: + Accounts Payable | B34: BS_ACCT_PAYABLE | C34: 949 | D34: 1043 | E34: 809 | F34: 963 | G34: 1130
A35: + Accrued Taxes | B35: BS_TAXES_PAYABLE | C35: 106 | D35: 69 | E35: 73 | F35: 134 | G35: 111
A36: + Interest & Dividends Payable | B36: INTEREST_DIVIDENDS_PAYABLE | C36: 0 | D36: 0 | E36: 0 | F36: 0 | G36: 0
A37: + Other Payables & Accruals | B37: BS_ACCRUAL | C37: 663 | D37: 589 | E37: 572 | F37: 748 | G37: 851
A38: + ST Debt | B38: BS_ST_BORROW | C38: 18 | D38: 302 | E38: 446 | F38: 245 | G38: 220
A39: + ST Borrowings | B39: SHORT_TERM_DEBT_DETAILED | C39: 0 | D39: 0 | E39: 0 | F39: 0 | G39: 0
A40: + ST Lease Liabilities | B40: ST_CAPITALIZED_LEASE_LIABILITIES | C40: 0 | D40: 57 | E40: 45 | F40: 64 | G40: 69
A41: + ST Finance Leases | B41: ST_CAPITAL_LEASE_OBLIGATIONS | C41: 0 | D41: 0 | E41: — | F41: — | G41: —
A42: + ST Operating Leases | B42: BS_ST_OPERATING_LEASE_LIABS | C42: — | D42: 57 | E42: 45 | F42: 64 | G42: 69
A43: + Current Portion of LT Debt | B43: BS_CURR_PORTION_LT_DEBT | C43: 18 | D43: 245 | E43: 401 | F43: 181 | G43: 151
A44: + Other ST Liabilities | B44: OTHER_CURRENT_LIABS_SUB_DETAILED | C44: 179 | D44: 148 | E44: 119 | F44: 143 | G44: 159
A45: + Deferred Revenue | B45: ST_DEFERRED_REVENUE | C45: 0 | D45: 0 | E45: 0 | F45: 0 | G45: 0
A46: + Derivatives & Hedging | B46: BS_DERIV_HEDGING_LIAB_ST | C46: 0 | D46: 0 | E46: 0 | F46: 0 | G46: 0
A47: + Misc ST Liabilities | B47: OTHER_CURRENT_LIABS_DETAILED | C47: 179 | D47: 148 | E47: 119 | F47: 143 | G47: 159
A48: Total Current Liabilities | B48: BS_CUR_LIAB | C48: 1915 | D48: 2151 | E48: 2019 | F48: 2233 | G48: 2471
A49: + LT Debt | B49: BS_LT_BORROW | C49: 14739 | D49: 16486 | E49: 16759 | F49: 16663 | G49: 18384
A50: + LT Borrowings | B50: LONG_TERM_BORROWINGS_DETAILED | C50: 14735 | D50: 15989 | E50: 16301 | F50: 16138 | G50: 17867
A51: + LT Lease Liabilities | B51: LT_CAPITALIZED_LEASE_LIABILITIES | C51: 4 | D51: 497 | E51: 458 | F51: 525 | G51: 517
A52: + LT Finance Leases | B52: LT_CAPITAL_LEASE_OBLIGATIONS | C52: 4 | D52: 4 | E52: 3 | F52: 47 | G52: 29
A53: + LT Operating Leases | B53: BS_LT_OPERATING_LEASE_LIABS | C53: — | D53: 493 | E53: 455 | F53: 478 | G53: 488
A54: + Other LT Liabilities | B54: OTHER_NONCUR_LIABS_SUB_DETAILED | C54: 7495 | D54: 7757 | E54: 7905 | F54: 8135 | G54: 8432
A55: + Accrued Liabilities | B55: BS_ACCRUED_LIABILITIES | C55: 211 | D55: 205 | E55: 224 | F55: 250 | G55: 292
A56: + Pension Liabilities | B56: PENSION_LIABILITIES | C56: 408 | D56: 402 | E56: 349 | F56: 244 | G56: 188
A57: + Deferred Revenue | B57: LT_DEFERRED_REVENUE | C57: 0 | D57: 0 | E57: 0 | F57: 0 | G57: 0
A58: + Deferred Tax Liabilities | B58: BS_DEFERRED_TAX_LIABILITIES_LT | C58: 6690 | D58: 6961 | E58: 7168 | F58: 7383 | G58: 7569
A59: + Derivatives & Hedging | B59: BS_DERIV_HEDGING_LIAB_LT | C59: 0 | D59: 0 | E59: 0 | F59: 0 | G59: 0
A60: + Misc LT Liabilities | B60: OTHER_NONCURRENT_LIABS_DETAILED | C60: 186 | D60: 189 | E60: 164 | F60: 258 | G60: 383
A61: Total Noncurrent Liabilities | B61: NON_CUR_LIAB | C61: 22234 | D61: 24243 | E61: 24664 | F61: 24798 | G61: 26816
A62: Total Liabilities | B62: BS_TOT_LIAB2 | C62: 24149 | D62: 26394 | E62: 26683 | F62: 27031 | G62: 29287
A63: + Preferred Equity and Hybrid Capital | B63: PFD_EQTY_HYBRID_CAPITAL | C63: 0 | D63: 0 | E63: 0 | F63: 0 | G63: 0
A64: + Share Capital & APIC | B64: BS_SH_CAP_AND_APIC | C64: 1067 | D64: 1119 | E64: 2440 | F64: 2268 | G64: 2640
A65: + Common Stock | B65: BS_COMMON_STOCK | C65: 818.18 | D65: 773.471 | E65: 2288 | F65: 2202 | G65: 2066
... A73: Total Liabilities & Equity | B73: TOT_LIAB_AND_EQY | C73: 36729 | D73: 38257 | E73: 39793 | F73: 40531 | G73: 41912
A75: Reference Items
A76: Accounting Standard | B76: ACCOUNTING_STANDARD | C76: US GAAP | D76: US GAAP | E76: US GAAP | F76: US GAAP | G76: US GAAP
A77: Shares Outstanding | B77: BS_SH_OUT | C77: 2454.54 | D77: 2320.413 | E77: 6862.761 | F77: 2201.787 | G77: 2066.367
A78: Number of Treasury Shares | B78: BS_NUM_OF_TSY_SH | C78: 0 | D78: 0 | E78: 0 | F78: 0 | G78: 0
A79: Pension Obligations | B79: BS_PENSION_RSRV | C79: 408 | D79: 402 | E79: 349 | F79: 244 | G79: 188
A80: Future Minimum Operating Lease Obligations | B80: BS_FUTURE_MIN_OPER_LEASE_OBLIG | C80: 1556 | D80: 1444 | E80: 1369 | F80: 1390 | G80: 1386
A81: Capital Leases - Total | B81: BS_TOTAL_CAPITAL_LEASES | C81: 4 | D81: 4 | E81: 3 | F81: 47 | G81: 29
A82: Options Granted During Period | B82: BS_OPTIONS_GRANTED | C82: 3.027 | D82: 3.561 | E82: 4.017 | F82: 2.005 | G82: 1.726
A83: Options Outstanding at Period End | B83: BS_OPTIONS_OUTSTANDING | C83: 14.019 | D83: 11.385 | E83: 12.651 | F83: 12.512 | G83: 13.4
A84: Net Debt | B84: NET_DEBT | C84: 13646 | D84: 14834 | E84: 14074 | F84: 14592 | G84: 16517
A85: Net Debt to Equity | B85: NET_DEBT_TO_SHRHLDR_EQTY | C85: 108.4738 | D85: 125.0443 | E85: 107.3532 | F85: 108.0889 | G85: 130.8277
A86: Tangible Common Equity Ratio | B86: TCE_RATIO | C86: 34.2046 | D86: 30.9695 | E86: 32.8165 | F86: 32.5324 | G86: 29.2514
A87: Current Ratio | B87: CUR_RATIO | C87: 1.3394 | D87: 1.5239 | E87: 2.1996 | F87: 1.7344 | G87: 1.5577
A88: Number of Employees | B88: NUM_OF_EMPLOYEES | C88: 22500 | D88: 21000 | E88: 19282 | F88: 20919 | G88: 22542
A89: Source: Bloomberg | C89: Right click to show data transparency (not supported for all values)

Sheet CF
A1: CSX Corp (CSX US) - Standardized
A3: In Millions of USD except Per Share | C3: FY 2018 | D3: FY 2019 | E3: FY 2020 | F3: FY 2021 | G3: FY 2022 | H3: Last 12M
A4: 12 Months Ending | C4: 12/31/2018 | D4: 12/31/2019 | E4: 12/31/2020 | F4: 12/31/2021 | G4: 12/31/2022 | H4: 09/30/2023
A5: Cash from Operating Activities
A6: + Net Income | B6: CF_NET_INC | C6: 3309 | D6: 3331 | E6: 2765 | F6: 3781 | G6: 4166 | H6: 3847
A7: + Depreciation & Amortization | B7: CF_DEPR_AMORT | C7: 1331 | D7: 1349 | E7: 1383 | F7: 1420 | G7: 1500 | H7: 1587
A8: + Non-Cash Items | B8: NON_CASH_ITEMS_DETAILED | C8: -7 | D8: 53 | E8: 113 | F8: -275 | G8: -138 | H8: 126
A9: + Deferred Income Taxes | B9: CF_DEF_INC_TAX | C9: 279 | D9: 273 | E9: 180 | F9: 167 | G9: 117 | H9: 103
A10: + Other Non-Cash Adj | B10: OTHER_NON_CASH_ADJ_LESS_DETAILED | C10: -286 | D10: -220 | E10: -67 | F10: -442 | G10: -255 | H10: 23
A11: + Chg in Non-Cash Work Cap | B11: CF_CHNG_NON_CASH_WORK_CAP | C11: 8 | D11: 117 | E11: 2 | F11: 173 | G11: 91 | H11: -147
A12: + (Inc) Dec in Accts Receiv | B12: CF_ACCT_RCV_UNBILLED_REV | C12: -46 | D12: 45 | E12: 83 | F12: -141 | G12: -101 | H12: -23
A13: + (Inc) Dec in Inventories | B13: CF_CHANGE_IN_INVENTORIES | C13: 0 | D13: 0 | E13: 0 | F13: 0 | G13: 0 | H13: 0
A14: + Inc (Dec) in Accts Payable | B14: CF_CHANGE_IN_ACCOUNTS_PAYABLE | C14: 104 | D14: 98 | E14: -20 | F14: 128 | G14: 140 | H14: 26
A15: + Inc (Dec) in Other | B15: INC_DEC_IN_OT_OP_AST_LIAB_DETAIL | C15: -50 | D15: -26 | E15: -61 | F15: 186 | G15: 52 | H15: -150
A16: + Net Cash From Disc Ops | B16: CF_NET_CASH_DISCONT_OPS_OPER | C16: 0 | D16: 0 | E16: 0 | F16: 0 | G16: 0 | H16: 0
A17: Cash from Operating Activities | B17: CF_CASH_FROM_OPER | C17: 4641 | D17: 4850 | E17: 4263 | F17: 5099 | G17: 5619 | H17: 5413
A19: Cash from Investing Activities
A20: + Change in Fixed & Intang | B20: FIXED_INTANG_ASST_CHANGE | C20: -1426 | D20: -1403 | E20: -1570 | F20: -1262 | G20: -1887 | H20: -2056
A21: + Disp in Fixed & Intang | B21: DISPOSAL_OF_FIXED_INTANG | C21: 319 | D21: 254 | E21: 56 | F21: 529 | G21: 246 | H21: 230
A22: + Disp of Fixed Prod Assets | B22: CF_DISPOSAL_OF_FIXED_PROD_ASSETS | C22: 319 | D22: 254 | E22: 56 | F22: 529 | G22: 246 | H22: 230
A23: + Disp of Intangible Assets | B23: CF_DISPOSAL_OF_INTANGIBLE_ASSETS | C23: 0 | D23: 0 | E23: 0 | F23: 0 | G23: 0 | H23: 0
A24: + Acq of Fixed & Intang | B24: ACQUIS_OF_FIXED_INTANG | C24: -1745 | D24: -1657 | E24: -1626 | F24: -1791 | G24: -2133 | H24: -2286
A25: + Acq of Fixed Prod Assets | B25: CF_PURCHASE_OF_FIXED_PROD_ASSETS | C25: -1745 | D25: -1657 | E25: -1626 | F25: -1791 | G25: -2133 | H25: -2286
A26: + Acq of Intangible Assets | B26: CF_ACQUISITION_OF_INTANG_ASSETS | C26: 0 | D26: 0 | E26: 0 | F26: 0 | G26: 0 | H26: 0
A27: + Net Change in LT Investment | B27: NET_CHG_IN_LT_INVEST_DETAILED | C27: 0 | D27: 0 | E27: 0 | F27: 0 | G27: 0 | H27: 0
A28: + Dec in LT Investment | B28: CF_DECR_INVEST | C28: 0 | D28: 0 | E28: 0 | F28: 0 | G28: 0 | H28: 0
A29: + Inc in LT Investment | B29: CF_INCR_INVEST | C29: 0 | D29: 0 | E29: 0 | F29: 0 | G29: 0 | H29: 0
A30: + Net Cash From Acq & Div | B30: CF_NT_CSH_RCVD_PD_FOR_ACQUIS_DIV | C30: 0 | D30: 0 | E30: 0 | F30: -541 | G30: -227 | H30: -35
A31: + Cash from Divestitures | B31: CF_CASH_FOR_DIVESTITURES | C31: 0 | D31: 0 | E31: 0 | F31: 0 | G31: 0 | H31: 0
... A36: Cash from Investing Activities | B36: CF_CASH_FROM_INV_ACT | C36: -1684 | D36: -2102 | E36: -649 | F36: -1877 | G36: -2131 | H36: -2042
A38: Cash from Financing Activities
A39: + Dividends Paid | B39: CF_DVD_PAID | C39: -751 | D39: -763 | E39: -797 | F39: -839 | G39: -852 | H39: -873
A40: + Cash From (Repayment) Debt | B40: PROC_FR_REPAYMNTS_BOR_DETAILED | C40: 2981 | D40: 1482 | E40: 255 | F40: -426 | G40: 1814 | H40: 442
A41: + Cash From (Repay) ST Debt | B41: CF_NET_CHG_ST_DEBT_CPTL_LEAS | C41: 0 | D41: 0 | E41: 0 | F41: 0 | G41: 0 | H41: 0
A42: + Cash From LT Debt | B42: CF_LT_DEBT_CAP_LEAS_PROCEEDS | C42: 3000 | D42: 2000 | E42: 1000 | F42: 0 | G42: 2000 | H42: 600
A43: + Repayments of LT Debt | B43: CF_LT_DEBT_CAP_LEAS_PAYMENT | C43: -19 | D43: -518 | E43: -745 | F43: -426 | G43: -186 | H43: -158
A44: + Cash (Repurchase) of Equity | B44: NET_CAP_STOCK | C44: -4671 | D44: -3373 | E44: -867 | F44: -2886 | G44: -4731 | H44: -3922
A45: + Increase in Capital Stock | B45: CF_INCR_CAP_STOCK | C45: 0 | D45: 0 | E45: 0 | F45: 0 | G45: 0 | H45: 0
A46: + Decrease in Capital Stock | B46: CF_DECR_CAP_STOCK | C46: -4671 | D46: -3373 | E46: -867 | F46: -2886 | G46: -4731 | H46: -3922
A47: + Other Financing Activities | B47: OTHER_FIN_AND_DEC_CAP | C47: -59 | D47: 6 | E47: -34 | F47: 39 | G47: 0 | H47: 31
A48: + Net Cash From Disc Ops | B48: CF_NET_CASH_DISCONTINUED_OPS_FIN | C48: 0 | D48: 0 | E48: 0 | F48: 0 | G48: 0 | H48: 0
A49: Cash from Financing Activities | B49: CFF_ACTIVITIES_DETAILED | C49: -2500 | D49: -2648 | E49: -1443 | F49: -4112 | G49: -3769 | H49: -4322
A51: Effect of Foreign Exchange Rates | B51: CF_EFFECT_FOREIGN_EXCHANGES | C51: 0 | D51: 0 | E51: 0 | F51: 0 | G51: 0 | H51: 0
A53: Net Changes in Cash | B53: CF_NET_CHNG_CASH | C53: 457 | D53: 100 | E53: 2171 | F53: -890 | G53: -281 | H53: -951
A55: Cash Paid for Taxes | B55: CF_CASH_PAID_FOR_TAX | C55: 814 | D55: 691 | E55: 664 | F55: 931 | G55: 1167
A56: Cash Paid for Interest | B56: CF_ACT_CASH_PAID_FOR_INT_DEBT | C56: 614 | D56: 717 | E56: 750 | F56: 718 | G56: 729
A58: Reference Items
A59: EBITDA | B59: EBITDA | C59: 6200 | D59: 6398 | E59: 5827 | F59: 7103 | G59: 7632 | H59: 7287
A60: Trailing 12M EBITDA Margin | B60: EBITDA_MARGIN | C60: 50.6122 | D60: 53.5981 | E60: 55.06 | F60: 56.7242 | G60: 51.3836 | H60: 49.547834
A61: Net Cash Paid for Acquisitions | B61: CF_NET_CASH_PAID_FOR_AQUIS | C61: — | D61: 0 | E61: 0 | F61: 541 | G61: 227 | H61: 35
A62: Free Cash Flow | B62: CF_FREE_CASH_FLOW | C62: 2896 | D62: 3193 | E62: 2637 | F62: 3308 | G62: 3486 | H62: 3127
A63: Free Cash Flow to Firm | B63: CF_FREE_CASH_FLOW_FIRM | C63: 3387.2758 | D63: 3761.8014 | E63: 3211.8029 | F63: 3859.3799 | G63: 4056.959 | H63: 3739.6004
A64: Free Cash Flow to Equity | B64: FREE_CASH_FLOW_EQUITY | C64: 6196 | D64: 4929 | E64: 2948 | F64: 3411 | G64: 5546 | H64: 3799
A65: Free Cash Flow per Basic Share | B65: FREE_CASH_FLOW_PER_SH | C65: 1.1264 | D65: 1.3365 | E65: 0.3822 | F65: 1.4702 | G65: 1.632 | H65: 1.5374861
A66: Price to Free Cash Flow | B66: PX_TO_FREE_CASH_FLOW | C66: 18.3858 | D66: 18.0466 | E66: 79.1524 | F66: 25.5744 | G66: 18.9826 | H66: 21.021328
A67: Cash Flow to Net Income | B67: CASH_FLOW_TO_NET_INC | C67: 1.4025 | D67: 1.456 | E67: 1.5418 | F67: 1.3486 | G67: 1.3488 | H67: 1.8510638
A68: Source: Bloomberg | C68: Right click to show data transparency (not supported for all values)

Sheet Graphs
C2: Terminal Growth Rate
C3: {=DCF!P26:T26} -> 0.01 | D3: 0.015 | E3: 0.02 | F3: 0.025 | G3: 0.03 | M3: 2020 | N3: 1397 | O3: 737 | P3: {=N3:N5} -> 1397 | Q3: {=O3:O5} -> 737
A4: WACC | B4: {=DCF!O27:O31} -> 0.083055 | C4: {=DCF!P27:T31} -> -14.5% / $27.03 | D4: -7.9% / $29.13 | E4: -0.2% / $31.57 | F4: 8.8% / $34.43 | G4: 19.6% / $37.82 | M4: 2021 | N4: 1790 | O4: 706 | P4: 1790 | Q4: 706
B5: 0.078055 | C5: -8.3% / $28.99 | D5: -0.7% / $31.42 | E5: 8.3% / $34.26 | F5: 19.0% / $37.64 | G5: 31.9% / $41.72 | M5: 2022 | N5: 2434 | O5: 690 | P5: 2434 | Q5: 690
B6: 0.073055 | C6: -1.2% / $31.26 | D6: 7.8% / $34.09 | E6: 18.4% / $37.46 | F6: 31.3% / $41.52 | G6: 47.1% / $46.53
B7: 0.068055 | C7: 7.3% / $33.93 | D7: 17.8% / $37.28 | E7: 30.6% / $41.32 | F7: 46.4% / $46.31 | G7: 66.3% / $52.60
B8: 0.063055 | C8: 17.3% / $37.09 | D8: 30.0% / $41.12 | E8: 45.7% / $46.08 | F8: 65.5% / $52.35 | G8: 91.3% / $60.51
P11: Merchandise | Q11: 55.5
P12: Intermodal | Q12: 15.5
P13: Trucking | Q13: 6.5
N14: 17 | P14: Other | Q14: 6.1
N15: 22.5 | P15: Coal | Q15: 16.4
N16: 23
N17: 24.5
N18: 24.5
N19: 27
N20: 36
I31: Metric | J31: Score | K31: Peer rank
I33: Environment | J33: 6.69 | K33: Leading
I34: Energy Management | J34: 7.45 | K34: Leading | N34: NAV valuation | P34: China | Q34: 12.5 | R34: 24 | S34: 32.5
I35: GHG Emission Management | J35: 5.69 | K35: Above Median | P35: North America | Q35: 15 | R35: 17 | S35: 23
P36: India | Q36: 4 | R36: 9 | S36: 13.5
I37: Social | J37: 5 | K37: Leading | P37: Europe | Q37: 7 | R37: 9 | S37: 12
I38: Operational Risk Management | J38: 4 | K38: Leading | P38: Russia | Q38: 5.5 | R38: 7.5 | S38: 8
I39: Occupational Health & Safety Management | J39: 4.93 | K39: Leading | P39: Japan | Q39: 3 | R39: 2.5 | S39: 3.5
I40: Ethics & Compliance | J40: 10 | K40: Leading
I41: Product Quality Management | J41: 3 | K41: Leading
I43: Governance | J43: 7.52 | K43: Leading
I44: Board Composition | J44: 7.13 | K44: Leading
I45: Executive Compensation | J45: 8.21 | K45: Leading
I46: Shareholder Rights | J46: 6.73 | K46: Below Median
I47: Audit | J47: 8.67 | K47: Leading
P55: 2023 | Q55: 2024 | R55: 2025 | S55: 2026 | T55: 2027
P56: 14614.154 | Q56: 14995.846 | R56: 16795 | S56: 19507.6 | T56: 18978.6 | V56: =P56-P57-P58 -> 4334.045 | W56: =Q56-Q57-Q58 -> 4098.176 | X56: =R56-R57-R58 -> 4257.9689 | Y56: =S56-S57-S58 -> 5651.5054 | Z56: =T56-T57-T58 -> 5293.7557
P57: 7149.182 | Q57: 7417.5 | R57: 8598.7811 | S57: 9849.8346 | T57: 9483.8043 | V57: =P57-P58 -> 4018.255 | W57: =Q57-Q58 -> 3937.33 | X57: =R57-R58 -> 4660.5311 | Y57: =S57-S58 -> 5843.5746 | Z57: =T57-T58 -> 5282.7643
P58: 3130.927 | Q58: 3480.17 | R58: 3938.25 | S58: 4006.26 | T58: 4201.04
N62: 274849.29 | O62: 2200
N63: 274849.29 | O63: 3100 | S63: REvenue per Carload | T63: Revenue | U63: Carload
N64: 274849.29 | O64: 2900 | R64: 2017.5 | S64: 3 | T64: 9 | U64: 3.9
N65: =AVERAGE(CCA!E20:E30)*1000000 -> 334299.08 | O65: =N65/100 -> 3342.9908 | R65: 2017.75 | S65: 2.5 | T65: -2 | U65: -5
N66: =AVERAGE(CCA!F20:F30)*1000000 -> 274849.29 | O66: =N66/100 -> 2748.4929 | R66: 2018 | S66: -2 | T66: -3.5 | U66: -1
R67: 2018.25 | S67: 1 | T67: 10 | U67: 9
R68: 2018.5 | S68: 8 | T68: 20 | U68: 10
R69: 2018.75 | S69: 7 | T69: 12 | U69: 5
R70: 2019 | S70: 1.5 | T70: 9 | U70: 7
R71: 2019.25 | S71: -4 | T71: -1 | U71: 2
R72: 2019.5 | S72: -3.5 | T72: -10 | U72: -7
R73: 2019.75 | S73: -5 | T73: -18 | U73: -15
R74: 2020 | S74: -11 | T74: -21 | U74: -13
R75: 2020.25 | S75: -8 | T75: -45 | U75: -40
R76: 2020.5 | S76: -11.5 | T76: -29 | U76: -23
R77: 2020.75 | S77: -5 | T77: -12 | U77: -6
R78: 2021 | S78: 0 | T78: -5 | U78: -5
... R87: 2023.25 | S87: -6 | T87: -2 | U87: 5

Sheet Rev. segments
A1: CSX Corp (CSX US) - By Measure
A3: In Millions of USD except Per Share | C3: FY 2013 | E3: FY 2014 | G3: FY 2015 | I3: FY 2016 | K3: FY 2017 | M3: FY 2018 | O3: FY 2019 | Q3: FY 2020 | S3: FY 2021 | U3: FY 2022
A4: 12 Months Ending | C4: 12/27/2013 | E4: 12/26/2014 | G4: 12/25/2015 | I4: 12/30/2016 | K4: 12/31/2017 | M4: 12/31/2018 | O4: 12/31/2019 | Q4: 12/31/2020 | S4: 12/31/2021 | U4: 12/31/2022
A5: Revenue | C5: 12026 | D5: 1 | E5: 12669 | F5: 1 | G5: 11811 | H5: 1 | I5: 11069 | J5: 1 | K5: 11408 | L5: 1 | M5: 12250 | N5: 1 | O5: 11937 | P5: 1 | Q5: 10583 | R5: 1 | S5: 12522 | T5: 1 | U5: 14853 | V5: 1
A6: Merchandise | C6: 7037 | D6: 0.58514884 | E6: 7608 | F6: 0.60052096 | G6: 7271 | H6: 0.61561256 | I6: 7142 | J6: 0.6452254 | K6: 7068 | L6: 0.61956522 | M6: 7491 | N6: 0.6115102 | O6: 7589 | P6: 0.63575438 | Q6: 7076 | R6: 0.66861948 | S6: 7539 | T6: 0.60206037 | U6: 8239 | V6: 0.55470275
A7: Chemicals | C7: 1896 | D7: 0.15765841 | E7: 2178 | F7: 0.1719157 | G7: 2284 | H7: 0.19337905 | I7: 2191 | J7: 0.19794019 | K7: 2210 | L7: 0.1937237 | M7: 2339 | N7: 0.19093878 | O7: 2349 | P7: 0.19678311 | Q7: 2309 | R7: 0.2181801 | S7: 2421 | T7: 0.19333972 | U7: 2584 | V7: 0.17397159
A8: Agriculture & Food Product | C8: — | E8: — | G8: 1345 | H8: 0.11387689 | I8: 1286 | J8: 0.11618032 | K8: 1262 | L8: 0.11062412 | M8: 1306 | N8: 0.10661224 | O8: 1410 | P8: 0.11812013 | Q8: 1386 | R8: 0.13096475 | S8: 1461 | T8: 0.11667465 | U8: 1664 | V8: 0.11203124
A9: Automotive | C9: 1217 | D9: 0.10119741 | E9: 1213 | F9: 0.095745521 | G9: 1175 | H9: 0.099483532 | I9: 1261 | J9: 0.11392176 | K9: 1195 | L9: 0.10475105 | M9: 1267 | N9: 0.10342857 | O9: 1236 | P9: 0.1035436 | Q9: 920 | R9: 0.086931872 | S9: 886 | T9: 0.07075547 | U9: 1054 | V9: 0.070962095
A10: Forest Products | C10: 775 | D10: 0.064443705 | E10: 819 | F10: 0.064645986 | G10: 796 | H10: 0.067394801 | I10: 773 | J10: 0.069834673 | K10: 755 | L10: 0.066181627 | M10: 850 | N10: 0.069387755 | O10: 870 | P10: 0.072882634 | Q10: 834 | R10: 0.078805632 | S10: 918 | T10: 0.073310973 | U10: 996 | V10: 0.06705716
A11: Metal & Equipment | C11: — | E11: — | G11: 723 | H11: 0.061214122 | I11: 704 | J11: 0.063601048 | K11: 703 | L11: 0.061623422 | M11: 769 | N11: 0.06277551 | O11: 742 | P11: 0.062159672 | Q11: 675 | R11: 0.063781536 | S11: 796 | T11: 0.06356812 | U11: 828 | V11: 0.055746314
A12: Minerals | C12: 432 | D12: 0.035922169 | E12: 459 | F12: 0.036230168 | G12: 459 | H12: 0.038862078 | I12: 464 | J12: 0.041918873 | K12: 477 | L12: 0.041812763 | M12: 518 | N12: 0.042285714 | O12: 559 | P12: 0.046829187 | Q12: 538 | R12: 0.050836247 | S12: 587 | T12: 0.046877496 | U12: 658 | V12: 0.044300815
A13: Fertilizers | C13: 527 | D13: 0.04382172 | E13: 534 | F13: 0.04215013 | G13: 489 | H13: 0.041402083 | I13: 463 | J13: 0.04182853 | K13: 466 | L13: 0.040848527 | M13: 442 | N13: 0.036081633 | O13: 423 | P13: 0.035436039 | Q13: 414 | R13: 0.039119342 | S13: 470 | T13: 0.03753394 | U13: 455 | V13: 0.030633542
A14: Housing and Construction | C14: 1471 | D14: 0.12231831 | E14: 1587 | F14: 0.1252664 | G14: 1255 | H14: 0.10625688 | I14: — | K14: — | M14: — | O14: — | Q14: — | S14: — | U14: —
A15: Waste & Equipment | C15: 264 | D15: 0.021952436 | E15: 309 | F15: 0.024390244 | G15: — | I15: — | K15: — | M15: — | O15: — | Q15: — | S15: — | U15: —
A16: Agricultural | C16: 1809 | D16: 0.15042408 | E16: 1929 | F16: 0.15226143 | G16: 1834 | H16: 0.15527898 | I16: — | K16: — | M16: — | O16: — | Q16: — | S16: — | U16: —
A17: Food and Consumer | C17: 269 | D17: 0.022368202 | E17: 265 | F17: 0.020917199 | G17: — | I17: — | K17: — | M17: — | O17: — | Q17: — | S17: — | U17: —
A18: Agriculture Products | C18: 1013 | D18: 0.084234159 | E18: 1130 | F18: 0.089194096 | G18: — | I18: — | K18: — | M18: — | O18: — | Q18: — | S18: — | U18: —
A19: Industrial | C19: 3757 | D19: 0.31240645 | E19: 4092 | F19: 0.32299313 | G19: 4182 | H19: 0.35407671 | I19: — | K19: — | M19: — | O19: — | Q19: — | S19: — | U19: —
A20: Metals | C20: 644 | D20: 0.05355064 | E20: 701 | F20: 0.055331913 | G20: — | I20: — | K20: — | M20: — | O20: — | Q20: — | S20: — | U20: —
A21: Coal | C21: 2895 | D21: 0.24072842 | E21: 2849 | F21: 0.22487963 | G21: 2300 | H21: 0.19473372 | I21: 1833 | J21: 0.16559761 | K21: 2107 | L21: 0.18469495 | M21: 2246 | N21: 0.18334694 | O21: 2070 | P21: 0.1734104 | Q21: 1397 | R21: 0.13200416 | S21: 1790 | T21: 0.14294841 | U21: 2434 | V21: 0.16387262
A22: Intermodal | C22: 1697 | D22: 0.14111093 | E22: 1790 | F22: 0.14128976 | G22: 1762 | H22: 0.14918297 | I22: 1726 | J22: 0.15593098 | K22: 1799 | L22: 0.15769635 | M22: 1931 | N22: 0.15763265 | O22: 1760 | P22: 0.14744073 | Q22: 1702 | R22: 0.16082396 | S22: 2039 | T22: 0.16283341 | U22: 2306 | V22: 0.15525483 | Y22: 2020 | Z22: 2021 | AA22: 2022
A23: Trucking | C23: — | E23: — | G23: — | I23: — | K23: — | M23: — | O23: 0 | Q23: 0 | S23: 410 | T23: 0.032742373 | U23: 966 | V23: 0.065037366 | Y23: =Q23 -> 0 | Z23: =S23 -> 410 | AA23: =U23 -> 966
A24: Other | C24: 397 | D24: 0.033011808 | E24: 422 | F24: 0.033309653 | G24: 478 | H24: 0.040470748 | I24: 368 | J24: 0.033246002 | K24: 434 | L24: 0.038043478 | M24: 582 | N24: 0.047510204 | O24: 518 | P24: 0.043394488 | Q24: 408 | R24: 0.038552395 | S24: 744 | T24: 0.059415429 | U24: 908 | V24: 0.061132431 | Y24: 1000 | Z24: 1000 | AA24: 1000
A25: Sales Volume | C25: — | E25: — | G25: — | I25: — | K25: — | M25: — | O25: — | Q25: 5892000 | R25: 1 | S25: 6253000 | T25: 1 | U25: 6218000 | V25: 1 | Y25: 637000 | Z25: 706000 | AA25: 697000
A26: Intermodal | C26: — | E26: — | G26: — | I26: — | K26: — | M26: — | O26: — | Q26: 2720000 | R26: 0.46164291 | S26: 2976000 | T26: 0.47593155 | U26: 2963000 | V26: 0.47651978 | Y26: 637000 | Z26: 706000 | AA26: 697000
A27: Merchandise | C27: — | E27: — | G27: — | I27: — | K27: — | M27: — | O27: — | Q27: 2535000 | R27: 0.4302444 | S27: 2571000 | T27: 0.41116264 | U27: 2558000 | V27: 0.4113863
A28: Chemicals | C28: — | E28: — | G28: — | I28: — | K28: — | M28: — | O28: — | Q28: 664000 | R28: 0.11269518 | S28: 659000 | T28: 0.10538941 | U28: 641000 | V28: 0.10308781
A29: Agriculture & Food Product | C29: — | E29: — | G29: — | I29: — | K29: — | M29: — | O29: — | Q29: 463000 | R29: 0.078581127 | S29: 467000 | T29: 0.074684152 | U29: 481000 | V29: 0.077356063
A30: Automotive | C30: — | E30: — | G30: — | I30: — | K30: — | M30: — | O30: — | Q30: 344000 | R30: 0.05838425 | S30: 318000 | T30: 0.050855589 | U30: 338000 | V30: 0.054358315
A31: Minerals | C31: — | E31: — | G31: — | I31: — | K31: — | M31: — | O31: — | Q31: 321000 | R31: 0.054480652 | S31: 325000 | T31: 0.051975052 | U31: 337000 | V31: 0.054197491
A32: Forest Products | C32: — | E32: — | G32: — | I32: — | K32: — | M32: — | O32: — | Q32: 278000 | R32: 0.047182621 | S32: 296000 | T32: 0.047337278 | U32: 291000 | V32: 0.046799614
A33: Metal & Equipment | C33: — | E33: — | G33: — | I33: — | K33: — | M33: — | O33: — | Q33: 239000 | R33: 0.040563476 | S33: 277000 | T33: 0.044298737 | U33: 267000 | V33: 0.042939852
A34: Fertilizers | C34: — | E34: — | G34: — | I34: — | K34: — | M34: — | O34: — | Q34: 226000 | R34: 0.038357094 | S34: 229000 | T34: 0.036622421 | U34: 203000 | V34: 0.032647153
A35: Coal | C35: — | E35: — | G35: — | I35: — | K35: — | M35: — | O35: — | Q35: 637000 | R35: 0.1081127 | S35: 706000 | T35: 0.11290581 | U35: 697000 | V35: 0.11209392
A36: Trucking | C36: — | E36: — | G36: — | I36: — | K36: — | M36: — | O36: — | Q36: 0 | S36: 0 | U36: 0
A37: Other | C37: — | E37: — | G37: — | I37: — | K37: — | M37: — | O37: — | Q37: 0 | S37: 0 | U37: 0
A38: Revenue Per Unit | C38: — | E38: — | G38: — | I38: — | K38: — | M38: — | O38: — | Q38: — | S38: — | U38: —
A39: Coal | C39: 2423 | E39: 2258 | G39: 2164 | I39: 2187 | K39: 2464 | M39: 2532 | O39: 2456 | Q39: 2193 | S39: 2535 | U39: 3492
A40: Merchandise | C40: 2548 | E40: 2595 | G40: 2542 | I40: 2549 | K40: 2616 | M40: 2774 | O40: 2803 | Q40: 2791 | S40: 2932 | U40: 3221
A41: Chemicals | C41: 3564 | E41: 3513 | G41: 3146 | I41: 3130 | K41: 3289 | M41: 3465 | O41: 3507 | Q41: 3477 | S41: 3674 | U41: 4031
A42: Agriculture & Food Product | C42: — | E42: — | G42: 2674 | I42: 2696 | K42: 2780 | M42: 2922 | O42: 3006 | Q42: 2994 | S42: 3128 | U42: 3459
A43: Forest Products | C43: 2601 | E43: 2668 | G43: 2745 | I43: 2821 | K43: 2860 | M43: 2982 | O43: 3049 | Q43: 3000 | S43: 3101 | U43: 3423
A44: Automotive | C44: 2817 | E44: 2789 | G44: 2611 | I44: 2616 | K44: 2615 | M44: 2737 | O44: 2711 | Q44: 2674 | S44: 2786 | U44: 3118
A45: Metal & Equipment | C45: — | E45: — | G45: 2546 | I45: 2718 | K45: 2746 | M45: 2880 | O45: 2988 | Q45: 2824 | S45: 2874 | U45: 3101
A46: Fertilizers | C46: 1612 | E46: 1618 | G46: 1625 | I46: 1543 | K46: 1601 | M46: 1782 | O46: 1774 | Q46: 1832 | S46: 2052 | U46: 2241
A47: Minerals | C47: 1571 | E47: 1567 | G47: 1500 | I47: 1497 | K47: 1549 | M47: 1644 | O47: 1642 | Q47: 1676 | S47: 1806 | U47: 1953
A48: Waste & Equipment | C48: 1760 | E48: 1956 | G48: — | I48: — | K48: — | M48: — | O48: — | Q48: — | S48: — | U48: —
A49: Metals | C49: 2458 | E49: 2540 | G49: — | I49: — | K49: — | M49: — | O49: — | Q49: — | S49: — | U49: —
A50: Food and Consumer | C50: 2802 | E50: 2819 | G50: — | I50: — | K50: — | M50: — | O50: — | Q50: — | S50: — | U50: —
A51: Agriculture Products | C51: 2597 | E51: 2697 | G51: — | I51: — | K51: — | M51: — | O51: — | Q51: — | S51: — | U51: —
A52: Intermodal | C52: 657 | E52: 656 | G52: 621 | I52: 614 | K52: 633 | M52: 667 | O52: 659 | Q52: 626 | S52: 685 | U52: 778
A53: Trucking | C53: — | E53: — | G53: — | I53: — | K53: — | M53: — | O53: — | Q53: 0 | S53: 0 | U53: 0
A54: Other | C54: 0 | E54: 0 | G54: 0 | I54: 0 | K54: 0 | M54: 0 | O54: 0 | Q54: 0 | S54: 0 | U54: 0
A55: Revenue Per Unit Growth % | C55: — | E55: — | G55: — | I55: — | K55: — | M55: — | O55: — | Q55: — | S55: — | U55: —
A56: Coal | C56: -2 | E56: -7 | G56: -4 | I56: 1 | K56: 13 | M56: 3 | O56: -3 | Q56: -11 | S56: 16 | U56: 38
A57: Intermodal | C57: 1 | E57: 0 | G57: -5 | I57: -1 | K57: 3 | M57: 5 | O57: -1 | Q57: -5 | S57: 9 | U57: 14
A58: Merchandise | C58: 2 | E58: 2 | G58: -2 | I58: 0 | K58: 3 | M58: 6 | O58: 1 | Q58: 0 | S58: 5 | U58: 10
A59: Automotive | C59: 4 | E59: -1 | G59: -6 | I59: 0 | K59: 0 | M59: 5 | O59: -1 | Q59: -1 | S59: 4 | U59: 12
A60: Agriculture & Food Product | C60: — | E60: — | G60: — | I60: 1 | K60: 3 | M60: 5 | O60: 3 | Q60: 0 | S60: 4 | U60: 11
A61: Chemicals | C61: 0 | E61: -1 | G61: -4 | I61: -1 | K61: 5 | M61: 5 | O61: 1 | Q61: -1 | S61: 6 | U61: 10
A62: Forest Products | C62: 3 | E62: 3 | G62: 3 | I62: 3 | K62: 1 | M62: 4 | O62: 2 | Q62: 0 | S62: 3 | U62: 10
A63: Fertilizers | C63: 1 | E63: 0 | G63: 0 | I63: -5 | K63: 4 | M63: 11 | O63: 0 | Q63: 2 | S63: 12 | U63: 9
A64: Minerals | C64: 4 | E64: 0 | G64: -4 | I64: 0 | K64: 3 | M64: 6 | O64: 0 | Q64: 1 | S64: 8 | U64: 8
A65: Metal & Equipment | C65: — | E65: — | G65: — | I65: 7 | K65: 1 | M65: 5 | O65: 4 | Q65: -5 | S65: 2 | U65: 8
A66: Waste & Equipment | C66: -7 | E66: 11 | G66: 4 | I66: — | K66: — | M66: — | O66: — | Q66: — | S66: — | U66: —
A67: Metals | C67: 2 | E67: 3 | G67: 1 | I67: — | K67: — | M67: — | O67: — | Q67: — | S67: — | U67: —
A68: Food and Consumer | C68: 3 | E68: 1 | G68: -1 | I68: — | K68: — | M68: — | O68: — | Q68: — | S68: — | U68: —
A69: Agriculture Products | C69: 2 | E69: 4 | G69: -2 | I69: — | K69: — | M69: — | O69: — | Q69: — | S69: — | U69: —
A70: Trucking | C70: — | E70: — | G70: — | I70: — | K70: — | M70: — | O70: — | Q70: — | S70: 0 | U70: 0
A71: Other | C71: 0 | E71: 0 | G71: 0 | I71: 0 | K71: 0 | M71: 0 | O71: 0 | Q71: 0 | S71: 0 | U71: 0
A72: Revenue Growth % | C72: — | E72: — | G72: — | I72: — | K72: — | M72: — | O72: — | Q72: — | S72: — | U72: —
A73: Trucking | C73: — | E73: — | G73: — | I73: — | K73: — | M73: — | O73: — | Q73: — | S73: 0 | U73: 136
A74: Coal | C74: -9 | E74: -2 | G74: -19 | I74: -20 | K74: 15 | M74: 7 | O74: -8 | Q74: -33 | S74: 28 | U74: 36
A75: Other | C75: 23 | E75: 6 | G75: 13 | I75: -23 | K75: 18 | M75: 34 | O75: -11 | Q75: -21 | S75: 82 | U75: 22
A76: Intermodal | C76: 6 | E76: 5 | G76: -2 | I76: -2 | K76: 4 | M76: 7 | O76: -9 | Q76: -3 | S76: 20 | U76: 13
A77: Merchandise | C77: 6 | E77: 8 | G77: -4 | I77: -2 | K77: -1 | M77: 6 | O77: 1 | Q77: -7 | S77: 7 | U77: 9
A78: Automotive | C78: 5 | E78: 0 | G78: -3 | I78: 7 | K78: -5 | M78: 6 | O78: -2 | Q78: -26 | S78: -4 | U78: 19
A79: Agriculture & Food Product | C79: — | E79: — | G79: — | I79: -4 | K79: -2 | M79: 3 | O79: 8 | Q79: -2 | S79: 5 | U79: 14
A80: Minerals | C80: 6 | E80: 6 | G80: 2 | I80: 1 | K80: 3 | M80: 9 | O80: 6 | Q80: -4 | S80: 9 | U80: 12
A81: Forest Products | C81: 7 | E81: 6 | G81: -3 | I81: -3 | K81: -2 | M81: 13 | O81: 3 | Q81: -4 | S81: 10 | U81: 8
A82: Chemicals | C82: 13 | E82: 15 | G82: -4 | I82: -4 | K82: 1 | M82: 6 | O82: 0 | Q82: -2 | S82: 5 | U82: 7
A83: Metal & Equipment | C83: — | E83: — | G83: — | I83: -3 | K83: 0 | M83: 9 | O83: -4 | Q83: -9 | S83: 18 | U83: 4
A84: Fertilizers | C84: 3 | E84: 1 | G84: -8 | I84: -5 | K84: 1 | M84: -5 | O84: -2 | Q84: -2 | S84: 14 | U84: -3
A85: Waste & Equipment | C85: 1 | E85: 17 | G85: 0 | I85: — | K85: — | M85: — | O85: — | Q85: — | S85: — | U85: —
A86: Metals | C86: 1 | E86: 9 | G86: -15 | I86: — | K86: — | M86: — | O86: — | Q86: — | S86: — | U86: —
A87: Food and Consumer | C87: -1 | E87: -1 | G87: -3 | I87: — | K87: — | M87: — | O87: — | Q87: — | S87: — | U87: —
A88: Agriculture Products | C88: 1 | E88: 12 | G88: -4 | I88: — | K88: — | M88: — | O88: — | Q88: — | S88: — | U88: —
A89: Transportation Fuel | C89: — | E89: — | G89: — | I89: 713 | J89: 1 | K89: 864 | L89: 1 | M89: 1046 | N89: 1 | O89: 906 | P89: 1 | Q89: 541 | R89: 1 | S89: 913 | T89: 1 | U89: 1626 | V89: 1
A90: Locomotive | C90: — | E90: — | G90: — | I90: 647 | J90: 0.90743338 | K90: 785 | L90: 0.90856481 | M90: 967 | N90: 0.92447419 | O90: 823 | P90: 0.90838852 | Q90: 496 | R90: 0.9168207 | S90: 807 | T90: 0.88389923 | U90: 1381 | V90: 0.84932349
A91: Non - Locomotive | C91: — | E91: — | G91: — | I91: 66 | J91: 0.09256662 | K91: 79 | L91: 0.091435185 | M91: 79 | N91: 0.075525813 | O91: 83 | P91: 0.091611479 | Q91: 45 | R91: 0.083179298 | S91: 106 | T91: 0.11610077 | U91: 245 | V91: 0.15067651
A92: Sales Change - Volume % | C92: — | E92: — | G92: — | I92: — | K92: — | M92: — | O92: — | Q92: — | S92: — | U92: —
A93: Trucking | C93: — | E93: — | G93: — | I93: — | K93: — | M93: — | O93: — | Q93: — | S93: 0 | U93: 0
A94: Other | C94: 0 | E94: 0 | G94: 0 | I94: 0 | K94: 0 | M94: 0 | O94: 0 | Q94: 0 | S94: 0 | U94: 0
A95: Intermodal | C95: 5 | E95: 6 | G95: 4 | I95: -1 | K95: 1 | M95: 2 | O95: -8 | Q95: 2 | S95: 9 | U95: 0
A96: Coal | C96: -7 | E96: 6 | G96: -16 | I96: -21 | K96: 2 | M96: 4 | O96: -5 | Q96: -24 | S96: 11 | U96: -1
A97: Merchandise | C97: 4 | E97: 6 | G97: -2 | I97: -2 | K97: -4 | M97: 0 | O97: 0 | Q97: -6 | S97: 1 | U97: -1
A98: Automotive | C98: 2 | E98: 1 | G98: 3 | I98: 7 | K98: -5 | M98: 1 | O98: -2 | Q98: -25 | S98: -8 | U98: 6
A99: Minerals | C99: 2 | E99: 7 | G99: 6 | I99: 1 | K99: -1 | M99: 2 | O99: 6 | Q99: -5 | S99: 1 | U99: 4
A100: Agriculture & Food Product | C100: — | E100: — | G100: — | I100: -5 | K100: -5 | M100: -2 | O100: 5 | Q100: -1 | S100: 1 | U100: 3
A101: Forest Products | C101: 4 | E101: 3 | G101: -6 | I101: -6 | K101: -4 | M101: 8 | O101: 1 | Q101: -5 | S101: 6 | U101: -2
...
