Workbook
Name cash: DCF!$C$21
Name debt: DCF!$C$22
Name ebi: CCA!$L$25:$L$29,CCA!$L$31:$L$37,CCA!$L$30
Name fcff: DCF!$L$16
Name reve: CCA!$J$25:$J$37
Name tgr: DCF!$I$20
Name wacc: DCF!$I$23

Sheet DCF
B2: Discounted Cash Flow Analysis | F2: CSX Corp. (CSX)
H4: 0.5 | I4: =H4+1 -> 1.5 | J4: =I4+1 -> 2.5 | K4: =J4+1 -> 3.5 | L4: =K4+1 -> 4.5
B5: $M | C5: 2018 | D5: 2019 | E5: 2020 | F5: 2021 | G5: 2022 | H5: 2023 | I5: 2024 | J5: 2025 | K5: 2026 | L5: 2027
B6: Revenue, Adj | C6: 22832 | D6: 21708 | E6: 19533 | F6: 21804 | G6: 24875 | H6: 23991.76 | I6: 25025.16
B7: Growth %, YoY | C7: 7.4953 | D7: -4.9229 | E7: -10.0193 | F7: 11.6265 | G7: 14.0846 | H7: -3.5507136 | I7: 4.3073122
B8: Gross Profit, Adj | C8: — | D8: — | E8: — | F8: — | G8: — | H8: 8975.7973 | I8: 9995.7997
B9: Margin % | C9: — | D9: — | E9: — | F9: — | G9: — | H9: 37.412 | I9: 39.943
B10: EBITDA, Adj | C10: 10708 | D10: 11136 | E10: 10570 | F10: 11849 | G10: 12593 | H10: 11291.6 | I10: 12238.917
B11: Margin % | C11: 46.899089 | D11: 51.29906 | E11: 54.113551 | F11: 54.34324 | G11: 50.625126 | H11: 47.064492 | I11: 48.906449
B12: Net Income, Adj | C12: 6027.62 | D12: 5903.2 | E12: 5510.463 | F12: 6417.14 | G12: 7067 | H12: 6251.192 | I12: 6836.885
B13: Margin % | C13: 26.399877 | D13: 27.193661 | E13: 28.211043 | F13: 29.431022 | G13: 28.41005 | H13: 26.055579 | I13: 27.320045
B14: EPS, Adj | C14: 7.9917 | D14: 8.3576 | E14: 8.1178 | F14: 9.7885 | G14: 11.3206 | H14: 10.253 | I14: 11.322
B15: Growth %, YoY | C15: -39.580615 | D15: 4.5789052 | E15: -2.8700023 | F15: 20.581047 | G15: 15.652042 | H15: -9.4304115 | I15: 10.426217
B16: FCFF | C16: 5249 | D16: 5156 | E16: 5613 | F16: 6096 | G16: 5742 | H16: 4846.03 | I16: 6040.806 | J16: 6100 | K16: 6300 | L16: 7000
B17: Discounted CF | H17: =H16/(1+wacc)^H4 -> 4744.0553 | I17: {=I16/(1+wacc)^I4} -> 5667.4256 | J17: {=J16/(1+wacc)^J4} -> 5484.6393 | K17: =K16/(1+wacc)^K4 -> 5428.5779 | L17: =L16/(1+wacc)^L4 -> 5780.5726
B19: Terminal Value | C19: =fcff*(1+tgr)/(wacc-tgr) -> 304444.46 | E19: % Debt | F19: =C22/F28 -> 0.73466857 | H19: WACC (% Equity x Cost of Equity) + (% Debt x Cost of Debt x (1 -Tax rate)) | I19: 0.09 | J19: ← from Bloomberg | N19: Share Price on | O19: 45251 | P19: 224.28
B20: Enterprise Value | C20: =SUM(H17:K17,C19) -> 325769.15 | E20: Cost of Debt | F20: =Summary!$AZ$9/100 -> 0.041244 | H20: TGR | I20: 0.02 | O20: Upside in 2026 | P20: =AVERAGE(C25)/P19-1 -> 1.13345
B21: + Cash | C21: =Summary!G6 -> 1019 | E21: Tax Rate | F21: 0.231 | O21: " a year | P21: =((1+P20)^(1/3.5))-1 -> 0.24171968
B22: - Debt | C22: =Summary!G8 -> 34957 | E22: Equity Value | F22: =BS!G72 -> 12625 | I22: Calculated WACC
B23: Equity Value | C23: =C20+C21-C22 -> 291831.15 | E23: % Equity | F23: =F22/F28 -> 0.26533143 | I23: =F23*G24+(F19*F20*(1-F21)) -> 0.043452554 | P23: Terminal Growth Rate
B24: Shares | C24: 609.9 | E24: Cost of Equity Risk Free Rate + (Beta x (Expected Market Return - Risk Free Rate)) | F24: =Summary!$AZ$6/100 -> 0.0823 | G24: =F25+F27*F26 -> 0.0759478 | P24: =Q24-0.005 -> 0.01 | Q24: =R24-0.005 -> 0.015 | R24: =tgr -> 0.02 | S24: =R24+0.005 -> 0.025 | T24: =S24+0.005 -> 0.03
B25: Share Price | C25: =C23/C24 -> 478.49017 | E25: Risk Free Rate | F25: 0.0441 | G25: from US10Y | N25: WACC | O25: =O26+0.005 -> 0.053452554 | P25: =TEXT((((((fcff*(1+P$24))/ABS($O25-P$24))+SUM($H$17:$K$17)-$C$22+$C$21)/$C$24/$P$19)-1),"0.0%") &" / "& TEXT((((fcff*(1+P$24))/ABS($O25-P$24))+SUM($H$17:$K$17)-$C$22+$C$21)/$C$24,"$0.00") -> 9.7% / $246.09 | Q25: =TEXT((((((fcff*(1+Q$24))/ABS($O25-Q$24))+SUM($H$17:$K$17)-$C$22+$C$21)/$C$24/$P$19)-1),"0.0%") &" / "& TEXT((((fcff*(1+Q$24))/ABS($O25-Q$24))+SUM($H$17:$K$17)-$C$22+$C$21)/$C$24,"$0.00") -> 25.9% / $282.28 | R25: =TEXT((((((fcff*(1+R$24))/ABS($O25-R$24))+SUM($H$17:$K$17)-$C$22+$C$21)/$C$24/$P$19)-1),"0.0%") &" / "& TEXT((((fcff*(1+R$24))/ABS($O25-R$24))+SUM($H$17:$K$17)-$C$22+$C$21)/$C$24,"$0.00") -> 46.8% / $329.27 | S25: =TEXT((((((fcff*(1+S$24))/ABS($O25-S$24))+SUM($H$17:$K$17)-$C$22+$C$21)/$C$24/$P$19)-1),"0.0%") &" / "& TEXT((((fcff*(1+S$24))/ABS($O25-S$24))+SUM($H$17:$K$17)-$C$22+$C$21)/$C$24,"$0.00") -> 75.1% / $392.79 | T25: =TEXT((((((fcff*(1+T$24))/ABS($O25-T$24))+SUM($H$17:$K$17)-$C$22+$C$21)/$C$24/$P$19)-1),"0.0%") &" / "& TEXT((((fcff*(1+T$24))/ABS($O25-T$24))+SUM($H$17:$K$17)-$C$22+$C$21)/$C$24,"$0.00") -> 115.5% / $483.38
C26: =AVERAGE(CCA!M43,CCA!M46) -> 164.82844 | E26: Beta | F26: 0.986 | O26: =O27+0.005 -> 0.048452554 | P26: =TEXT((((((fcff*(1+P$24))/ABS($O26-P$24))+SUM($H$17:$K$17)-$C$22+$C$21)/$C$24/$P$19)-1),"0.0%") &" / "& TEXT((((fcff*(1+P$24))/ABS($O26-P$24))+SUM($H$17:$K$17)-$C$22+$C$21)/$C$24,"$0.00") -> 25.2% / $280.78 | Q26: =TEXT((((((fcff*(1+Q$24))/ABS($O26-Q$24))+SUM($H$17:$K$17)-$C$22+$C$21)/$C$24/$P$19)-1),"0.0%") &" / "& TEXT((((fcff*(1+Q$24))/ABS($O26-Q$24))+SUM($H$17:$K$17)-$C$22+$C$21)/$C$24,"$0.00") -> 46.0% / $327.56 | R26: =TEXT((((((fcff*(1+R$24))/ABS($O26-R$24))+SUM($H$17:$K$17)-$C$22+$C$21)/$C$24/$P$19)-1),"0.0%") &" / "& TEXT((((fcff*(1+R$24))/ABS($O26-R$24))+SUM($H$17:$K$17)-$C$22+$C$21)/$C$24,"$0.00") -> 74.2% / $390.77 | S26: =TEXT((((((fcff*(1+S$24))/ABS($O26-S$24))+SUM($H$17:$K$17)-$C$22+$C$21)/$C$24/$P$19)-1),"0.0%") &" / "& TEXT((((fcff*(1+S$24))/ABS($O26-S$24))+SUM($H$17:$K$17)-$C$22+$C$21)/$C$24,"$0.00") -> 114.4% / $480.94 | T26: =TEXT((((((fcff*(1+T$24))/ABS($O26-T$24))+SUM($H$17:$K$17)-$C$22+$C$21)/$C$24/$P$19)-1),"0.0%") &" / "& TEXT((((fcff*(1+T$24))/ABS($O26-T$24))+SUM($H$17:$K$17)-$C$22+$C$21)/$C$24,"$0.00") -> 176.4% / $619.97
E27: Market Risk Premium = Market return - Risk free return | F27: =G27-F25 -> 0.0323 | G27: 0.0764 | O27: =wacc -> 0.043452554 | P27: =TEXT((((((fcff*(1+P$24))/ABS($O27-P$24))+SUM($H$17:$K$17)-$C$22+$C$21)/$C$24/$P$19)-1),"0.0%") &" / "& TEXT((((fcff*(1+P$24))/ABS($O27-P$24))+SUM($H$17:$K$17)-$C$22+$C$21)/$C$24,"$0.00") -> 45.3% / $325.84 | Q27: =TEXT((((((fcff*(1+Q$24))/ABS($O27-Q$24))+SUM($H$17:$K$17)-$C$22+$C$21)/$C$24/$P$19)-1),"0.0%") &" / "& TEXT((((fcff*(1+Q$24))/ABS($O27-Q$24))+SUM($H$17:$K$17)-$C$22+$C$21)/$C$24,"$0.00") -> 73.3% / $388.75 | R27: =TEXT(((((fcff*(1+R$24)/($O27-R$24))+SUM($H$17:$K$17)-$C$22+$C$21)/$C$24/$P$19)-1),"0.0%") &" / "& TEXT((((fcff*(1+R$24))/ABS($O27-R$24))+SUM($H$17:$K$17)-$C$22+$C$21)/$C$24,"$0.00") -> 113.3% / $478.49 | S27: =TEXT((((((fcff*(1+S$24))/ABS($O27-S$24))+SUM($H$17:$K$17)-$C$22+$C$21)/$C$24/$P$19)-1),"0.0%") &" / "& TEXT((((fcff*(1+S$24))/ABS($O27-S$24))+SUM($H$17:$K$17)-$C$22+$C$21)/$C$24,"$0.00") -> 175.0% / $616.86 | T27: =TEXT((((((fcff*(1+T$24))/ABS($O27-T$24))+SUM($H$17:$K$17)-$C$22+$C$21)/$C$24/$P$19)-1),"0.0%") &" / "& TEXT((((fcff*(1+T$24))/ABS($O27-T$24))+SUM($H$17:$K$17)-$C$22+$C$21)/$C$24,"$0.00") -> 282.6% / $858.08
C28: 40 | E28: Debt + Equity | F28: =C22+F22 -> 47582 | O28: =O27-0.005 -> 0.038452554 | P28: =TEXT((((((fcff*(1+P$24))/ABS($O28-P$24))+SUM($H$17:$K$17)-$C$22+$C$21)/$C$24/$P$19)-1),"0.0%") &" / "& TEXT((((fcff*(1+P$24))/ABS($O28-P$24))+SUM($H$17:$K$17)-$C$22+$C$21)/$C$24,"$0.00") -> 72.4% / $386.74 | Q28: =TEXT((((((fcff*(1+Q$24))/ABS($O28-Q$24))+SUM($H$17:$K$17)-$C$22+$C$21)/$C$24/$P$19)-1),"0.0%") &" / "& TEXT((((fcff*(1+Q$24))/ABS($O28-Q$24))+SUM($H$17:$K$17)-$C$22+$C$21)/$C$24,"$0.00") -> 112.3% / $476.04 | R28: =TEXT((((((fcff*(1+R$24))/ABS($O28-R$24))+SUM($H$17:$K$17)-$C$22+$C$21)/$C$24/$P$19)-1),"0.0%") &" / "& TEXT((((fcff*(1+R$24))/ABS($O28-R$24))+SUM($H$17:$K$17)-$C$22+$C$21)/$C$24,"$0.00") -> 173.7% / $613.75 | S28: =TEXT((((((fcff*(1+S$24))/ABS($O28-S$24))+SUM($H$17:$K$17)-$C$22+$C$21)/$C$24/$P$19)-1),"0.0%") &" / "& TEXT((((fcff*(1+S$24))/ABS($O28-S$24))+SUM($H$17:$K$17)-$C$22+$C$21)/$C$24,"$0.00") -> 280.7% / $853.82 | T28: =TEXT((((((fcff*(1+T$24))/ABS($O28-T$24))+SUM($H$17:$K$17)-$C$22+$C$21)/$C$24/$P$19)-1),"0.0%") &" / "& TEXT((((fcff*(1+T$24))/ABS($O28-T$24))+SUM($H$17:$K$17)-$C$22+$C$21)/$C$24,"$0.00") -> 514.4% / $1377.90
O29: =O28-0.005 -> 0.033452554 | P29: =TEXT((((((fcff*(1+P$24))/ABS($O29-P$24))+SUM($H$17:$K$17)-$C$22+$C$21)/$C$24/$P$19)-1),"0.0%") &" / "& TEXT((((fcff*(1+P$24))/ABS($O29-P$24))+SUM($H$17:$K$17)-$C$22+$C$21)/$C$24,"$0.00") -> 111.2% / $473.60 | Q29: =TEXT((((((fcff*(1+Q$24))/ABS($O29-Q$24))+SUM($H$17:$K$17)-$C$22+$C$21)/$C$24/$P$19)-1),"0.0%") &" / "& TEXT((((fcff*(1+Q$24))/ABS($O29-Q$24))+SUM($H$17:$K$17)-$C$22+$C$21)/$C$24,"$0.00") -> 172.3% / $610.64 | R29: =TEXT((((((fcff*(1+R$24))/ABS($O29-R$24))+SUM($H$17:$K$17)-$C$22+$C$21)/$C$24/$P$19)-1),"0.0%") &" / "& TEXT((((fcff*(1+R$24))/ABS($O29-R$24))+SUM($H$17:$K$17)-$C$22+$C$21)/$C$24,"$0.00") -> 278.8% / $849.55 | S29: =TEXT((((((fcff*(1+S$24))/ABS($O29-S$24))+SUM($H$17:$K$17)-$C$22+$C$21)/$C$24/$P$19)-1),"0.0%") &" / "& TEXT((((fcff*(1+S$24))/ABS($O29-S$24))+SUM($H$17:$K$17)-$C$22+$C$21)/$C$24,"$0.00") -> 511.3% / $1371.11 | T29: =TEXT((((((fcff*(1+T$24))/ABS($O29-T$24))+SUM($H$17:$K$17)-$C$22+$C$21)/$C$24/$P$19)-1),"0.0%") &" / "& TEXT((((fcff*(1+T$24))/ABS($O29-T$24))+SUM($H$17:$K$17)-$C$22+$C$21)/$C$24,"$0.00") -> 1417.5% / $3403.34
D32: =(D16-C16)/C16 -> -0.017717661 | E32: =(E16-D16)/D16 -> 0.0886346 | F32: =(F16-E16)/E16 -> 0.086050241 | G32: =(G16-F16)/F16 -> -0.058070866 | H32: =(H16-G16)/G16 -> -0.15603797 | I32: =(I16-H16)/H16 -> 0.24654738

Sheet CCA
B2: Comparable Company Analysis | G2: Westinghouse Air Brake
G3: Technologies Corporation (WAB)
H7: Revenue (in million USDs) | K7: EBITDA (in million USDs) | M7: Net Income (in millions)
B8: Ticker | C8: Company | D8: Share Price | E8: nbr of Shares | F8: Enterprise Value | G8: Market Cap | H8: 2021 | I8: 2022 | J8: 2023 | K8: 2022 | L8: 2023 | M8: 2022 | N8: 2023
B9: WAB | C9: WAB Tech | D9: =DCF!P19 -> 224.28 | E9: =DCF!C24 -> 609.9 | F9: =Summary!G9 -> 160746.29 | G9: =Summary!G5 -> 126808.29 | H9: =DCF!F6 -> 21804 | I9: =DCF!G6 -> 24875 | J9: =DCF!H6 -> 23991.76 | K9: =Summary!G15 -> 12593 | L9: =Summary!I15 -> 11291.6 | M9: =Summary!G17 -> 7067 | N9: =Summary!I17 -> 6251.192
B10: CRRC | C10: CRRC Corp | D10: 0.73 | E10: 24327 | F10: 22821 | G10: 19479 | H10: 35000 | I10: 33152 | J10: 33384 | K10: 3008 | L10: 3119 | M10: 1411 | N10: 1688
B11: KTK | C11: KTK Group | D11: 1.31 | E11: 783 | F11: 1132 | G11: 1028 | H11: 588 | I11: 525.6 | J11: 523.7 | K11: 47.5 | L11: 52.9 | M11: 26.3 | N11: 35.2
B12: GBX | C12: Greenbrier Companies | D12: 35.81 | E12: 31.1 | F12: 2725.2 | G12: 1114 | H12: 1748 | I12: 2997 | J12: 3944 | K12: 193.5 | L12: 325.7 | M12: 17.5 | N12: 85.7
B13: SRAIL | C13: Stadler Rail | D13: 35.92 | E13: 100 | F13: 3815 | G13: 3592 | H13: 3976 | I13: 3930 | J13: 4317 | K13: 322 | L13: 367 | M13: 75 | N13: 163
B14: CAF | C14: Construcciones y Auxiliar de Ferrocarr | D14: 30.8 | E14: 34.3 | F14: 1374 | G14: 1056 | H14: 3480 | I14: 3334 | J14: 3958 | K14: 244.6 | L14: 295.6 | M14: 52.6 | N14: 79
B15: ALO | C15: Alstom | D15: 14.38 | E15: 384.3 | F15: 12050 | G15: 5514 | H15: 10252 | I15: 17983 | J15: 17189 | K15: 1162 | L15: 1203 | M15: -436.5 | N15: 135.5
B16: CSX | C16: CSX Corp | D16: 30.45 | E16: 1980 | F16: 77680 | G16: 60163 | H16: 12550 | I16: 14853 | J16: 14707 | K16: 7656 | L16: 7437 | M16: 4166 | N16: 3847
B17: NSC | C17: Norfolk Southern | D17: 199.07 | E17: 226.14 | F17: 60090 | G17: 45017 | H17: 11142 | I17: 12745 | J17: 12320 | K17: 6043 | L17: 4688 | M17: 3270 | N17: 2090
B18: CNI | C18: Canadian National | D18: 112.54 | E18: 647.7 | F18: 86100 | G18: 72908 | H18: 14477 | I18: 17107 | J18: 16899 | K18: 9040 | L18: 8978 | M18: 5118 | N18: 4915
B19: TRN | C19: Trinity Industres | D19: 23.32 | E19: 81.87 | F19: 7580 | G19: 1909 | H19: 1516 | I19: 1977 | J19: 2451 | K19: 334 | L19: 658 | M19: 86 | N19: 94
B20: UNP | C20: Union Pacific | D20: 215.33 | E20: 609.6 | F20: 161370 | G20: 127650 | H20: 21804 | I20: 24875 | J20: 24140 | K20: 12589 | L20: 11860 | M20: 6998 | N20: 6365
B21: GET | C21: Getlink | D21: 16.09 | E21: 540 | F21: 12620 | G21: 8490 | H21: 774 | I21: 1606 | J21: 1962 | K21: 460 | L21: 617 | M21: 252 | N21: 358
C23: Revenue Growth | E23: EBITDA Margin | G23: Profit Margin | I23: EV / Revenue | K23: EV / EBITDA | M23: P / E
C24: 2022 | D24: 2023 | E24: 2022 | F24: 2023 | G24: 2022 | H24: 2023 | I24: 2022 | J24: 2023 | K24: 2022 | L24: 2023 | M24: 2022 | N24: 2023
A25: 0 | B25: =B9 -> WAB | C25: =I9/H9-1 -> 0.14084572 | D25: =J9/I9-1 -> -0.035507136 | E25: =K9/I9 -> 0.50625126 | F25: =L9/J9 -> 0.47064492 | G25: =M9/I9 -> 0.2841005 | H25: =N9/J9 -> 0.26055579 | I25: =$F9/I9 -> 6.4621622 | J25: =$F9/J9 -> 6.7000622 | K25: =$F9/K9 -> 12.764733 | L25: =$F9/L9 -> 14.235917 | M25: =$G9/M9 -> 17.943722 | N25: =$G9/N9 -> 20.285457
A26: 1 | B26: =B10 -> CRRC | C26: =I10/H10-1 -> -0.0528 | D26: =J10/I10-1 -> 0.0069980695 | E26: =K10/I10 -> 0.090733591 | F26: =L10/J10 -> 0.093427989 | G26: =M10/I10 -> 0.042561535 | H26: =N10/J10 -> 0.050563144 | I26: =$F10/I10 -> 0.68837476 | J26: =$F10/J10 -> 0.68359094 | K26: =$F10/K10 -> 7.5867686 | L26: =$F10/L10 -> 7.3167682 | M26: =$G10/M10 -> 13.805103 | N26: =$G10/N10 -> 11.539692
A27: 2 | B27: =B11 -> KTK | C27: =I11/H11-1 -> -0.10612245 | D27: =J11/I11-1 -> -0.0036149163 | E27: =K11/I11 -> 0.090372907 | F27: =L11/J11 -> 0.10101203 | G27: =M11/I11 -> 0.050038052 | H27: =N11/J11 -> 0.067214054 | I27: =$F11/I11 -> 2.1537291 | J27: =$F11/J11 -> 2.1615429 | K27: =$F11/K11 -> 23.831579 | L27: =$F11/L11 -> 21.398866 | M27: =$G11/M11 -> 39.087452 | N27: =$G11/N11 -> 29.204545
A28: 3 | B28: =B12 -> GBX | C28: =I12/H12-1 -> 0.71453089 | D28: =J12/I12-1 -> 0.31598265 | E28: =K12/I12 -> 0.064564565 | F28: =L12/J12 -> 0.082581136 | G28: =M12/I12 -> 0.0058391725 | H28: =N12/J12 -> 0.021729209 | I28: =$F12/I12 -> 0.90930931 | J28: =$F12/J12 -> 0.69097363 | K28: =$F12/K12 -> 14.083721 | L28: =$F12/L12 -> 8.3672091 | M28: =$G12/M12 -> 63.657143 | N28: =$G12/N12 -> 12.998833
A29: 4 | B29: =B13 -> SRAIL | C29: =I13/H13-1 -> -0.011569416 | D29: =J13/I13-1 -> 0.098473282 | E29: =K13/I13 -> 0.081933842 | F29: =L13/J13 -> 0.08501274 | G29: =M13/I13 -> 0.019083969 | H29: =N13/J13 -> 0.037757702 | I29: =$F13/I13 -> 0.97073791 | J29: =$F13/J13 -> 0.88371554 | K29: =$F13/K13 -> 11.847826 | L29: =$F13/L13 -> 10.395095 | M29: =$G13/M13 -> 47.893333 | N29: =$G13/N13 -> 22.03681
A30: 5 | B30: =B14 -> CAF | C30: =I14/H14-1 -> -0.041954023 | D30: =J14/I14-1 -> 0.18716257 | E30: =K14/I14 -> 0.073365327 | F30: =L14/J14 -> 0.074684184 | G30: =M14/I14 -> 0.015776845 | H30: =N14/J14 -> 0.019959576 | I30: =$F14/I14 -> 0.41211758 | J30: =$F14/J14 -> 0.34714502 | K30: =$F14/K14 -> 5.6173344 | L30: =$F14/L14 -> 4.6481732 | M30: =$G14/M14 -> 20.076046 | N30: =$G14/N14 -> 13.367089
A31: 6 | B31: =B15 -> ALO | C31: =I15/H15-1 -> 0.75409676 | D31: =J15/I15-1 -> -0.044152811 | E31: =K15/I15 -> 0.064616582 | F31: =L15/J15 -> 0.069986619 | G31: =M15/I15 -> -0.024272924 | H31: =N15/J15 -> 0.0078829484 | I31: =$F15/I15 -> 0.6700773 | J31: =$F15/J15 -> 0.70102973 | K31: =$F15/K15 -> 10.370052 | L31: =$F15/L15 -> 10.016625 | M31: =$G15/M15 -> -12.632302 | N31: =$G15/N15 -> 40.693727
A32: 7 | B32: =B16 -> CSX | C32: =I16/H16-1 -> 0.18350598 | D32: =J16/I16-1 -> -0.009829664 | E32: =K16/I16 -> 0.51545142 | F32: =L16/J16 -> 0.50567757 | G32: =M16/I16 -> 0.28048206 | H32: =N16/J16 -> 0.26157612 | I32: =$F16/I16 -> 5.2299199 | J32: =$F16/J16 -> 5.2818386 | K32: =$F16/K16 -> 10.14629 | L32: =$F16/L16 -> 10.445072 | M32: =$G16/M16 -> 14.441431 | N32: =$G16/N16 -> 15.638939
A33: 8 | B33: =B17 -> NSC | C33: =I17/H17-1 -> 0.14387004 | D33: =J17/I17-1 -> -0.03334641 | E33: =K17/I17 -> 0.47414672 | F33: =L17/J17 -> 0.38051948 | G33: =M17/I17 -> 0.2565712 | H33: =N17/J17 -> 0.16964286 | I33: =$F17/I17 -> 4.7147901 | J33: =$F17/J17 -> 4.8774351 | K33: =$F17/K17 -> 9.9437366 | L33: =$F17/L17 -> 12.817833 | M33: =$G17/M17 -> 13.766667 | N33: =$G17/N17 -> 21.539234
A34: 9 | B34: =B18 -> CNI | C34: =I18/H18-1 -> 0.18166747 | D34: =J18/I18-1 -> -0.012158765 | E34: =K18/I18 -> 0.52843865 | F34: =L18/J18 -> 0.53127404 | G34: =M18/I18 -> 0.29917578 | H34: =N18/J18 -> 0.29084561 | I34: =$F18/I18 -> 5.0330274 | J34: =$F18/J18 -> 5.094976 | K34: =$F18/K18 -> 9.5243363 | L34: =$F18/L18 -> 9.5901092 | M34: =$G18/M18 -> 14.245408 | N34: =$G18/N18 -> 14.833774
A35: 10 | B35: =B19 -> TRN | C35: =I19/H19-1 -> 0.30408971 | D35: =J19/I19-1 -> 0.23975721 | E35: =K19/I19 -> 0.16894284 | F35: =L19/J19 -> 0.26846185 | G35: =M19/I19 -> 0.043500253 | H35: =N19/J19 -> 0.038351693 | I35: =$F19/I19 -> 3.8340921 | J35: =$F19/J19 -> 3.0926153 | K35: =$F19/K19 -> 22.694611 | L35: =$F19/L19 -> 11.519757 | M35: =$G19/M19 -> 22.197674 | N35: =$G19/N19 -> 20.308511
A36: 11 | B36: UNP | C36: =I20/H20-1 -> 0.14084572 | D36: =J20/I20-1 -> -0.029547739 | E36: =K20/I20 -> 0.50609045 | F36: =L20/J20 -> 0.49130075 | G36: =M20/I20 -> 0.28132663 | H36: =N20/J20 -> 0.26367026 | I36: =$F20/I20 -> 6.4872362 | J36: =$F20/J20 -> 6.6847556 | K36: =$F20/K20 -> 12.818333 | L36: =$F20/L20 -> 13.606239 | M36: =$G20/M20 -> 18.240926 | N36: =$G20/N20 -> 20.054988
A37: 12 | B37: =B21 -> GET | C37: =I21/H21-1 -> 1.0749354 | D37: =J21/I21-1 -> 0.22166874 | E37: =K21/I21 -> 0.2864259 | F37: =L21/J21 -> 0.31447503 | G37: =M21/I21 -> 0.15691158 | H37: =N21/J21 -> 0.18246687 | I37: =$F21/I21 -> 7.8580324 | J37: =$F21/J21 -> 6.432212 | K37: =$F21/K21 -> 27.434783 | L37: =$F21/L21 -> 20.453809 | M37: =$G21/M21 -> 33.690476 | N37: =$G21/N21 -> 23.715084
C39: 2023 Trading Multiple | F39: Enterprise Value | I39: Equity Value | L39: Implied Share Price
C40: Revenue | D40: EBITDA | E40: P/E | F40: Revenue | G40: EBITDA | H40: Net Income | I40: Revenue | J40: EBITDA | K40: Net Income | L40: Share Price | M40: EBITDA | N40: Net Income
B41: Minimum | C41: =MIN(reve) -> 0.34714502 | D41: =MIN(ebi) -> 4.6481732 | E41: =MIN(N25:N37) -> 11.539692 | F41: =C41*$J$9 -> 8328.6201 | G41: =D41*$L$9 -> 52485.313 | H41: =N$9*E41 -> 72136.83 | I41: =F41+cash-debt -> -25609.38 | J41: =G41+cash-debt -> 18547.313 | K41: =H41+cash-debt -> 38198.83 | L41: =I41/E$9 -> -41.989474 | M41: =J41/E$9 -> 30.410416 | N41: =K41/E$9 -> 62.6313
B42: 1st Quartile | C42: =QUARTILE(reve,1) -> 0.70102973 | D42: =QUARTILE(ebi,1) -> 9.5901092 | E42: =QUARTILE(N25:N37,1) -> 14.833774 | F42: =C42*$J$9 -> 16818.937 | G42: =D42*$L$9 -> 108287.68 | H42: =N$9*E42 -> 92728.77 | I42: =F42+cash-debt -> -17119.063 | J42: =G42+cash-debt -> 74349.677 | K42: =H42+cash-debt -> 58790.77 | L42: =I42/E$9 -> -28.068639 | M42: =J42/E$9 -> 121.9047 | N42: =K42/E$9 -> 96.394114
B43: Lower Limit 75% | C43: =C44-0.674*_xlfn.STDEV.S(reve)/SQRT(11) -> 2.8357773 | D43: =D44-0.674*_xlfn.STDEV.S(ebi)/SQRT(11) -> 10.940901 | E43: =E44-0.674*_xlfn.STDEV.S(N25:N37)/SQRT(11) -> 18.88153 | F43: =C43*$J$9 -> 68035.288 | G43: =D43*$L$9 -> 123540.28 | H43: =N$9*E43 -> 118032.07 | I43: =F43+cash-debt -> 34097.288 | J43: =G43+cash-debt -> 89602.277 | K43: =H43+cash-debt -> 84094.069 | L43: =I43/E$9 -> 55.906359 | M43: =J43/E$9 -> 146.91306 | N43: =K43/E$9 -> 137.88173
B44: Mean | C44: =AVERAGE(reve) -> 3.3562994 | D44: =AVERAGE(ebi) -> 11.908575 | E44: =AVERAGE(N25:N37) -> 20.478206 | F44: =C44*$J$9 -> 80523.53 | G44: =D44*$L$9 -> 134466.86 | H44: =N$9*E44 -> 128013.2 | I44: =F44+cash-debt -> 46585.53 | J44: =G44+cash-debt -> 100528.86 | K44: =H44+cash-debt -> 94075.2 | L44: =I44/E$9 -> 76.382243 | M44: =J44/E$9 -> 164.82844 | N44: =K44/E$9 -> 154.24693
B45: Median | C45: =MEDIAN(reve) -> 3.0926153 | D45: =MEDIAN(ebi) -> 10.445072 | E45: =MEDIAN(N25:N37) -> 20.285457 | F45: =C45*$J$9 -> 74197.283 | G45: =D45*$L$9 -> 117941.57 | H45: =N$9*E45 -> 126808.29 | I45: =F45+cash-debt -> 40259.283 | J45: =G45+cash-debt -> 84003.574 | K45: =H45+cash-debt -> 92870.285 | L45: =I45/E$9 -> 66.009646 | M45: =J45/E$9 -> 137.73336 | N45: =K45/E$9 -> 152.27133
B46: Upper Limit 75% | C46: =C44+0.674*_xlfn.STDEV.S(reve)/SQRT(11) -> 3.8768216 | D46: =D44+0.674*_xlfn.STDEV.S(ebi)/SQRT(11) -> 12.876249 | E46: =E44+0.674*_xlfn.STDEV.S(N25:N37)/SQRT(11) -> 22.074883 | F46: =C46*$J$9 -> 93011.772 | G46: =D46*$L$9 -> 145393.45 | H46: =N$9*E46 -> 137994.33 | I46: =F46+cash-debt -> 59073.772 | J46: =G46+cash-debt -> 111455.45 | K46: =H46+cash-debt -> 104056.33 | L46: =I46/E$9 -> 96.858128 | M46: =J46/E$9 -> 182.74381 | N46: =K46/E$9 -> 170.61212
B47: 3rd Quartile | C47: =QUARTILE(reve,3) -> 5.2818386 | D47: =QUARTILE(ebi,3) -> 13.606239 | E47: =QUARTILE(N25:N37,3) -> 22.03681 | F47: =C47*$J$9 -> 126720.6 | G47: =D47*$L$9 -> 153636.21 | H47: =N$9*E47 -> 137756.33 | I47: =F47+cash-debt -> 92782.604 | J47: =G47+cash-debt -> 119698.21 | K47: =H47+cash-debt -> 103818.33 | L47: =I47/E$9 -> 152.12757 | M47: =J47/E$9 -> 196.25875 | N47: =K47/E$9 -> 170.22189
B48: Maximum | C48: =MAX(J26:J37) -> 6.6847556 | D48: =MAX(L26:L37) -> 21.398866 | E48: =MAX(N25:N37) -> 40.693727 | F48: =C48*$J$9 -> 160379.05 | G48: =D48*$L$9 -> 241627.43 | H48: =N$9*E48 -> 254384.3 | I48: =F48+cash-debt -> 126441.05 | J48: =G48+cash-debt -> 207689.43 | K48: =H48+cash-debt -> 220446.3 | L48: =I48/E$9 -> 207.3144 | M48: =J48/E$9 -> 340.5303 | N48: =K48/E$9 -> 361.44663

Sheet Summary
A1: CSX Corp (CSX US) - BBG Adj Highlights | L1: CSX Corp (CSX US) - Growth | AX1: CSX Corp (CSX US) - L#1518025
A3: In Millions of USD | C3: FY 2018 | D3: FY 2019 | E3: FY 2020 | F3: FY 2021 | G3: FY 2022 | H3: Current/LTM | I3: FY 2023 Est | J3: FY 2024 Est | L3: In Millions of USD except Per Share | N3: FY 1988 | O3: FY 1989 | P3: FY 1990 | Q3: FY 1991 | R3: FY 1992 | S3: FY 1993 | T3: FY 1994 | U3: FY 1995 | V3: FY 1996 | W3: FY 1997 | X3: FY 1998 | Y3: FY 1999 | Z3: FY 2000 | AA3: FY 2001 | AB3: FY 2002 | AC3: FY 2003 | AD3: FY 2004 | AE3: FY 2005 | AF3: FY 2006 | AG3: FY 2007 | AH3: FY 2008 | AI3: FY 2009 | AJ3: FY 2010 | AK3: FY 2011 | AL3: FY 2012 | AM3: FY 2013 | AN3: FY 2014 | AO3: FY 2015 | AP3: FY 2016 | AQ3: FY 2017 | AR3: FY 2018 | AS3: FY 2019 | AT3: FY 2020 | AU3: FY 2021 | AV3: FY 2022 | AX3: WACC History | AZ3: FY 2022 | BA3: FY 2021 | BB3: FY 2020 | BC3: FY 2019 | BD3: FY 2018 | BE3: FY 2017 | BF3: FY 2016 | BG3: FY 2015 | BH3: FY 2014 | BI3: FY 2013 | BJ3: FY 2012 | BK3: FY 2011 | BL3: FY 2010 | BM3: FY 2009 | BN3: FY 2008 | BO3: FY 2007 | BP3: FY 2006 | BQ3: FY 2005 | BR3: FY 2004 | BS3: FY 2003
A4: 12 Months Ending | C4: 12/31/2018 | D4: 12/31/2019 | E4: 12/31/2020 | F4: 12/31/2021 | G4: 12/31/2022 | H4: 09/30/2023 | I4: 12/31/2023 | J4: 12/31/2024 | L4: 12 Months Ending | N4: 12/31/1988 | O4: 12/31/1989 | P4: 12/31/1990 | Q4: 12/31/1991 | R4: 12/31/1992 | S4: 12/31/1993 | T4: 12/30/1994 | U4: 12/30/1995 | V4: 12/31/1996 | W4: 12/26/1997 | X4: 12/31/1998 | Y4: 12/31/1999 | Z4: 12/29/2000 | AA4: 12/28/2001 | AB4: 12/27/2002 | AC4: 12/26/2003 | AD4: 12/31/2004 | AE4: 12/30/2005 | AF4: 12/29/2006 | AG4: 12/28/2007 | AH4: 12/26/2008 | AI4: 12/25/2009 | AJ4: 12/31/2010 | AK4: 12/30/2011 | AL4: 12/28/2012 | AM4: 12/27/2013 | AN4: 12/26/2014 | AO4: 12/25/2015 | AP4: 12/30/2016 | AQ4: 12/31/2017 | AR4: 12/31/2018 | AS4: 12/31/2019 | AT4: 12/31/2020 | AU4: 12/31/2021 | AV4: 12/31/2022 | AX4: 12 Months Ending | AZ4: 12/31/2022 | BA4: 12/31/2021 | BB4: 12/31/2020 | BC4: 12/31/2019 | BD4: 12/31/2018 | BE4: 12/31/2017 | BF4: 12/30/2016 | BG4: 12/25/2015 | BH4: 12/26/2014 | BI4: 12/27/2013 | BJ4: 12/28/2012 | BK4: 12/30/2011 | BL4: 12/31/2010 | BM4: 12/25/2009 | BN4: 12/26/2008 | BO4: 12/28/2007 | BP4: 12/29/2006 | BQ4: 12/30/2005 | BR4: 12/31/2004 | BS4: 12/26/2003
A5: Market Capitalization | B5: HISTORICAL_MARKET_CAP | C5: 100224.59 | D5: 125124.88 | E5: 139788.78 | F5: 160943.38 | G5: 126808.29 | H5: 136720.53 | L5: 1 Year Growth | N5: {=GEOMEAN(AR6:AV6/100+1)-1} -> 0.032100101 | AX5: Equity
A6: - Cash & Equivalents | B6: CASH_AND_MARKETABLE_SECURITIES | C6: 1333 | D6: 891 | E6: 1859 | F6: 1006 | G6: 1019 | H6: 766 | L6: Revenue | M6: SALES_GROWTH | AC6: =_xll.BDH("UNP US Equity","SALES_GROWTH","FY 2003","FY 2003","Currency=USD","Period=FY","BEST_FPERIOD_OVERRIDE=FY","FILING_STATUS=MR","FA_ADJUSTED=GAAP","Sort=A","Dates=H","DateFormat=P","Fill=—","Direction=H","UseDPDF=Y") -> 3.5129 | AD6: =_xll.BDH("UNP US Equity","SALES_GROWTH","FY 2004","FY 2004","Currency=USD","Period=FY","BEST_FPERIOD_OVERRIDE=FY","FILING_STATUS=MR","FA_ADJUSTED=GAAP","Sort=A","Dates=H","DateFormat=P","Fill=—","Direction=H","UseDPDF=Y") -> 5.7484 | AE6: =_xll.BDH("UNP US Equity","SALES_GROWTH","FY 2005","FY 2005","Currency=USD","Period=FY","BEST_FPERIOD_OVERRIDE=FY","FILING_STATUS=MR","FA_ADJUSTED=GAAP","Sort=A","Dates=H","DateFormat=P","Fill=—","Direction=H","UseDPDF=Y") -> 11.1584 | AF6: =_xll.BDH("UNP US Equity","SALES_GROWTH","FY 2006","FY 2006","Currency=USD","Period=FY","BEST_FPERIOD_OVERRIDE=FY","FILING_STATUS=MR","FA_ADJUSTED=GAAP","Sort=A","Dates=H","DateFormat=P","Fill=—","Direction=H","UseDPDF=Y") -> 14.7297 | AG6: =_xll.BDH("UNP US Equity","SALES_GROWTH","FY 2007","FY 2007","Currency=USD","Period=FY","BEST_FPERIOD_OVERRIDE=FY","FILING_STATUS=MR","FA_ADJUSTED=GAAP","Sort=A","Dates=H","DateFormat=P","Fill=—","Direction=H","UseDPDF=Y") -> 4.5256 | AH6: =_xll.BDH("UNP US Equity","SALES_GROWTH","FY 2008","FY 2008","Currency=USD","Period=FY","BEST_FPERIOD_OVERRIDE=FY","FILING_STATUS=MR","FA_ADJUSTED=GAAP","Sort=A","Dates=H","DateFormat=P","Fill=—","Direction=H","UseDPDF=Y") -> 10.3605 | AI6: =_xll.BDH("UNP US Equity","SALES_GROWTH","FY 2009","FY 2009","Currency=USD","Period=FY","BEST_FPERIOD_OVERRIDE=FY","FILING_STATUS=MR","FA_ADJUSTED=GAAP","Sort=A","Dates=H","DateFormat=P","Fill=—","Direction=H","UseDPDF=Y") -> -21.2966 | AJ6: =_xll.BDH("UNP US Equity","SALES_GROWTH","FY 2010","FY 2010","Currency=USD","Period=FY","BEST_FPERIOD_OVERRIDE=FY","FILING_STATUS=MR","FA_ADJUSTED=GAAP","Sort=A","Dates=H","DateFormat=P","Fill=—","Direction=H","UseDPDF=Y") -> 19.9533 | AK6: =_xll.BDH("UNP US Equity","SALES_GROWTH","FY 2011","FY 2011","Currency=USD","Period=FY","BEST_FPERIOD_OVERRIDE=FY","FILING_STATUS=MR","FA_ADJUSTED=GAAP","Sort=A","Dates=H","DateFormat=P","Fill=—","Direction=H","UseDPDF=Y") -> 15.2785 | AL6: =_xll.BDH("UNP US Equity","SALES_GROWTH","FY 2012","FY 2012","Currency=USD","Period=FY","BEST_FPERIOD_OVERRIDE=FY","FILING_STATUS=MR","FA_ADJUSTED=GAAP","Sort=A","Dates=H","DateFormat=P","Fill=—","Direction=H","UseDPDF=Y") -> 7.0001 | AM6: =_xll.BDH("UNP US Equity","SALES_GROWTH","FY 2013","FY 2013","Currency=USD","Period=FY","BEST_FPERIOD_OVERRIDE=FY","FILING_STATUS=MR","FA_ADJUSTED=GAAP","Sort=A","Dates=H","DateFormat=P","Fill=—","Direction=H","UseDPDF=Y") -> 4.9556 | AN6: =_xll.BDH("UNP US Equity","SALES_GROWTH","FY 2014","FY 2014","Currency=USD","Period=FY","BEST_FPERIOD_OVERRIDE=FY","FILING_STATUS=MR","FA_ADJUSTED=GAAP","Sort=A","Dates=H","DateFormat=P","Fill=—","Direction=H","UseDPDF=Y") -> 9.2201 | AO6: =_xll.BDH("UNP US Equity","SALES_GROWTH","FY 2015","FY 2015","Currency=USD","Period=FY","BEST_FPERIOD_OVERRIDE=FY","FILING_STATUS=MR","FA_ADJUSTED=GAAP","Sort=A","Dates=H","DateFormat=P","Fill=—","Direction=H","UseDPDF=Y") -> -9.067 | AP6: =_xll.BDH("UNP US Equity","SALES_GROWTH","FY 2016","FY 2016","Currency=USD","Period=FY","BEST_FPERIOD_OVERRIDE=FY","FILING_STATUS=MR","FA_ADJUSTED=GAAP","Sort=A","Dates=H","DateFormat=P","Fill=—","Direction=H","UseDPDF=Y") -> -8.582 | AQ6: =_xll.BDH("UNP US Equity","SALES_GROWTH","FY 2017","FY 2017","Currency=USD","Period=FY","BEST_FPERIOD_OVERRIDE=FY","FILING_STATUS=MR","FA_ADJUSTED=GAAP","Sort=A","Dates=H","DateFormat=P","Fill=—","Direction=H","UseDPDF=Y") -> 6.5142 | AR6: =_xll.BDH("UNP US Equity","SALES_GROWTH","FY 2018","FY 2018","Currency=USD","Period=FY","BEST_FPERIOD_OVERRIDE=FY","FILING_STATUS=MR","FA_ADJUSTED=GAAP","Sort=A","Dates=H","DateFormat=P","Fill=—","Direction=H","UseDPDF=Y") -> 7.4953 | AS6: =_xll.BDH("UNP US Equity","SALES_GROWTH","FY 2019","FY 2019","Currency=USD","Period=FY","BEST_FPERIOD_OVERRIDE=FY","FILING_STATUS=MR","FA_ADJUSTED=GAAP","Sort=A","Dates=H","DateFormat=P","Fill=—","Direction=H","UseDPDF=Y") -> -4.9229 | AT6: =_xll.BDH("UNP US Equity","SALES_GROWTH","FY 2020","FY 2020","Currency=USD","Period=FY","BEST_FPERIOD_OVERRIDE=FY","FILING_STATUS=MR","FA_ADJUSTED=GAAP","Sort=A","Dates=H","DateFormat=P","Fill=—","Direction=H","UseDPDF=Y") -> -10.0193 | AU6: =_xll.BDH("UNP US Equity","SALES_GROWTH","FY 2021","FY 2021","Currency=USD","Period=FY","BEST_FPERIOD_OVERRIDE=FY","FILING_STATUS=MR","FA_ADJUSTED=GAAP","Sort=A","Dates=H","DateFormat=P","Fill=—","Direction=H","UseDPDF=Y") -> 11.6265 | AV6: =_xll.BDH("UNP US Equity","SALES_GROWTH","FY 2022","FY 2022","Currency=USD","Period=FY","BEST_FPERIOD_OVERRIDE=FY","FILING_STATUS=MR","FA_ADJUSTED=GAAP","Sort=A","Dates=H","DateFormat=P","Fill=—","Direction=H","UseDPDF=Y") -> 14.0846 | AX6: Cost of Equity | AY6: WACC_COST_EQUITY | AZ6: 8.23 | BA6: 9.9753 | BB6: 8.8113 | BC6: 9.0663 | BD6: 11.8505 | BE6: 10.1221 | BF6: 10.5031 | BG6: 10.7549 | BH6: 9.9474 | BI6: 11.2585 | BJ6: 12.3654 | BK6: 13.0941 | BL6: 15.0257 | BM6: 11.5097 | BN6: 11.7515 | BO6: 11.9134 | BP6: 11.6332 | BQ6: 10.9957 | BR6: 9.3144 | BS6: 9.0797
A7: + Preferred & Other | B7: PFD_EQTY_MINORTY_INTEREST | C7: 0 | D7: 0 | E7: 0 | F7: 0 | G7: 0 | H7: 0 | L7: EBITDA | M7: EBITDA_GROWTH | N7: -4.378 | O7: -4.3605 | P7: -2.1277 | Q7: 5.2019 | R7: 10.1107 | S7: -0.4692 | T7: 21.8182 | U7: 12.1614 | V7: 5.5692 | W7: 6.0224 | X7: -22.5011 | Y7: -32.1591 | Z7: 17.6717 | AA7: 12.3843 | AB7: 12.4763 | AC7: -34.5158 | AD7: 48.7532 | AE7: 37.7457 | AF7: 26.1016 | AG7: 4.6922 | AH7: 17.1647 | AI7: -13.9175 | AJ7: 26.6309 | AK7: 10.6521 | AL7: 1.5744 | AM7: 1.3508 | AN7: 4.0856 | AO7: 0.5877 | AP7: -2.1285 | AQ7: 7.3561 | AR7: 23.138 | AS7: 3.1935 | AT7: -8.9247 | AU7: 21.8981 | AV7: 7.4476 | AX7: Weight of Equity | AY7: WACC_WEIGHT_OF_EQUITY | AZ7: 77.4825 | BA7: 83.0403 | BB7: 92.3467 | BC7: 76.9257 | BD7: 77.5013 | BE7: 80.5644 | BF7: 74.7035 | BG7: 70.5429 | BH7: 78.8739 | BI7: 74.9184 | BJ7: 66.851 | BK7: 70.5102 | BL7: 73.3986 | BM7: 71.21 | BN7: 61.0998 | BO7: 71.3311 | BP7: 71.6557 | BQ7: 64.7537 | BR7: 54.0901 | BS7: 51.1861
A8: + Total Debt | B8: SHORT_AND_LONG_TERM_DEBT | C8: 22391 | D8: 27033 | E8: 28333 | F8: 31488 | G8: 34957 | H8: 34483 | L8: Operating Income | M8: OPER_INC_GROWTH | N8: 1.5642 | O8: -4.4004 | P8: -6.214 | Q8: 4.7853 | R8: 12.9977 | S8: -5.3886 | T8: 34.9398 | U8: 15.9903 | V8: 6.508 | W8: 4.0079 | X8: -28.6166 | Y8: -49.292 | Z8: 40.4887 | AA8: 18.882 | AB8: 17.7638 | AC8: -53.8598 | AD8: 92.3077 | AE8: 55 | AF8: 37.9355 | AG8: 5.5192 | AH8: 22.695 | AI8: -17.9913 | AJ8: 35.2863 | AK8: 12.9925 | AL8: -0.3746 | AM8: 0.4628 | AN8: 4.0311 | AO8: -0.8027 | AP8: -5.4408 | AQ8: 9.7669 | AR8: 30.8871 | AS8: 1.9717 | AT8: -12.145 | AU8: 28.2439 | AV8: 7.6689 | AX8: + Debt
A9: Enterprise Value | B9: ENTERPRISE_VALUE | C9: 121282.59 | D9: 151266.88 | E9: 166262.78 | F9: 191425.38 | G9: 160746.29 | H9: 170437.53 | L9: Net Income to Common | M9: EARN_FOR_COM_GROWTH | N9: 0.7353 | O9: 220.438 | P9: -7.2893 | Q9: — | R9: — | S9: 1695 | T9: 81.6156 | U9: -5.2147 | V9: 38.3495 | W9: -6.5497 | X9: -32.791 | Y9: -99.6276 | Z9: 28150 | AA9: -48.1416 | AB9: 44.7099 | AC9: -41.9811 | AD9: 37.8049 | AE9: 237.7581 | AF9: 14.4105 | AG9: 1.9847 | AH9: 2.1707 | AI9: -16.2637 | AJ9: 36.7454 | AK9: 18.682 | AL9: 0.2156 | AM9: 0.2152 | AN9: 3.3816 | AO9: 2.1288 | AP9: -12.9131 | AQ9: 219.3228 | AR9: -39.5247 | AS9: 0.6953 | AT9: -16.9919 | AU9: 36.745 | AV9: 10.1825 | AX9: Cost of Debt | AY9: WACC_COST_DEBT | AZ9: 4.1244 | BA9: 1.5807 | BB9: 0.9397 | BC9: 2.0369 | BD9: 2.8496 | BE9: 3.3206 | BF9: 2.079 | BG9: 1.9388 | BH9: 1.936 | BI9: 2.5144 | BJ9: 1.4206 | BK9: 1.6093 | BL9: 2.8116 | BM9: 3.5887 | BN9: 1.9549 | BO9: 3.7171 | BP9: 4.7908 | BQ9: 4.3609 | BR9: 3.7945 | BS9: 4.0281
L10: EPS Diluted | M10: DILUTED_EPS_AFT_XO_ITEMS_GROWTH | N10: 5.6818 | O10: 366.6667 | P10: -4.3779 | Q10: — | R10: — | S10: 1721.0526 | T10: 80.0578 | U10: -5.618 | V10: 34.6939 | W10: -6.0606 | X10: -32.5269 | Y10: -99.6016 | Z10: 26600 | AA10: -48.3146 | AB10: 44.2029 | AC10: -44.2211 | AD10: 36.9369 | AE10: 231.5789 | AF10: 11.9048 | AG10: 6.0284 | AH10: 11.7057 | AI10: -13.4731 | AJ10: 40.1384 | AK10: 25.9259 | AL10: 5.2941 | AM10: 2.2346 | AN10: 4.918 | AO10: 4.1667 | AP10: -9.5 | AQ10: 230.9392 | AR10: -35.8932 | AS10: 8.5938 | AT10: -71.223 | AU10: 320 | AV10: 16.0714 | AX10: Weight of Debt | AY10: WACC_WEIGHT_OF_DEBT | AZ10: 22.5175 | BA10: 16.9597 | BB10: 7.6533 | BC10: 23.0743 | BD10: 22.4987 | BE10: 19.4356 | BF10: 25.2965 | BG10: 29.4571 | BH10: 21.1261 | BI10: 25.0816 | BJ10: 33.149 | BK10: 29.4898 | BL10: 26.6014 | BM10: 28.79 | BN10: 38.9002 | BO10: 28.6689 | BP10: 28.3443 | BQ10: 35.2463 | BR10: 45.9099 | BS10: 48.8139
A11: Revenue, Adj | B11: SALES_REV_TURN | C11: 22832 | D11: 21708 | E11: 19533 | F11: 21804 | G11: 24875 | H11: 24140 | I11: 23991.76 | J11: 25025.16 | L11: EPS Diluted before XO | M11: DILUTED_EPS_BEF_XO_ITEMS_GROWTH | N11: — | O11: — | P11: -11.2469 | Q11: — | R11: — | S11: 1721.0526 | T11: 80.0578 | U11: -5.618 | V11: 34.6939 | W11: -6.0606 | X11: -32.5269 | Y11: -90.4382 | Z11: 265.1921 | AA11: 57.4514 | AB11: 58.6957 | AC11: -71.2329 | AD11: 196.8254 | AE11: 69.5187 | AF11: 77.918 | AG11: -2.8369 | AH11: 33.5766 | AI11: -22.1311 | AJ11: 42.1053 | AK11: 25.9259 | AL11: 5.2941 | AM11: 2.2346 | AN11: 4.918 | AO11: 4.1667 | AP11: -9.5 | AQ11: 230.9392 | AR11: -35.8932 | AS11: 8.5938 | AT11: -71.223 | AU11: 320 | AV11: 16.0714 | AX11: + Preferred Equity
A12: Growth %, YoY | B12: SALES_GROWTH | C12: 7.4953 | D12: -4.9229 | E12: -10.0193 | F12: 11.6265 | G12: 14.0846 | H12: -1.1789749 | I12: -3.5507136 | J12: 4.3073122 | L12: EPS Diluted before Abnormal | M12: RR_DIL_EPS_CONT_OPS_GROWTH | N12: — | O12: — | P12: -11.2469 | Q12: — | R12: — | S12: 1721.0526 | T12: 80.0578 | U12: -5.618 | V12: 34.6939 | W12: 5.303 | X12: -52.0384 | Y12: -92.5 | Z12: 486.6667 | AA12: 56.8182 | AB12: 44.2029 | AC12: -42.7136 | AD12: 64.0351 | AE12: 69.5187 | AF12: 77.918 | AG12: -4.2553 | AH12: 35.5556 | AI12: -22.1311 | AJ12: 45.3434 | AK12: 23.1204 | AL12: -0.625 | AM12: 5.0118 | AN12: 10.2385 | AO12: -0.7736 | AP12: -7.2455 | AQ12: 24.7399 | AR12: 65.4584 | AS12: 7.7674 | AT12: -70.326 | AU12: 279.1495 | AV12: 21.849 | AX12: Cost of Pref. Equity | AY12: WACC_COST_PFD | AZ12: 0 | BA12: 0 | BB12: 0 | BC12: 0 | BD12: 0 | BE12: 0 | BF12: 0 | BG12: 0 | BH12: 0 | BI12: 0 | BJ12: 0 | BK12: 0 | BL12: 0 | BM12: 0 | BN12: 0 | BO12: 0 | BP12: 0 | BQ12: 0 | BR12: 0 | BS12: 0
A13: Gross Profit, Adj | B13: GROSS_PROFIT | C13: — | D13: — | E13: — | F13: — | G13: — | I13: 8975.7973 | J13: 9995.7997 | L13: Dividend per Share | M13: DIVIDEND_PER_SHARE_1_YEAR_GROWTH | N13: 11.2069 | O13: -0.7752 | P13: 9.375 | Q13: 2.1429 | R13: 6.2937 | S13: 3.9474 | T13: 11.3924 | U13: 4.5455 | V13: 13.0435 | W13: 3.8462 | X13: 11.1111 | Y13: 0 | Z13: 0 | AA13: -33.3333 | AB13: -50 | AC13: 0 | AD13: 0 | AE13: 7.5 | AF13: 53.4884 | AG13: 63.6364 | AH13: 42.5926 | AI13: 14.2857 | AJ13: 12.5 | AK13: 36.3636 | AL13: 20 | AM13: 9.2593 | AN13: 6.7797 | AO13: 11.1111 | AP13: 2.8571 | AQ13: 8.3333 | AR13: 12.8205 | AS13: 227.2727 | AT13: -87.9167 | AU13: 220.6896 | AV13: 7.5269 | AX13: Weight of Pref. Equity | AY13: WACC_WEIGHT_OF_PREFERRED_EQUITY | AZ13: 0 | BA13: 0 | BB13: 0 | BC13: 0 | BD13: 0 | BE13: 0 | BF13: 0 | BG13: 0 | BH13: 0 | BI13: 0 | BJ13: 0 | BK13: 0 | BL13: 0 | BM13: 0 | BN13: 0 | BO13: 0 | BP13: 0 | BQ13: 0 | BR13: 0 | BS13: 0
A14: Margin % | B14: GROSS_PROFIT | C14: — | D14: — | E14: — | F14: — | G14: — | I14: 37.412 | J14: 39.943 | AX14: WACC | AY14: WACC | AZ14: =_xll.BDH("UNP US Equity","WACC","FY 2022","FY 2022","Currency=USD","Period=FY","BEST_FPERIOD_OVERRIDE=FY","FILING_STATUS=MR","Sort=D","Dates=H","DateFormat=P","Fill=—","Direction=H","UseDPDF=Y") -> 7.0156 | BA14: =_xll.BDH("UNP US Equity","WACC","FY 2021","FY 2021","Currency=USD","Period=FY","BEST_FPERIOD_OVERRIDE=FY","FILING_STATUS=MR","Sort=D","Dates=H","DateFormat=P","Fill=—","Direction=H","UseDPDF=Y") -> 8.9158 | BB14: =_xll.BDH("UNP US Equity","WACC","FY 2020","FY 2020","Currency=USD","Period=FY","BEST_FPERIOD_OVERRIDE=FY","FILING_STATUS=MR","Sort=D","Dates=H","DateFormat=P","Fill=—","Direction=H","UseDPDF=Y") -> 7.6743 | BC14: =_xll.BDH("UNP US Equity","WACC","FY 2019","FY 2019","Currency=USD","Period=FY","BEST_FPERIOD_OVERRIDE=FY","FILING_STATUS=MR","Sort=D","Dates=H","DateFormat=P","Fill=—","Direction=H","UseDPDF=Y") -> 7.3163 | BD14: =_xll.BDH("UNP US Equity","WACC","FY 2018","FY 2018","Currency=USD","Period=FY","BEST_FPERIOD_OVERRIDE=FY","FILING_STATUS=MR","Sort=D","Dates=H","DateFormat=P","Fill=—","Direction=H","UseDPDF=Y") -> 9.3826 | BE14: =_xll.BDH("UNP US Equity","WACC","FY 2017","FY 2017","Currency=USD","Period=FY","BEST_FPERIOD_OVERRIDE=FY","FILING_STATUS=MR","Sort=D","Dates=H","DateFormat=P","Fill=—","Direction=H","UseDPDF=Y") -> 7.7235 | BF14: =_xll.BDH("UNP US Equity","WACC","FY 2016","FY 2016","Currency=USD","Period=FY","BEST_FPERIOD_OVERRIDE=FY","FILING_STATUS=MR","Sort=D","Dates=H","DateFormat=P","Fill=—","Direction=H","UseDPDF=Y") -> 8.0489 | BG14: =_xll.BDH("UNP US Equity","WACC","FY 2015","FY 2015","Currency=USD","Period=FY","BEST_FPERIOD_OVERRIDE=FY","FILING_STATUS=MR","Sort=D","Dates=H","DateFormat=P","Fill=—","Direction=H","UseDPDF=Y") -> 8.9576 | BH14: =_xll.BDH("UNP US Equity","WACC","FY 2014","FY 2014","Currency=USD","Period=FY","BEST_FPERIOD_OVERRIDE=FY","FILING_STATUS=MR","Sort=D","Dates=H","DateFormat=P","Fill=—","Direction=H","UseDPDF=Y") -> 8.6918 | BI14: =_xll.BDH("UNP US Equity","WACC","FY 2013","FY 2013","Currency=USD","Period=FY","BEST_FPERIOD_OVERRIDE=FY","FILING_STATUS=MR","Sort=D","Dates=H","DateFormat=P","Fill=—","Direction=H","UseDPDF=Y") -> 8.9777 | BJ14: =_xll.BDH("UNP US Equity","WACC","FY 2012","FY 2012","Currency=USD","Period=FY","BEST_FPERIOD_OVERRIDE=FY","FILING_STATUS=MR","Sort=D","Dates=H","DateFormat=P","Fill=—","Direction=H","UseDPDF=Y") -> 10.0191 | BK14: =_xll.BDH("UNP US Equity","WACC","FY 2011","FY 2011","Currency=USD","Period=FY","BEST_FPERIOD_OVERRIDE=FY","FILING_STATUS=MR","Sort=D","Dates=H","DateFormat=P","Fill=—","Direction=H","UseDPDF=Y") -> 10.3805 | BL14: =_xll.BDH("UNP US Equity","WACC","FY 2010","FY 2010","Currency=USD","Period=FY","BEST_FPERIOD_OVERRIDE=FY","FILING_STATUS=MR","Sort=D","Dates=H","DateFormat=P","Fill=—","Direction=H","UseDPDF=Y") -> 11.7584 | BM14: =_xll.BDH("UNP US Equity","WACC","FY 2009","FY 2009","Currency=USD","Period=FY","BEST_FPERIOD_OVERRIDE=FY","FILING_STATUS=MR","Sort=D","Dates=H","DateFormat=P","Fill=—","Direction=H","UseDPDF=Y") -> 9.0324 | BN14: =_xll.BDH("UNP US Equity","WACC","FY 2008","FY 2008","Currency=USD","Period=FY","BEST_FPERIOD_OVERRIDE=FY","FILING_STATUS=MR","Sort=D","Dates=H","DateFormat=P","Fill=—","Direction=H","UseDPDF=Y") -> 8.5613 | BO14: =_xll.BDH("UNP US Equity","WACC","FY 2007","FY 2007","Currency=USD","Period=FY","BEST_FPERIOD_OVERRIDE=FY","FILING_STATUS=MR","Sort=D","Dates=H","DateFormat=P","Fill=—","Direction=H","UseDPDF=Y") -> 10.3763 | BP14: =_xll.BDH("UNP US Equity","WACC","FY 2006","FY 2006","Currency=USD","Period=FY","BEST_FPERIOD_OVERRIDE=FY","FILING_STATUS=MR","Sort=D","Dates=H","DateFormat=P","Fill=—","Direction=H","UseDPDF=Y") -> 8.9917 | BQ14: =_xll.BDH("UNP US Equity","WACC","FY 2005","FY 2005","Currency=USD","Period=FY","BEST_FPERIOD_OVERRIDE=FY","FILING_STATUS=MR","Sort=D","Dates=H","DateFormat=P","Fill=—","Direction=H","UseDPDF=Y") -> 8.1771 | BR14: =_xll.BDH("UNP US Equity","WACC","FY 2004","FY 2004","Currency=USD","Period=FY","BEST_FPERIOD_OVERRIDE=FY","FILING_STATUS=MR","Sort=D","Dates=H","DateFormat=P","Fill=—","Direction=H","UseDPDF=Y") -> 6.88 | BS14: =_xll.BDH("UNP US Equity","WACC","FY 2003","FY 2003","Currency=USD","Period=FY","BEST_FPERIOD_OVERRIDE=FY","FILING_STATUS=MR","Sort=D","Dates=H","DateFormat=P","Fill=—","Direction=H","UseDPDF=Y") -> 6.7372
A15: EBITDA, Adj | B15: EBITDA | C15: 10708 | D15: 11136 | E15: 10570 | F15: 11849 | G15: 12593 | H15: 11363 | I15: 11291.6 | J15: 12238.917 | L15: Accounts Receivable | M15: ACCOUNTS_RECEIVABLE_GROWTH | N15: 2.2831 | O15: -28.0134 | P15: 12.8682 | Q15: 0 | R15: -16.8956 | S15: 10.4132 | T15: 5.6886 | U15: 17.847 | V15: 7.4519 | W15: 10.4027 | X15: -9.0172 | Y15: 26.392 | Z15: -25.1101 | AA15: 3.2941 | AB15: -8.9977 | AC15: 45.5569 | AD15: -0.3439 | AE15: 3.7101 | AF15: -2.3295 | AG15: 0 | AH15: -5.707 | AI15: -10.1174 | AJ15: -0.201 | AK15: 0.7049 | AL15: -3.8 | AM15: 9.3555 | AN15: 7.3194 | AO15: -13.0204 | AP15: -4.4807 | AQ15: 3.4115 | AR15: 4.1237 | AS15: -2.3762 | AT15: -7.5051 | AU15: 25.8772 | AV15: 14.3728 | AY15: =AVERAGE(AZ14:BS14) -> 8.680905 | AZ15: =(AZ14-BA14)/BA14 -> -0.21312726 | BA15: =(BA14-BB14)/BB14 -> 0.16177371 | BB15: =(BB14-BC14)/BC14 -> 0.048931837 | BC15: =(BC14-BD14)/BD14 -> -0.2202268 | BD15: =(BD14-BE14)/BE14 -> 0.21481194 | BE15: =(BE14-BF14)/BF14 -> -0.040427885 | BF15: =(BF14-BG14)/BG14 -> -0.10144458 | BG15: =(BG14-BH14)/BH14 -> 0.030580547 | ... BO15: =(BO14-BP14)/BP14 -> 0.15398645
A16: Margin % | B16: EBITDA | C16: 46.899089 | D16: 51.29906 | E16: 54.113551 | F16: 54.34324 | G16: 50.625126 | H16: 47.071251 | I16: 47.064492 | J16: 48.906449 | L16: Inventory | M16: INVENTORY_GROWTH | N16: -33.6088 | O16: -1.6598 | P16: 8.4388 | Q16: -19.8444 | R16: -8.2524 | S16: 5.291 | T16: 6.0302 | U16: 4.2654 | V16: 4.0909 | W16: -0.8734 | X16: -0.8811 | Y16: -2.2222 | Z16: 11.3636 | AA16: -15.9184 | AB16: -12.6214 | AC16: -5.5556 | AD16: -2.9412 | AE16: 20.6061 | AF16: 2.5126 | AG16: 17.6471 | AH16: -9.5833 | AI16: -6.4516 | AJ16: 7.3892 | AK16: 10.0917 | AL16: 14.1667 | AM16: -8.0292 | AN16: 8.3333 | AO16: 28.2051 | AP16: 16.2857 | AQ16: -8.5995 | AR16: -29.3011 | AS16: -0.7605 | AT16: 15.7088 | AU16: 12.2517 | AV16: 0.59 | AX16: Capital Structure | BS16: {=GEOMEAN(AZ15:BO15/100+1)-1} -> -4.5499138e-05
A17: Net Income, Adj | B17: EARN_FOR_COMMON | C17: 6027.62 | D17: 5903.2 | E17: 5510.463 | F17: 6417.14 | G17: 7067 | H17: 6348 | I17: 6251.192 | J17: 6836.885 | L17: Fixed Assets | M17: NET_FIXED_ASSETS_1_YEAR_GROWTH | N17: -5.2253 | O17: 0.218 | P17: 3.5122 | Q17: 1.8617 | R17: 4.5102 | S17: 1.4291 | T17: 2.373 | U17: 2.2908 | V17: 5.3908 | W17: 4.1996 | X17: 1.9265 | Y17: -3.0684 | Z17: 3.1411 | AA17: 2.6103 | AB17: 2.4206 | AC17: 3.3419 | AD17: 45.2658 | AE17: 1.093 | AF17: 3.7693 | AG17: 4.096 | AH17: 4.169 | AI17: 1.6573 | AJ17: 3.1868 | AK17: 4.9372 | AL17: 4.3085 | AM17: 4.7639 | AN17: 4.7378 | AO17: 5.5626 | AP17: 3.2346 | AQ17: 1.9711 | AR17: 0.7367 | AS17: 2.1939 | AT17: 0.6606 | AU17: 1.8228 | AV17: 3.6729 | AX17: + Historical Market Cap | AY17: HISTORICAL_MARKET_CAP | AZ17: 64016.05 | BA17: 82787.191 | BB17: 207598.52 | BC17: 55968.362 | BD17: 50833.523 | BE17: 48950.704 | BF17: 33349.507 | BG17: 25228.881 | BH17: 36371.558 | BI17: 28540.649 | BJ17: 19828.024 | BK17: 22095.246 | BL17: 23905.7 | BM17: 19807.2 | BN17: 12301.569 | BO17: 18056.139 | BP17: 15072.215 | BQ17: 11078.166 | BR17: 8638.4023 | BS17: 7669.4319
A18: Margin % | B18: EARN_FOR_COMMON | C18: 26.399877 | D18: 27.193661 | E18: 28.211043 | F18: 29.431022 | G18: 28.41005 | H18: 26.296603 | I18: 26.055579 | J18: 27.320045 | L18: Total Assets | M18: ASSET_GROWTH | N18: -1.5494 | O18: -5.5888 | P18: 4.1145 | Q18: -0.0469 | R18: 1.9612 | S18: 2.8431 | T18: 2.2653 | U18: 4.0659 | V18: 18.7859 | W18: 17.6363 | X18: 2.3551 | Y18: 1.4344 | Z18: -1.1052 | AA18: 1.5129 | AB18: 0.7211 | AC18: 3.8614 | AD18: 13.0744 | AE18: -1.516 | AF18: 3.7017 | AG18: 1.6117 | AH18: 2.9529 | AI18: 2.2786 | AJ18: 4.664 | AK18: 4.2749 | AL18: 4.1814 | AM18: 3.9613 | AN18: 3.9991 | AO18: 5.1191 | AP18: 1.9255 | AQ18: 0.9177 | AR18: 2.7701 | AS18: 4.1602 | AT18: 4.015 | AU18: 1.8546 | AV18: 3.4073 | AX18: + Short Term Debt | AY18: BS_ST_BORROW | AZ18: 220 | BA18: 245 | BB18: 446 | BC18: 302 | BD18: 18 | BE18: 19 | BF18: 331 | BG18: 20 | BH18: 228 | BI18: 533 | BJ18: 780 | BK18: 507 | BL18: 613 | BM18: 113 | BN18: 320 | BO18: 787 | BP18: 600 | BQ18: 937 | BR18: 1084 | BS18: 428
A19: EPS, Adj | B19: IS_DIL_EPS_CONT_OPS | C19: 7.9917 | D19: 8.3576 | E19: 8.1178 | F19: 9.7885 | G19: 11.3206 | H19: 10.392299 | I19: 10.253 | J19: 11.322 | L19: Modified Working Capital | M19: MODIFIED_WORK_CAP_GROWTH | N19: -30.4167 | O19: -92.8144 | P19: — | Q19: — | R19: — | S19: 53.271 | T19: 82 | U19: -666.6667 | V19: 4.3478 | W19: — | X19: — | Y19: — | Z19: -89.8734 | AA19: 637.5 | AB19: 50 | AC19: 185.8757 | AD19: -10.2767 | AE19: -1.5419 | AF19: -9.6197 | AG19: 8.4158 | AH19: -19.863 | AI19: -34.188 | AJ19: -28.5714 | AK19: 34.5455 | AL19: 0 | AM19: 56.3063 | AN19: 60.5187 | AO19: 1.9749 | AP19: -5.1056 | AQ19: -8.1633 | AR19: -34.5455 | AS19: -37.037 | AT19: 98.5294 | AU19: 29.3827 | AV19: 0 | AX19: + Long Term Debt | AY19: BS_LT_BORROW | AZ19: 18384 | BA19: 16663 | BB19: 16759 | BC19: 16486 | BD19: 14739 | BE19: 11790 | BF19: 10962 | BG19: 10515 | BH19: 9514 | BI19: 9022 | BJ19: 9052 | BK19: 8734 | BL19: 8051 | BM19: 7895 | BN19: 7512 | BO19: 6470 | BP19: 5362 | BQ19: 5093 | BR19: 6248 | BS19: 6886
A20: Growth %, YoY | B20: IS_DIL_EPS_CONT_OPS | C20: -39.580615 | D20: 4.5789052 | E20: -2.8700023 | F20: 20.581047 | G20: 15.652042 | H20: -6.9889293 | I20: -9.4304115 | J20: 10.426217 | L20: Working Capital | M20: WORK_CAP_GROWTH | N20: — | O20: 0.9585 | P20: 6.7742 | Q20: -62.9758 | R20: 8.811 | S20: 18.0442 | T20: -19.3182 | U20: -25.7143 | V20: 35.1326 | W20: 22.3358 | X20: -15.7895 | Y20: -47.7273 | Z20: -35.6044 | AA20: 0.4052 | AB20: 45.891 | AC20: 53.8346 | AD20: -2.2801 | AE20: -93.3121 | AF20: — | AG20: — | AH20: 92.7778 | AI20: — | AJ20: -54.8936 | AK20: -22.0126 | AL20: -29.8387 | AM20: 2.2989 | AN20: 161.236 | AO20: 90.9677 | AP20: -49.6622 | AQ20: -95.302 | AR20: 2995.2381 | AS20: 73.3846 | AT20: 114.9068 | AU20: -32.2874 | AV20: -15.9756 | AX20: + Preferred Equity and Hybrid Capital | AY20: PFD_EQTY_HYBRID_CAPITAL | AZ20: 0 | BA20: 0 | BB20: 0 | BC20: 0 | BD20: 0 | BE20: 0 | BF20: 0 | BG20: 0 | BH20: 0 | BI20: 0 | BJ20: 0 | BK20: 0 | BL20: 0 | BM20: 0 | BN20: 0 | BO20: — | BP20: 0 | BQ20: 0 | BR20: 0 | BS20: 0
L21: Employees | M21: EMPL_GROWTH | N21: -3.3611 | O21: -1.6139 | P21: -3.1264 | Q21: -2.9162 | R21: -4.6839 | S21: -1.124 | T21: -9.738 | U21: 10.6403 | V21: 0.6681 | W21: -0.8518 | X21: -1.6286 | Y21: — | Z21: — | AA21: -3.8717 | AB21: — | AC21: — | AD21: -4.4488 | AE21: -2.3628 | AF21: 2.8571 | AG21: -2.7778 | AH21: -2.8571 | AI21: -11.5059 | AJ21: -0.2925 | AK21: 3.3333 | AL21: 3.2258 | AM21: -3.125 | AN21: 3.2258 | AO21: -9.375 | AP21: -6.8966 | AQ21: -11.1111 | AR21: -6.25 | AS21: -6.6667 | AT21: -8.181 | AU21: 8.4898 | AV21: 7.7585 | AX21: Total Capital | AY21: WACC_TOTAL_CAPITAL | AZ21: 82620.05 | BA21: 99695.191 | BB21: 224803.52 | BC21: 72756.362 | BD21: 65590.523 | BE21: 60759.704 | BF21: 44642.507 | BG21: 35763.881 | BH21: 46113.558 | BI21: 38095.649 | BJ21: 29660.024 | BK21: 31336.246 | BL21: 32569.7 | BM21: 27815.2 | BN21: 20133.569 | BO21: 25313.139 | BP21: 21034.214 | BQ21: 17108.166 | BR21: 15970.402 | BS21: 14983.432
A22: Cash from Operations | B22: CF_CASH_FROM_OPER | C22: 8686 | D22: 8609 | E22: 8540 | F22: 9032 | G22: 9362 | H22: 8276 | L22: Accounts Payable | M22: ACCOUNTS_PAYABLE_GROWTH_1YR | N22: 5.7971 | O22: 6.8493 | P22: 20.2797 | Q22: -10.2713 | R22: -2.6998 | S22: 1.7758 | T22: 0.9815 | U22: 21.0583 | V22: 6.066 | W22: -0.841 | X22: 3.1383 | Y22: -1.5625 | Z22: -9.858 | AA22: -10.4727 | AB22: -16.9772 | AC22: 3.1172 | AD22: 5.1995 | AE22: 9.6552 | AF22: 2.0964 | AG22: 0.2053 | AH22: -0.3074 | AI22: -0.6166 | AJ22: 8.1696 | AK22: -2.6769 | AL22: -0.3929 | AM22: -5.6213 | AN22: -11.7032 | AO22: -9.5858 | AP22: 5.4974 | AQ22: 5.0868 | AR22: 12.0425 | AS22: 9.9052 | AT22: -22.4353 | AU22: 19.0358 | AV22: 17.3416
A23: Capital Expenditures | B23: CAPITAL_EXPEND | C23: -3437 | D23: -3453 | E23: -2927 | F23: -2936 | G23: -3620 | H23: -3557 | I23: -3695.062 | J23: -3590.944 | L23: Short-Term Debt | M23: SHORT_TERM_DEBT_1_YEAR_GROWTH | N23: 270.2786 | O23: -61.204 | P23: -23.0603 | Q23: 11.4846 | R23: -46.2312 | S23: 44.8598 | T23: 65.4839 | U23: 23.5867 | V23: -31.2303 | W23: -18.578 | X23: -19.1549 | Y23: 221.6028 | Z23: -0.2167 | AA23: 37.785 | AB23: -57.9196 | AC23: -19.8502 | AD23: 153.271 | AE23: -13.5609 | AF23: -35.9658 | AG23: 31.1667 | AH23: -59.3393 | AI23: -64.6875 | AJ23: 442.4779 | AK23: -17.292 | AL23: 53.8462 | AM23: -31.6667 | AN23: -57.2233 | AO23: -91.2281 | AP23: 1555 | AQ23: -94.2598 | AR23: -5.2632 | AS23: 1577.7778 | AT23: 47.6821 | AU23: -45.0673 | AV23: -10.2041 | AX23: EVA
A24: Free Cash Flow | B24: CF_FREE_CASH_FLOW | C24: 5249 | D24: 5156 | E24: 5613 | F24: 6096 | G24: 5742 | H24: 4719 | I24: 4846.03 | J24: 6040.806 | L24: Total Debt | M24: TOTAL_DEBT_1_YEAR_GROWTH | N24: 21.3199 | O24: -24.527 | P24: 5.9856 | Q24: -5.3223 | R24: 8.0262 | S24: -0.4626 | T24: -9.0619 | U24: -8.7831 | V24: 66.9118 | W24: 42.039 | X24: -0.768 | Y24: 5.9533 | Z24: -5.4502 | AA24: 5.601 | AB24: -0.7738 | AC24: 3.7006 | AD24: 0.2461 | AE24: -17.7578 | AF24: -1.1277 | AG24: 21.7209 | AH24: 7.9234 | AI24: 2.2472 | AJ24: 8.1918 | AK24: 6.6597 | AL24: 6.3954 | AM24: -2.8173 | AN24: 1.9571 | AO24: 8.14 | AP24: 7.1951 | AQ24: 4.5692 | AR24: 24.964 | AS24: 13.763 | AT24: 2.4839 | AU24: -1.7262 | AV24: 10.0308 | AX24: + Net Op. Profit | AY24: WACC_NET_OPER_PROFIT | AZ24: 5949 | BA24: 5536 | BB24: 4322 | BC24: 4927 | BD24: 4825 | BE24: 3753 | BF24: 3398 | BG24: 3613 | BH24: 3693 | BI24: 3517 | BJ24: 3496 | BK24: 3503 | BL24: 3086 | BM24: 2273 | BN24: 2767 | BO24: 2287 | BP24: 2164 | BQ24: 1562 | BR24: 1005 | BS24: 513
A25: Source: Bloomberg | L25: Total Equity | M25: TOTAL_EQUITY_1_YEAR_GROWTH | N25: -32.3563 | O25: 0.3706 | P25: 0.568 | Q25: -10.1384 | R25: -6.5053 | S25: 6.8908 | T25: 17.327 | U25: 13.6961 | V25: 17.7511 | W25: 15.4354 | X25: 1.9771 | Y25: -2.1088 | Z25: 4.5344 | AA25: 1.7118 | AB25: 1.9771 | AC25: 3.3969 | AD25: 5.5478 | AE25: 16.7817 | AF25: 12.4214 | AG25: -2.8741 | AH25: -7.3345 | AI25: 8.9463 | AJ25: -0.7755 | AK25: -2.6667 | AL25: 6.3061 | AM25: 16.6852 | AN25: 6.3976 | AO25: 4.4023 | AP25: 0.2228 | AQ25: 25.8851 | AR25: -14.5438 | AS25: -5.6995 | AT25: 10.5117 | AU25: 2.9748 | AV25: -6.4815 | AX25: - Cash Op. Taxes | AY25: WACC_CASH_OPER_TAXES | AZ25: 1202.3827 | BA25: 1106.9511 | BB25: 829.6816 | BC25: 862.1152 | BD25: 853.6169 | BE25: 849 | BF25: 852.7931 | BG25: 874.2906 | BH25: 1115.7953 | BI25: 727.5065 | BJ25: 730.7939 | BK25: 723.7755 | BL25: 694.7003 | BM25: 465.4708 | BN25: 816.3312 | BO25: 841.3975 | BP25: 615.6638 | BQ25: 625.7799 | BR25: -2051.2009 | BS25: -22.3333
L26: Capital | M26: GROWTH_IN_CAP | N26: -10.7831 | O26: -13.2368 | P26: 3.1436 | Q26: -7.7856 | R26: 0.7832 | S26: 2.9375 | T26: 3.6086 | U26: 3.4392 | V26: 37.5317 | W26: 28.4266 | X26: 0.4945 | Y26: 2.1907 | Z26: -0.9864 | AA26: 3.7653 | AB26: 0.4989 | AC26: 3.558 | AD26: 2.7312 | AE26: -1.1242 | AF26: 6.5789 | AG26: 6.9646 | AH26: -0.3889 | AI26: 5.6423 | AJ26: 3.505 | AK26: 1.9869 | AL26: 6.3527 | AM26: 6.5042 | AN26: 4.2824 | AO26: 6.143 | AP26: 3.5311 | AQ26: 15.4131 | AR26: 3.0418 | AS26: 4.8067 | AT26: 5.8078 | AU26: 0.3068 | AV26: 2.6999 | AX26: + NOPAT | AY26: WACC_NOPAT | AZ26: 4746.6173 | BA26: 4429.0489 | BB26: 3492.3184 | BC26: 4064.8848 | BD26: 3971.3831 | BE26: 2904 | BF26: 2545.2069 | BG26: 2738.7094 | BH26: 2577.2047 | BI26: 2789.4935 | BJ26: 2765.2061 | BK26: 2779.2245 | BL26: 2391.2997 | BM26: 1807.5292 | BN26: 1950.6688 | BO26: 1445.6025 | BP26: 1548.3362 | BQ26: 936.2201 | BR26: 3056.2009 | BS26: 535.3333
L27: Book Value per Share | M27: BVPS_GROWTH | N27: -2.7611 | O27: 9.3674 | P27: 8.1205 | Q27: -13.5072 | R27: -7.4974 | S27: 6.1532 | T27: 16.7366 | U27: 13.1284 | V27: 14.2818 | W27: 14.6819 | X27: 2.5365 | Y27: -2.7026 | Z27: 7.3382 | AA27: 1.2596 | AB27: 1.5026 | AC27: 3.2123 | AD27: 5.3235 | AE27: 15.3506 | AF27: 12.0727 | AG27: 4.2461 | AH27: -3.2205 | AI27: 8.0876 | AJ27: 5.3911 | AK27: 2.9855 | AL27: 9.2907 | AM27: 17.9772 | AN27: 8.2344 | AO27: 7.3054 | AP27: 4.2633 | AQ27: 31.3331 | AR27: -7.0827 | AS27: -0.24 | AT27: -62.6126 | AU27: 220.9453 | AV27: -0.3578 | AX27: Total Invested Capital | AY27: WACC_TOTAL_INV_CAPITAL | AZ27: 38983 | BA27: 37959 | BB27: 37841 | BC27: 36008 | BD27: 34486 | BE27: 33300 | BF27: 33077 | BG27: 32078 | BH27: 30337 | BI27: 28869 | BJ27: 27592 | BK27: 26118 | BL27: 24984 | BM27: 23919 | BN27: 22849 | BO27: 22431 | BP27: 21523 | BQ27: 20594 | BR27: 20902 | BS27: 18042
AX28: WACC | AY28: WACC | AZ28: 7.3055 | BA28: 8.5516 | BB28: 8.2089 | BC28: 7.4443 | BD28: 9.8254 | BE28: 8.8002 | BF28: 8.3721 | BG28: 8.158 | BH28: 8.2549 | BI28: 9.0653 | BJ28: 8.7373 | BK28: 9.7072 | BL28: 11.7766 | BM28: 9.2292 | BN28: 7.9406 | BO28: 9.5636 | BP28: 9.6938 | BQ28: 8.6572 | BR28: 6.7802 | BS28: 6.6139
L29: Cash From Operations | M29: CASH_FLOW_GROWTH | N29: -32.9198 | O29: 24.1677 | P29: -11.718 | Q29: -2.5872 | R29: 8.4296 | S29: 2.4494 | T29: 37.8378 | U29: 18.175 | V29: -8.1047 | W29: 8.1944 | X29: -35.8151 | Y29: 7.1 | Z29: -33.7068 | AA29: 16.4789 | AB29: 36.2757 | AC29: -28.6602 | AD29: 79.8507 | AE29: -23.2365 | AF29: 85.4054 | AG29: 6.1224 | AH29: 33.4249 | AI29: -30.0275 | AJ29: 59.9313 | AK29: 7.0531 | AL29: -15.6116 | AM29: 10.8961 | AN29: 2.3263 | AO29: 0.8077 | AP29: -9.7626 | AQ29: 14.173 | AR29: 33.6694 | AS29: 4.5033 | AT29: -12.1031 | AU29: 19.6106 | AV29: 10.1981 | AX29: - Capital Charge | AY29: WACC_CAPITAL_CHARGE | AZ29: 2847.8995 | BA29: 3246.1049 | BB29: 3106.3292 | BC29: 2680.559 | BD29: 3388.3884 | BE29: 2930.4646 | BF29: 2769.2336 | BG29: 2616.9094 | BH29: 2504.2848 | BI29: 2617.0651 | BJ29: 2410.7886 | BK29: 2535.3354 | BL29: 2942.2646 | BM29: 2207.5388 | BN29: 1814.3501 | BO29: 2145.2112 | BP29: 2086.3874 | BQ29: 1782.8579 | BR29: 1417.1948 | BS29: 1193.2711
L30: Capital Expenditures | M30: TOT_CAP_EXPEND_GROWTH | N30: 49.5695 | O30: 7.2368 | P30: -9.0491 | Q30: -27.1501 | R30: 20.4861 | S30: -26.2248 | T30: 13.9323 | U30: 32.1143 | V30: 5.7958 | W30: -8.0131 | X30: 31.4667 | Y30: 2.5693 | Z30: -39.8154 | AA30: 1.862 | AB30: 16.129 | AC30: -1.9444 | AD30: -2.7384 | AE30: 10.2913 | AF30: 44.2782 | AG30: 8.1757 | AH30: -1.8613 | AI30: -18.046 | AJ30: 29.0323 | AK30: 24.837 | AL30: 1.9155 | AM30: -1.1961 | AN30: 5.8798 | AO30: 4.6141 | AP30: -6.4012 | AQ30: -14.9291 | AR30: -14.4608 | AS30: -5.043 | AT30: -1.8709 | AU30: 10.1476 | AV30: 19.0955 | AX30: Economic Value Added | AY30: WACC_ECON_VALUE_ADDED | AZ30: 1898.7178 | BA30: 1182.944 | BB30: 385.9893 | BC30: 1384.3258 | BD30: 582.9947 | BE30: -26.4646 | BF30: -224.0267 | BG30: 121.7999 | BH30: 72.9199 | BI30: 172.4284 | BJ30: 354.4175 | BK30: 243.8891 | BL30: -550.965 | BM30: -400.0096 | BN30: 136.3186 | BO30: -699.6087 | BP30: -538.0512 | BQ30: -846.6378 | BR30: 1639.0061 | BS30: -657.9377
L31: Net Change In Cash | M31: NET_CHANGE_IN_CASH_1_YEAR_GROWTH | N31: — | O31: — | P31: — | Q31: 88.8889 | R31: — | S31: — | T31: 56.5789 | U31: — | V31: -12.7273 | W31: — | X31: -24.7863 | Y31: — | Z31: — | AA31: 66.3934 | AB31: 91.8699 | AC31: — | AD31: 33.7278 | AE31: — | AF31: — | AG31: — | AH31: — | AI31: 19.6013 | AJ31: -26.9444 | AK31: — | AL31: — | AM31: — | AN31: — | AO31: — | AP31: 39.0244 | AQ31: -708 | AR31: — | AS31: -78.1182 | AT31: 2071 | AU31: — | AV31: 68.427 | AX31: ROIC | AY31: WACC_RETURN_ON_INV_CAPITAL | AZ31: 12.1761 | BA31: 11.668 | BB31: 9.2289 | BC31: 11.2888 | BD31: 11.5159 | BE31: 8.7207 | BF31: 7.6948 | BG31: 8.5377 | BH31: 8.4953 | BI31: 9.6626 | BJ31: 10.0218 | BK31: 10.641 | BL31: 9.5713 | BM31: 7.5569 | BN31: 8.5372 | BO31: 6.4447 | BP31: 7.1939 | BQ31: 4.5461 | BR31: 14.6216 | BS31: 2.9672
L32: Free Cash Flow | M32: FREE_CASH_FLOW_1_YEAR_GROWTH | N32: — | O32: 26.6667 | P32: 0 | Q32: — | R32: — | S32: — | T32: 132.4742 | U32: -8.8692 | V32: -47.2019 | W32: 99.5392 | X32: — | Y32: 6.8894 | Z32: 54.4843 | AA32: 49.2611 | AB32: — | AC32: — | AD32: — | AE32: — | AF32: — | AG32: -1.9093 | AH32: 185.6448 | AI32: -47.7853 | AJ32: 131.8108 | AK32: -15.9747 | AL32: -49.33 | AM32: 57.686 | AN32: -6.2893 | AO32: -9.6197 | AP32: -20.4208 | AQ32: 122.7061 | AR32: 102.2346 | AS32: 10.2555 | AT32: -17.4131 | AU32: 25.4456 | AV32: 5.3809 | AX32: EVA Spread | AY32: WACC_EVA_SPREAD | AZ32: 4.8706 | BA32: 3.1164 | BB32: 1.02 | BC32: 3.8445 | BD32: 1.6905 | BE32: -0.0795 | BF32: -0.6773 | BG32: 0.3797 | BH32: 0.2404 | BI32: 0.5973 | BJ32: 1.2845 | BK32: 0.9338 | BL32: -2.2053 | BM32: -1.6724 | BN32: 0.5966 | BO32: -3.1189 | BP32: -2.4999 | BQ32: -4.1111 | BR32: 7.8414 | BS32: -3.6467
L33: Cash Flow to Firm | M33: CASH_FLOW_TO_FIRM_1_YEAR_GROWTH | N33: — | O33: — | P33: -9.3578 | Q33: — | R33: — | S33: — | T33: 33.0147 | U33: 15.2637 | V33: -7.6995 | W33: 16.394 | X33: -27.2717 | Y33: -9.3432 | Z33: -12.7258 | AA33: 8.4837 | AB33: 21.3293 | AC33: -22.395 | AD33: 57.7382 | AE33: -18.9131 | AF33: 66.4511 | AG33: 4.779 | AH33: 32.4957 | AI33: -26.04 | AJ33: 50.1543 | AK33: 6.5545 | AL33: -14.0165 | AM33: 9.831 | AN33: 1.7239 | AO33: 0.6279 | AP33: -8.3022 | AQ33: — | AR33: — | AS33: 5.5828 | AT33: -10.7219 | AU33: 16.7964 | AV33: 9.5494 | AX33: Source: Bloomberg | AZ33: Right click to show data transparency (not supported for all values)
L34: Free Cash Flow to Firm | M34: FCF_TO_FIRM_1_YEAR_GROWTH | N34: — | O34: — | P34: 4.3852 | Q34: — | R34: — | S34: — | T34: 73.0784 | U34: -8.0246 | V34: -34.4903 | W34: 94.6433 | X34: — | Y34: -136.5158 | Z34: — | AA34: 45.8919 | AB34: 41.8409 | AC34: -88.4367 | AD34: 1713.8476 | AE34: -61.7966 | AF34: 160.4462 | AG34: -3.1976 | AH34: 122.6573 | AI34: -35.2864 | AJ34: 81.0944 | AK34: -12.5271 | AL34: -37.7477 | AM34: 36.7211 | AN34: -5.5999 | AO34: -7.251 | AP34: -12.5404 | AQ34: — | AR34: — | AS34: 11.0568 | AT34: -14.6206 | AU34: 20.1624 | AV34: 5.1195
L36: 5 Year Growth
L37: Revenue | M37: GEO_GROW_NET_SALES | N37: — | O37: — | P37: — | Q37: — | R37: 1.6621 | S37: 3.3228 | T37: 4.4052 | U37: 5.0643 | V37: 4.0573 | W37: 3.9897 | X37: 1.9949 | Y37: 1.5479 | Z37: -4.8527 | AA37: -5.0994 | AB37: -5.1538 | AC37: -5.174 | AD37: -4.9716 | AE37: 1.0215 | AF37: 3.3575 | AG37: 4.2335 | AH37: 8.2669 | AI37: 2.3746 | AJ37: 4.2976 | AK37: 4.2782 | AL37: 3.2266 | AM37: 1.334 | AN37: 6.9806 | AO37: 2.1179 | AP37: -1.2625 | AQ37: -0.5992 | AR37: 0.3698 | AS37: -1.1832 | AT37: -2.1717 | AU37: 2.4975 | AV37: 5.4195
L38: EBITDA | M38: GEO_GROW_EBITDA | N38: — | O38: — | P38: — | Q38: — | R38: 0.726 | S38: 1.5364 | T38: 6.5704 | U38: 9.5149 | V38: 9.5913 | W38: 8.7651 | X38: 3.4564 | Y38: -7.9734 | Z38: -7.0865 | AA38: -5.9167 | AB38: -4.7982 | AC38: -7.9522 | AD38: 7.6982 | AE38: 11.1449 | AF38: 13.7346 | AG38: 12.1149 | AH38: 25.9491 | AI38: 12.8976 | AJ38: 11.0139 | AK38: 8.1496 | AL38: 7.4977 | AM38: 4.4252 | AN38: 8.4677 | AO38: 3.5861 | AP38: 1.0743 | AQ38: 2.1996 | AR38: 6.2581 | AS38: 6.0754 | AT38: 3.9886 | AU38: 8.656 | AV38: 8.6745
L39: Operating Income | M39: GEO_GROW_OPER_INC | N39: — | O39: — | P39: — | Q39: — | R39: 1.5175 | S39: 0.0879 | T39: 7.2305 | U39: 11.8858 | V39: 12.2513 | W39: 10.4055 | X39: 4.357 | Y39: -14.1958 | Z39: -10.8436 | AA39: -8.862 | AB39: -6.5695 | AC39: -14.3781 | AD39: 11.7813 | AE39: 14.0006 | AF39: 17.4408 | AG39: 14.8902 | AH39: 39.7116 | AI39: 17.8162 | AJ39: 14.6541 | AK39: 10.1703 | AL39: 8.9111 | AM39: 4.6424 | AN39: 9.7409 | AO39: 3.1377 | AP39: -0.4713 | AQ39: 1.4773 | AR39: 6.9909 | AS39: 6.5639 | AT39: 4.0072 | AU39: 10.5427 | AV39: 10.1169
L40: Net Income to Common | M40: NET_INCOME_TO_COMMON_5_YR_GROWTH | N40: — | O40: — | P40: — | Q40: — | R40: -31.8449 | S40: 21.2481 | T40: 8.2322 | U40: 8.7123 | V40: — | W40: 109.0756 | X40: 8.3867 | Y40: -68.5691 | Z40: -1.7773 | AA40: -19.2802 | AB40: -11.9025 | AC40: -14.4555 | AD40: 179.1476 | AE40: 15.1732 | AF40: 34.9214 | AG40: 25.8022 | AH40: 40.8768 | AI40: 27.5174 | AJ40: 6.4218 | AK40: 7.2049 | AL40: 6.8303 | AM40: 6.4182 | AN40: 10.9998 | AO40: 4.7054 | AP40: -1.5802 | AQ40: 24.0914 | AR40: 12.1684 | AS40: 11.5793 | AT40: 7.0479 | AU40: 17.1574 | AV40: -5.3008
L41: EPS Diluted | M41: 5Y_GEO_GROWTH_DILUTED_EPS | N41: — | O41: — | P41: — | Q41: — | R41: -26.404 | S41: 30.0525 | T41: 7.4978 | U41: 7.2175 | V41: — | W41: 108.2399 | X41: 7.7272 | Y41: -68.2818 | Z41: -1.9082 | AA41: -19.009 | AB41: -11.7607 | AC41: -15.0566 | AD41: 173.1296 | AE41: 13.5491 | AF41: 32.5196 | AG41: 24.6148 | AH41: 43.1827 | AI41: 30.6222 | AJ41: 9.954 | AK41: 12.5808 | AL41: 12.4244 | AM41: 10.4499 | AN41: 14.7902 | AO41: 8.1781 | AP41: 1.2619 | AQ41: 27.3253 | AR41: 15.9781 | AS41: 16.7796 | AT41: -9.712 | AU41: 22.7299 | AV41: -0.4719
L42: EPS Diluted before XO | M42: 5Y_GEO_GROWTH_DILUTED_EPS_BEF_XO | N42: — | O42: — | P42: — | Q42: — | R42: — | S42: — | T42: 8.781 | U42: 10.1271 | V42: — | W42: 108.2399 | X42: 7.7272 | Y42: -40.1105 | Z42: -21.4987 | AA42: -19.009 | AB42: -10.0543 | AC42: -24.1539 | AD42: 50.7739 | AE42: 29.3199 | AF42: 32.5196 | AG42: 20.1344 | AH42: 63.318 | AI42: 24.9703 | AJ42: 20.6383 | AK42: 12.5808 | AL42: 14.4049 | AM42: 8.4472 | AN42: 15.1107 | AO42: 8.1781 | AP42: 1.2619 | AQ42: 27.3253 | AR42: 15.9781 | AS42: 16.7796 | AT42: -9.712 | AU42: 22.7299 | AV42: -0.4719
L43: EPS Diluted before Abnormal | M43: GEO_GROW_DILUTED_EPS_CONT_OPS | N43: — | O43: — | P43: — | Q43: — | R43: — | S43: — | T43: 8.781 | U43: 10.1271 | V43: — | W43: 113.0505 | X43: 2.943 | Y43: -45.4837 | Z43: -21.4354 | AA43: -19.009 | AB43: -13.7531 | AC43: -10.6335 | AD43: 65.6342 | AE43: 29.2157 | AF43: 32.5196 | AG43: 22.0979 | AH43: 45.0512 | AI43: 24.9703 | AJ43: 21.1831 | AK43: 12.5808 | AL43: 13.4218 | AM43: 7.7757 | AN43: 15.5353 | AO43: 7.0437 | AP43: 1.1491 | AQ43: 5.8541 | AR43: 15.9306 | AS43: 15.4061 | AT43: -9.3477 | AU43: 20.1362 | AV43: 19.5741
L44: Dividend per Share | M44: GEO_GROW_DVD_PER_SH | N44: — | O44: — | P44: — | Q44: — | R44: 5.5546 | S44: 4.139 | T44: 6.5763 | U44: 5.618 | V44: 7.7818 | W44: 7.2808 | X44: 8.7203 | Y44: 6.3995 | Z44: 5.4578 | AA44: -5.112 | AB44: -18.0164 | AC44: -19.7258 | AD44: -19.7258 | AE44: -18.5563 | AF44: -3.7744 | AG44: 21.9755 | AH44: 30.946 | AI44: 34.4902 | AJ44: 35.7186 | AK44: 32.5452 | AL44: 24.5731 | AM44: 18.1127 | AN44: 16.5188 | AO44: 16.2296 | AP44: 9.8561 | AQ44: 7.6317 | AR44: 8.3244 | AS44: 35.5222 | AT44: -13.0447 | AU44: 9.1607 | AV44: 8.9977
L46: Accounts Receivable | M46: ACCOUNTS_RECEIVABLE_5_YR_GROWTH | N46: — | O46: — | P46: — | Q46: — | R46: -7.1354 | S46: -5.7039 | T46: 1.8237 | U46: 2.7066 | V46: 4.1936 | W46: 10.284 | X46: 6.0962 | Y46: 9.9609 | Z46: 0.429 | AA46: -0.3605 | AB46: -4.1381 | AC46: 5.3078 | AD46: 0.4194 | AE46: 7.1759 | AF46: 5.9826 | AG46: 8.0001 | AH46: -0.9821 | AI46: -3.0053 | AJ46: -3.7482 | AK46: -3.1574 | AL46: -3.9049 | AM46: -1.014 | AN46: 2.5591 | AO46: -0.2225 | AP46: -1.2719 | AQ46: 0.1658 | AR46: -0.8115 | AS46: -2.6723 | AT46: -1.4681 | AU46: 4.1233 | AV46: 6.2426
L47: Inventory | M47: INVENTORY_5_YEAR_GROWTH | N47: — | O47: — | P47: — | Q47: — | R47: -12.2371 | S47: -3.7574 | T47: -2.2972 | U47: -3.0611 | V47: 2.1395 | W47: 3.732 | X47: 2.4863 | Y47: 0.8389 | Z47: 2.1759 | AA47: -2.0947 | AB47: -4.5339 | AC47: -5.4518 | AD47: -5.5912 | AE47: -4.0738 | AF47: -0.1949 | AG47: 5.9224 | AH47: 5.0031 | AI47: 4.2323 | AJ47: 1.8405 | AK47: 3.3038 | AL47: 2.6852 | AM47: 3.0358 | AN47: 6.1044 | AO47: 9.9315 | AP47: 11.1416 | AQ47: 6.3062 | AR47: 0.8582 | AS47: -0.895 | AT47: -2.907 | AU47: -3.5902 | AV47: -1.7252
L48: Fixed Assets | M48: NET_FIXED_ASSETS_5_YEAR_GROWTH | N48: — | O48: — | P48: — | Q48: — | R48: 0.916 | S48: 2.2949 | T48: 2.7311 | U48: 2.4875 | V48: 3.188 | W48: 3.1266 | X48: 3.2275 | Y48: 2.1061 | Z48: 2.2752 | AA48: 1.7298 | AB48: 1.38 | AC48: 1.6601 | AD48: 10.2275 | AE48: 9.7862 | AF48: 10.0331 | AG48: 10.3908 | AH48: 10.5669 | AI48: 2.9485 | AJ48: 3.3715 | AK48: 3.6031 | AL48: 3.6454 | AM48: 3.7635 | AN48: 4.3849 | AO48: 4.8612 | AP48: 4.5187 | AQ48: 4.046 | AR48: 3.2335 | AS48: 2.7271 | AT48: 1.7548 | AU48: 1.4749 | AV48: 1.8114
L49: Total Assets | M49: GEO_GROW_TOT_ASSET | N49: — | O49: — | P49: — | Q49: — | R49: -0.2766 | S49: 0.5978 | T49: 2.2184 | U49: 2.2089 | V49: 5.7992 | W49: 8.8688 | X49: 8.7653 | Y49: 8.588 | Z49: 7.4867 | AA49: 4.1612 | AB49: 0.9769 | AC49: 1.2723 | AD49: 3.4968 | AE49: 3.4106 | AF49: 3.8528 | AG49: 4.0358 | AH49: 3.8532 | AI49: 1.7897 | AJ49: 3.0363 | AK49: 3.1499 | AL49: 3.6664 | AM49: 3.8687 | AN49: 4.2158 | AO49: 4.3063 | AP49: 3.832 | AQ49: 3.1731 | AR49: 2.9356 | AS49: 2.9675 | AT49: 2.7502 | AU49: 2.736 | AV49: 3.2379
L50: Modified Working Capital | M50: MODIFIED_WORKING_CPTL_5YR_GRWTH | N50: — | O50: — | P50: — | Q50: — | R50: — | S50: — | T50: — | U50: — | V50: — | W50: — | X50: — | Y50: — | Z50: — | AA50: — | AB50: 38.2869 | AC50: — | AD50: 23.5036 | AE50: 94.6424 | AF50: 27.9086 | AG50: 19.8671 | AH50: -7.0539 | AI50: -12.6403 | AJ50: -18.0714 | AK50: -11.2856 | AL50: -12.7077 | AM50: -0.229 | AN50: 19.2473 | AO50: 28.048 | AP50: 19.4118 | AQ50: 17.3952 | AR50: -1.3623 | AS50: -18.1997 | AT50: -6.541 | AU50: -0.5629 | AV50: 1.1452
L51: Working Capital | M51: WORKING_CAPITAL_5_YEAR_GROWTH | N51: — | O51: — | P51: — | Q51: — | R51: — | S51: — | T51: — | U51: — | V51: — | W51: — | X51: — | Y51: — | Z51: — | AA51: — | AB51: — | AC51: — | AD51: — | AE51: — | AF51: — | AG51: — | AH51: — | AI51: — | AJ51: — | AK51: — | AL51: — | AM51: — | AN51: -7.9862 | AO51: 22.7997 | AP51: 12.5048 | AQ51: -34.486 | AR51: 29.5683 | AS51: 19.3697 | AT51: 22.2228 | AU51: 29.6902 | AV51: 130.8905
L52: Employees | M52: EMPLOYEES_5_YEAR_GROWTH | N52: — | O52: — | P52: — | Q52: — | R52: -3.1453 | S52: -2.7009 | T52: -4.3637 | U52: -1.788 | V52: -1.0733 | W52: -0.2903 | X52: -0.3923 | Y52: — | Z52: — | AA52: — | AB52: — | AC52: — | AD52: — | AE52: — | AF52: — | AG52: — | AH52: -1.9489 | AI52: -3.442 | AJ52: -3.036 | AK52: -2.9464 | AL52: -1.7763 | AM52: -1.8305 | AN52: 1.2398 | AO52: -0.6757 | AP52: -2.7252 | AQ52: -5.5912 | AR52: -6.2084 | AS52: -8.0792 | AT52: -7.8382 | AU52: -4.9755 | AV52: -1.2456
L53: Accounts Payable | M53: ACCOUNTS_PAYABLE_5_YEAR_GROWTH | N53: — | O53: — | P53: — | Q53: — | R53: 3.4896 | S53: 2.6906 | T53: 1.5371 | U53: 1.6682 | V53: 5.127 | W53: 5.5256 | X53: 5.8066 | Y53: 5.2681 | Z53: -0.7608 | AA53: -4.069 | AB53: -7.4168 | AC53: -7.4206 | AD53: -6.1822 | AE53: -2.4325 | AF53: 0.1651 | AG53: 4.0052 | AH53: 3.305 | AI53: 2.1366 | AJ53: 1.8584 | AK53: 0.8876 | AL53: 0.7668 | AM53: -0.3311 | AN53: -2.6612 | AO53: -6.0899 | AP53: -4.5629 | AQ53: -3.5352 | AR53: -0.1678 | AS53: 4.3003 | AT53: 1.1512 | AU53: 3.6235 | AV53: 5.9349
L54: Short-Term Debt | M54: SHORT_TERM_DEBT_5_YEAR_GROWTH | N54: — | O54: — | P54: — | Q54: — | R54: -7.9037 | S54: -23.6646 | T54: 2.0281 | U54: 12.1719 | V54: 1.8405 | W54: 10.6529 | X54: -1.53 | Y54: 12.4649 | Z54: 7.7542 | AA54: 23.8212 | AB54: 8.5082 | AC54: 8.3209 | AD54: 3.2679 | AE54: 0.3451 | AF54: -13.9129 | AG54: 8.0654 | AH54: -5.6501 | AI54: -36.3776 | AJ54: -8.1362 | AK54: -3.3123 | AL54: -0.1785 | AM54: 10.7428 | AN54: 15.0724 | AO54: -49.5671 | AP54: -8.1744 | AQ54: -52.4301 | AR54: -49.2181 | AS54: 5.7826 | AT54: 86.0634 | AU54: -5.8397 | AV54: 63.2051
L55: Total Debt | M55: TOTAL_DEBT_5_YEAR_GROWTH | N55: — | O55: — | P55: — | Q55: — | R55: -0.1497 | S55: -4.0245 | T55: -0.3789 | U55: -3.3244 | V55: 8.2841 | W55: 14.3775 | X55: 14.3072 | Y55: 17.8548 | Z55: 18.7037 | AA55: 8.318 | AB55: 0.8194 | AC55: 1.7115 | AD55: 0.5914 | AE55: -2.1755 | AF55: -3.4552 | AG55: 0.5719 | AH55: 1.378 | AI55: 1.7795 | AJ55: 7.5178 | AK55: 9.1605 | AL55: 6.2617 | AM55: 4.0571 | AN55: 3.998 | AO55: 3.988 | AP55: 4.0922 | AQ55: 3.7324 | AR55: 9.0821 | AS55: 11.4988 | AT55: 10.3072 | AU55: 8.4068 | AV55: 9.5163
L56: Total Equity | M56: GEO_GROW_TOT_SHRHLDR_EQY | N56: — | O56: — | P56: — | Q56: — | R56: -10.519 | S56: -1.9442 | T56: 1.1654 | U56: 3.6786 | V56: 9.4377 | W56: 14.1504 | X56: 13.0811 | Y56: 9.0584 | Z56: 7.2413 | AA56: 4.1461 | AB56: 1.5958 | AC56: 1.8772 | AD56: 3.4232 | AE56: 5.7404 | AF56: 7.8789 | AG56: 6.8324 | AH56: 4.5166 | AI56: 5.1812 | AJ56: 1.8091 | AK56: -1.0834 | AL56: 0.7196 | AM56: 5.4711 | AN56: 4.9729 | AO56: 6.0463 | AP56: 6.6686 | AQ56: 10.3366 | AR56: 3.6729 | AS56: 1.2003 | AT56: 2.3579 | AU56: 2.9139 | AV56: -3.0252
L57: Total Capital 5 Year Growth | M57: TOTAL_CAPITAL_5_YEAR_GROWTH | N57: — | O57: — | P57: — | Q57: — | R57: -5.7932 | S57: -3.059 | T57: 0.443 | U57: 0.5005 | V57: 8.8652 | W57: 14.2727 | X57: 13.7251 | Y57: 13.4121 | Z57: 12.4246 | AA57: 6.2652 | AB57: 1.1795 | AC57: 1.789 | AD57: 1.8964 | AE57: 1.868 | AF57: 2.4146 | AG57: 3.6997 | AH57: 2.8969 | AI57: 3.4736 | AJ57: 4.4248 | AK57: 3.509 | AL57: 3.3903 | AM57: 4.7832 | AN57: 4.512 | AO57: 5.0394 | AP57: 5.3556 | AQ57: 7.0925 | AR57: 6.3869 | AS57: 6.4937 | AT57: 6.4264 | AU57: 5.755 | AV57: 3.3152
L58: Book Value per Share | M58: GEO_GROW_BOOK_VAL | N58: — | O58: — | P58: — | Q58: — | R58: -1.6546 | S58: 0.0858 | T58: 1.3996 | U58: 2.322 | V58: 8.1854 | W58: 12.9371 | X58: 12.1569 | Y58: 8.1446 | Z58: 7.0142 | AA58: 4.4559 | AB58: 1.9364 | AC58: 2.0705 | AD58: 3.7015 | AE58: 5.2054 | AF58: 7.362 | AG58: 7.9362 | AH58: 6.5559 | AI58: 7.1094 | AJ58: 5.1925 | AK58: 3.4284 | AL58: 4.4106 | AM58: 8.6295 | AN58: 8.6589 | AO58: 9.0508 | AP58: 9.3201 | AQ58: 13.4118 | AR58: 8.123 | AS58: 6.3742 | AT58: -13.8497 | AU58: 7.874 | AV58: 2.0776
L60: Cash From Operations | M60: GEO_GROW_CASH_OPER_ACT | N60: — | O60: — | P60: — | Q60: — | R60: -4.929 | S60: 3.4739 | T60: 5.6581 | U60: 12.004 | V60: 10.7054 | W60: 10.6574 | X60: 0.7778 | Y60: -4.1815 | Z60: -14.6433 | AA60: -10.4989 | AB60: -6.2716 | AC60: -4.2693 | AD60: 6.1881 | AE60: 9.3485 | AF60: 20.0019 | AG60: 14.1473 | AH60: 29.3739 | AI60: 7.1149 | AJ60: 24.0525 | AK60: 11.1478 | AL60: 6.1686 | AM60: 2.3133 | AN60: 10.3936 | AO60: 0.6597 | AP60: -2.7223 | AQ60: 3.3402 | AR60: 7.2735 | AS60: 7.7261 | AT60: 4.8135 | AU60: 10.8903 | AV60: 10.1072
L61: Free Cash Flow | M61: FREE_CASH_FLOW_5_YEAR_GROWTH | N61: — | O61: — | P61: — | Q61: — | R61: — | S61: — | T61: — | U61: — | V61: 155.3207 | W61: — | X61: — | Y61: — | Z61: — | AA61: — | AB61: — | AC61: — | AD61: — | AE61: — | AF61: — | AG61: — | AH61: — | AI61: 8.0621 | AJ61: — | AK61: 23.2986 | AL61: 8.0395 | AM61: -4.0652 | AN61: 7.8389 | AO61: -10.677 | AP61: -11.6429 | AQ61: 18.8058 | AR61: 24.8677 | AS61: 28.9948 | AT61: 26.6892 | AU61: 38.7621 | AV61: 19.475
L62: Cash Flow to Firm | M62: CASH_FLOW_TO_FIRM_5_YEAR_GROWTH | N62: — | O62: — | P62: — | Q62: — | R62: — | S62: — | T62: — | U62: — | V62: — | W62: — | X62: 3.6779 | Y62: -3.9746 | Z62: -9.1709 | AA62: -6.1883 | AB62: -5.4059 | AC62: -4.1701 | AD62: 7.0554 | AE62: 5.4925 | AF62: 14.9227 | AG62: 11.6009 | AH62: 24.2024 | AI62: 6.7437 | AJ62: 20.7423 | AK62: 10.4375 | AL62: 6.156 | AM62: 2.2467 | AN62: 8.9769 | AO62: 0.5937 | AP62: -2.3824 | AQ62: — | AR62: — | AS62: — | AT62: — | AU62: — | AV62: —
L63: Free Cash Flow to Firm | M63: FCF_TO_FIRM_5_YEAR_GROWTH | N63: — | O63: — | P63: — | Q63: — | R63: — | S63: — | T63: — | U63: — | V63: — | W63: — | X63: — | Y63: — | Z63: — | AA63: — | AB63: — | AC63: — | AD63: — | AE63: 10.643 | AF63: 24.2399 | AG63: 15.1007 | AH63: 107.9643 | AI63: 6.7745 | AJ63: 45.7566 | AK63: 17.1816 | AL63: 7.2786 | AM63: -2.691 | AN63: 4.9418 | AO63: -8.2029 | AP63: -8.2056 | AQ63: — | AR63: — | AS63: — | AT63: — | AU63: — | AV63: —
L65: Sequential Growth
L66: Revenue | M66: REVENUE_SEQUENTIAL_GROWTH | N66: -5.6074 | O66: 2.0153 | P66: 5.9393 | Q66: 5.2529 | R66: 1.1348 | S66: 2.3586 | T66: 7.472 | U66: 9.3256 | V66: 0.3046 | W66: 0.8068 | X66: -7.0897 | Y66: 5.1378 | Z66: -21.0506 | AA66: -0.9889 | AB66: 0.5179 | AC66: -7.1884 | AD66: 6.2649 | AE66: 7.1891 | AF66: 11.0002 | AG66: 4.8505 | AH66: 12.2134 | AI66: -19.6713 | AJ66: 17.6419 | AK66: 10.897 | AL66: -0.3306 | AM66: 2.2967 | AN66: 5.3467 | AO66: -6.7724 | AP66: -6.2823 | AQ66: 3.0626 | AR66: 7.3808 | AS66: -2.5551 | AT66: -11.3429 | AU66: 18.3218 | AV66: 18.6152
L67: EBITDA | M67: EBITDA_SEQUENTIAL_GROWTH | N67: -4.378 | O67: -4.3605 | P67: -2.1277 | Q67: 5.2019 | R67: 10.1107 | S67: -0.4692 | T67: 21.8182 | U67: 12.1614 | V67: 5.5692 | W67: 6.0224 | X67: -22.5011 | Y67: -32.1591 | Z67: 17.6717 | AA67: 12.3843 | AB67: 12.4763 | AC67: -34.5158 | AD67: 48.7532 | AE67: 37.7457 | AF67: 26.1016 | AG67: 4.6922 | AH67: 17.1647 | AI67: -13.9175 | AJ67: 26.6309 | AK67: 10.6521 | AL67: 1.5744 | AM67: 1.3508 | AN67: 4.0856 | AO67: 0.5877 | AP67: -2.1285 | AQ67: 7.3561 | AR67: 23.138 | AS67: 3.1935 | AT67: -8.9247 | AU67: 21.8981 | AV67: 7.4476
L68: Operating Income | M68: OPERATING_INCOME_SEQ_GROWTH | N68: 1.5642 | O68: -4.4004 | P68: -6.214 | Q68: 4.7853 | R68: 12.9977 | S68: -5.3886 | T68: 34.9398 | U68: 15.9903 | V68: 6.508 | W68: 4.0079 | X68: -28.6166 | Y68: -49.292 | Z68: 40.4887 | AA68: 18.882 | AB68: 17.7638 | AC68: -53.8598 | AD68: 92.3077 | AE68: 55 | AF68: 37.9355 | AG68: 5.5192 | AH68: 22.695 | AI68: -17.9913 | AJ68: 35.2863 | AK68: 12.9925 | AL68: -0.3746 | AM68: 0.4628 | AN68: 4.0311 | AO68: -0.8027 | AP68: -5.4408 | AQ68: 9.7669 | AR68: 30.8871 | AS68: 1.9717 | AT68: -12.145 | AU68: 28.2439 | AV68: 7.6689
L69: Net Income to Common | M69: NET_INCOME_TO_COMMON_SEQ_GROWTH | N69: 0.7353 | O69: 220.438 | P69: -7.2893 | Q69: -166.8305 | R69: — | S69: 1695 | T69: 81.6156 | U69: -5.2147 | V69: 38.3495 | W69: -6.5497 | X69: -32.791 | Y69: -99.6276 | Z69: 28150 | AA69: -48.1416 | AB69: 44.7099 | AC69: -41.9811 | AD69: 37.8049 | AE69: 237.7581 | AF69: 14.4105 | AG69: 1.9847 | AH69: 2.1707 | AI69: -16.2637 | AJ69: 36.7454 | AK69: 18.682 | AL69: 0.2156 | AM69: 0.2152 | AN69: 3.3816 | AO69: 2.1288 | AP69: -12.9131 | AQ69: 219.3228 | AR69: -39.5247 | AS69: 0.6953 | AT69: -16.9919 | AU69: 36.745 | AV69: 10.1825
L70: EPS Diluted | M70: EPS_DILUTED_SEQUENTIAL_GROWTH | N70: 5.6818 | O70: 366.6667 | P70: -4.3779 | Q70: -165.0602 | R70: — | S70: 1721.0526 | T70: 80.0578 | U70: -5.618 | V70: 34.6939 | W70: -6.0606 | X70: -32.5269 | Y70: -99.6016 | Z70: 26600 | AA70: -48.3146 | AB70: 44.2029 | AC70: -44.2211 | AD70: 36.9369 | AE70: 231.5789 | AF70: 11.9048 | AG70: 6.0284 | AH70: 11.7057 | AI70: -13.4731 | AJ70: 40.1384 | AK70: 25.9259 | AL70: 5.2941 | AM70: 2.2346 | AN70: 4.918 | AO70: 4.1667 | AP70: -9.5 | AQ70: 230.9392 | AR70: -35.8932 | AS70: 8.5938 | AT70: -71.223 | AU70: 320 | AV70: 16.0714
L71: EPS Diluted before XO | M71: EPS_DIL_BEF_EXTRAORD_SEQ_GRWTH | N71: -111.8705 | O71: — | P71: -11.2469 | Q71: -120.6612 | R71: — | S71: 1721.0526 | T71: 80.0578 | U71: -5.618 | V71: 34.6939 | W71: -6.0606 | X71: -32.5269 | Y71: -90.4382 | Z71: 265.1921 | AA71: 57.4514 | AB71: 58.6957 | AC71: -71.2329 | AD71: 196.8254 | AE71: 69.5187 | AF71: 77.918 | AG71: -2.8369 | AH71: 33.5766 | AI71: -22.1311 | AJ71: 42.1053 | AK71: 25.9259 | AL71: 5.2941 | AM71: 2.2346 | AN71: 4.918 | AO71: 4.1667 | AP71: -9.5 | AQ71: 230.9392 | AR71: -35.8932 | AS71: 8.5938 | AT71: -71.223 | AU71: 320 | AV71: 16.0714
L72: EPS Diluted before Abnormal | M72: EPS_DILUTED_BEF_ABNRML_SEQ_GRWTH | N72: -111.8705 | O72: — | P72: -11.2469 | Q72: -120.6612 | R72: — | S72: 1721.0526 | T72: 80.0578 | U72: -5.618 | V72: 34.6939 | W72: 5.303 | X72: -52.0384 | Y72: -92.5 | Z72: 486.6667 | AA72: 56.8182 | AB72: 44.2029 | AC72: -42.7136 | AD72: 64.0351 | AE72: 69.5187 | AF72: 77.918 | AG72: -4.2553 | AH72: 35.5556 | AI72: -22.1311 | AJ72: 45.3434 | AK72: 23.1204 | AL72: -0.625 | AM72: 5.0118 | AN72: 10.2385 | AO72: -0.7736 | AP72: -7.2455 | AQ72: 24.7399 | AR72: 65.4584 | AS72: 7.7674 | AT72: -70.326 | AU72: 279.1495 | AV72: 21.849
L73: Dividend per Share | M73: DPS_SEQUENTIAL_GROWTH | N73: 11.2069 | O73: -0.7752 | P73: 9.375 | Q73: 2.1429 | R73: 6.2937 | S73: 3.9474 | T73: 11.3924 | U73: 4.5455 | V73: 13.0435 | W73: 3.8462 | X73: 11.1111 | Y73: 0 | Z73: 0 | AA73: -33.3333 | AB73: -50 | AC73: 0 | AD73: 0 | AE73: 7.5 | AF73: 53.4884 | AG73: 63.6364 | AH73: 42.5926 | AI73: 14.2857 | AJ73: 12.5 | AK73: 36.3636 | AL73: 20 | AM73: 9.2593 | AN73: 6.7797 | AO73: 11.1111 | AP73: 2.8571 | AQ73: 8.3333 | AR73: 12.8205 | AS73: 227.2727 | AT73: -87.9167 | AU73: 220.6896 | AV73: 7.5269
L75: Accounts Receivable | M75: ACCOUNTS_RECEIVABLE_SEQ_GROWTH | N75: 2.2831 | O75: -28.0134 | P75: 12.8682 | Q75: 0 | R75: -16.8956 | S75: 10.4132 | T75: 5.6886 | U75: 17.847 | V75: 7.4519 | W75: 10.4027 | X75: -9.0172 | Y75: 26.392 | Z75: -25.1101 | AA75: 3.2941 | AB75: -8.9977 | AC75: 45.5569 | AD75: -0.3439 | AE75: 3.7101 | AF75: -2.3295 | AG75: 0 | AH75: -5.707 | AI75: -10.1174 | AJ75: -0.201 | AK75: 0.7049 | AL75: -3.8 | AM75: 9.3555 | AN75: 7.3194 | AO75: -13.0204 | AP75: -4.4807 | AQ75: 3.4115 | AR75: 4.1237 | AS75: -2.3762 | AT75: -7.5051 | AU75: 25.8772 | AV75: 14.3728
L76: Inventory | M76: INVENTORY_SEQUENTIAL_GROWTH | N76: -33.6088 | O76: -1.6598 | P76: 8.4388 | Q76: -19.8444 | R76: -8.2524 | S76: 5.291 | T76: 6.0302 | U76: 4.2654 | V76: 4.0909 | W76: -0.8734 | X76: -0.8811 | Y76: -2.2222 | Z76: 11.3636 | AA76: -15.9184 | AB76: -12.6214 | AC76: -5.5556 | AD76: -2.9412 | AE76: 20.6061 | AF76: 2.5126 | AG76: 17.6471 | AH76: -9.5833 | AI76: -6.4516 | AJ76: 7.3892 | AK76: 10.0917 | AL76: 14.1667 | AM76: -8.0292 | AN76: 8.3333 | AO76: 28.2051 | AP76: 16.2857 | AQ76: -8.5995 | AR76: -29.3011 | AS76: -0.7605 | AT76: 15.7088 | AU76: 12.2517 | AV76: 0.59
L77: Fixed Assets | M77: FIXED_ASSETS_SEQUENTIAL_GROWTH | N77: -5.2253 | O77: 0.218 | P77: 3.5122 | Q77: 1.8617 | R77: 4.5102 | S77: 1.4291 | T77: 2.373 | U77: 2.2908 | V77: 5.3908 | W77: 4.1996 | X77: 1.9265 | Y77: -3.0684 | Z77: 3.1411 | AA77: 2.6103 | AB77: 2.4206 | AC77: 3.3419 | AD77: 45.2658 | AE77: 1.093 | AF77: 3.7693 | AG77: 4.096 | AH77: 4.169 | AI77: 1.6573 | AJ77: 3.1868 | AK77: 4.9372 | AL77: 4.3085 | AM77: 4.7639 | AN77: 4.7378 | AO77: 5.5626 | AP77: 3.2346 | AQ77: 1.9711 | AR77: 0.7367 | AS77: 2.1939 | AT77: 0.6606 | AU77: 1.8228 | AV77: 3.6729
L78: Total Assets | M78: TOTAL_ASSETS_SEQUENTIAL_GROWTH | N78: -1.5494 | O78: -5.5888 | P78: 4.1145 | Q78: -0.0469 | R78: 1.9612 | S78: 2.8431 | T78: 2.2653 | U78: 4.0659 | V78: 18.7859 | W78: 17.6363 | X78: 2.3551 | Y78: 1.4344 | Z78: -1.1052 | AA78: 1.5129 | AB78: 0.7211 | AC78: 3.8614 | AD78: 13.0744 | AE78: -1.516 | AF78: 3.7017 | AG78: 1.6117 | AH78: 2.9529 | AI78: 2.2786 | AJ78: 4.664 | AK78: 4.2749 | AL78: 4.1814 | AM78: 3.9613 | AN78: 3.9991 | AO78: 5.1191 | AP78: 1.9255 | AQ78: 0.9177 | AR78: 2.7701 | AS78: 4.1602 | AT78: 4.015 | AU78: 1.8546 | AV78: 3.4073
L79: Modified Working Capital | M79: MODIFIED_WORKING_CPTL_SEQ_GRWTH | N79: -30.4167 | O79: -92.8144 | P79: -295.8333 | Q79: — | R79: -1437.5 | S79: — | T79: — | U79: — | V79: — | W79: — | X79: -365.7143 | Y79: — | Z79: -89.8734 | AA79: 637.5 | AB79: 50 | AC79: 185.8757 | AD79: -10.2767 | AE79: -1.5419 | AF79: -9.6197 | AG79: 8.4158 | AH79: -19.863 | AI79: -34.188 | AJ79: -28.5714 | AK79: 34.5455 | AL79: 0 | AM79: 56.3063 | AN79: 60.5187 | AO79: 1.9749 | AP79: -5.1056 | AQ79: -8.1633 | AR79: -34.5455 | AS79: -37.037 | AT79: 98.5294 | AU79: 29.3827 | AV79: 0
L80: Working Capital | M80: WORKING_CAPITAL_SEQ_GROWTH | N80: -227.2358 | O80: — | P80: — | Q80: — | R80: — | S80: — | T80: — | U80: — | V80: — | W80: — | X80: — | Y80: — | Z80: — | AA80: — | AB80: — | AC80: — | AD80: — | AE80: — | AF80: — | AG80: -220 | AH80: — | AI80: — | AJ80: -54.8936 | AK80: -22.0126 | AL80: -29.8387 | AM80: 2.2989 | AN80: 161.236 | AO80: 90.9677 | AP80: -49.6622 | AQ80: -95.302 | AR80: 2995.2381 | AS80: 73.3846 | AT80: 114.9068 | AU80: -32.2874 | AV80: -15.9756
L81: Employees | M81: EMPLOYEES_SEQUENTIAL_GROWTH | N81: -3.3611 | O81: -1.6139 | P81: -3.1264 | Q81: -2.9162 | R81: -4.6839 | S81: -1.124 | T81: -9.738 | U81: 10.6403 | V81: 0.6681 | W81: -0.8518 | X81: -1.6286 | Y81: — | Z81: — | AA81: -3.8717 | AB81: — | AC81: — | AD81: -4.4488 | AE81: -2.3628 | AF81: 2.8571 | AG81: -2.7778 | AH81: -2.8571 | AI81: -11.5059 | AJ81: -0.2925 | AK81: 3.3333 | AL81: 3.2258 | AM81: -3.125 | AN81: 3.2258 | AO81: -9.375 | AP81: -6.8966 | AQ81: -11.1111 | AR81: -6.25 | AS81: -6.6667 | AT81: -8.181 | AU81: 8.4898 | AV81: 7.7585
L82: Accounts Payable | M82: ACCOUNTS_PAYABLE_SEQ_GROWTH | N82: 5.7971 | O82: 6.8493 | P82: 20.2797 | Q82: -10.2713 | R82: -2.6998 | S82: 1.7758 | T82: 0.9815 | U82: 21.0583 | V82: 6.066 | W82: -0.841 | X82: 3.1383 | Y82: -1.5625 | Z82: -9.858 | AA82: -10.4727 | AB82: -16.9772 | AC82: 3.1172 | AD82: 5.1995 | AE82: 9.6552 | AF82: 2.0964 | AG82: 0.2053 | AH82: -0.3074 | AI82: -0.6166 | AJ82: 8.1696 | AK82: -2.6769 | AL82: -0.3929 | AM82: -5.6213 | AN82: -11.7032 | AO82: -9.5858 | AP82: 5.4974 | AQ82: 5.0868 | AR82: 12.0425 | AS82: 9.9052 | AT82: -22.4353 | AU82: 19.0358 | AV82: 17.3416
L83: Short-Term Debt | M83: ST_DEBT_SEQUENTIAL_GROWTH | N83: 270.2786 | O83: -61.204 | P83: -23.0603 | Q83: 11.4846 | R83: -46.2312 | S83: 44.8598 | T83: 65.4839 | U83: 23.5867 | V83: -31.2303 | W83: -18.578 | X83: -19.1549 | Y83: 221.6028 | Z83: -0.2167 | AA83: 37.785 | AB83: -57.9196 | AC83: -19.8502 | AD83: 153.271 | AE83: -13.5609 | AF83: -35.9658 | AG83: 31.1667 | AH83: -59.3393 | AI83: -64.6875 | AJ83: 442.4779 | AK83: -17.292 | AL83: 53.8462 | AM83: -31.6667 | AN83: -57.2233 | AO83: -91.2281 | AP83: 1555 | AQ83: -94.2598 | AR83: -5.2632 | AS83: 1577.7778 | AT83: 47.6821 | AU83: -45.0673 | AV83: -10.2041
L84: Total Debt | M84: TOTAL_DEBT_SEQUENTIAL_GROWTH | N84: 21.3199 | O84: -24.527 | P84: 5.9856 | Q84: -5.3223 | R84: 8.0262 | S84: -0.4626 | T84: -9.0619 | U84: -8.7831 | V84: 66.9118 | W84: 42.039 | X84: -0.768 | Y84: 5.9533 | Z84: -5.4502 | AA84: 5.601 | AB84: -0.7738 | AC84: 3.7006 | AD84: 0.2461 | AE84: -17.7578 | AF84: -1.1277 | AG84: 21.7209 | AH84: 7.9234 | AI84: 2.2472 | AJ84: 8.1918 | AK84: 6.6597 | AL84: 6.3954 | AM84: -2.8173 | AN84: 1.9571 | AO84: 8.14 | AP84: 7.1951 | AQ84: 4.5692 | AR84: 24.964 | AS84: 13.763 | AT84: 2.4839 | AU84: -1.7262 | AV84: 10.0308
L85: Total Equity | M85: TOTAL_EQUITY_SEQUENTIAL_GROWTH | N85: -32.3563 | O85: 0.3706 | P85: 0.568 | Q85: -10.1384 | R85: -6.5053 | S85: 6.8908 | T85: 17.327 | U85: 13.6961 | V85: 17.7511 | W85: 15.4354 | X85: 1.9771 | Y85: -2.1088 | Z85: 4.5344 | AA85: 1.7118 | AB85: 1.9771 | AC85: 3.3969 | AD85: 5.5478 | AE85: 16.7817 | AF85: 12.4214 | AG85: -2.8741 | AH85: -7.3345 | AI85: 8.9463 | AJ85: -0.7755 | AK85: -2.6667 | AL85: 6.3061 | AM85: 16.6852 | AN85: 6.3976 | AO85: 4.4023 | AP85: 0.2228 | AQ85: 25.8851 | AR85: -14.5438 | AS85: -5.6995 | AT85: 10.5117 | AU85: 2.9748 | AV85: -6.4815
L86: Capital | M86: TOTAL_CAPITAL_SEQUENTIAL_GROWTH | N86: -10.7831 | O86: -13.2368 | P86: 3.1436 | Q86: -7.7856 | R86: 0.7832 | S86: 2.9375 | T86: 3.6086 | U86: 3.4392 | V86: 37.5317 | W86: 28.4266 | X86: 0.4945 | Y86: 2.1907 | Z86: -0.9864 | AA86: 3.7653 | AB86: 0.4989 | AC86: 3.558 | AD86: 2.7312 | AE86: -1.1242 | AF86: 6.5789 | AG86: 6.9646 | AH86: -0.3889 | AI86: 5.6423 | AJ86: 3.505 | AK86: 1.9869 | AL86: 6.3527 | AM86: 6.5042 | AN86: 4.2824 | AO86: 6.143 | AP86: 3.5311 | AQ86: 15.4131 | AR86: 3.0418 | AS86: 4.8067 | AT86: 5.8078 | AU86: 0.3068 | AV86: 2.6999
L87: Book Value per Share | M87: BPS_SEQUENTIAL_GROWTH | N87: -2.7611 | O87: 9.3674 | P87: 8.1205 | Q87: -13.5072 | R87: -7.4974 | S87: 6.1532 | T87: 16.7366 | U87: 13.1284 | V87: 14.2818 | W87: 14.6819 | X87: 2.5365 | Y87: -2.7026 | Z87: 7.3382 | AA87: 1.2596 | AB87: 1.5026 | AC87: 3.2123 | AD87: 5.3235 | AE87: 15.3506 | AF87: 12.0727 | AG87: 4.2461 | AH87: -3.2205 | AI87: 8.0876 | AJ87: 5.3911 | AK87: 2.9855 | AL87: 9.2907 | AM87: 17.9772 | AN87: 8.2344 | AO87: 7.3054 | AP87: 4.2633 | AQ87: 31.3331 | AR87: -7.0827 | AS87: -0.24 | AT87: -62.6126 | AU87: 220.9453 | AV87: -0.3578
L89: Cash From Operations | M89: CFO_SEQUENTIAL_GROWTH | N89: -32.9198 | O89: 24.1677 | P89: -11.718 | Q89: -2.5872 | R89: 8.4296 | S89: 2.4494 | T89: 37.8378 | U89: 18.175 | V89: -8.1047 | W89: 8.1944 | X89: -35.8151 | Y89: 7.1 | Z89: -33.7068 | AA89: 16.4789 | AB89: 36.2757 | AC89: -28.6602 | AD89: 79.8507 | AE89: -23.2365 | AF89: 85.4054 | AG89: 6.1224 | AH89: 33.4249 | AI89: -30.0275 | AJ89: 59.9313 | AK89: 7.0531 | AL89: -15.6116 | AM89: 10.8961 | AN89: 2.3263 | AO89: 0.8077 | AP89: -9.7626 | AQ89: 14.173 | AR89: 33.6694 | AS89: 4.5033 | AT89: -12.1031 | AU89: 19.6106 | AV89: 10.1981
L90: Capital Expenditures | M90: CAPEX_SEQUENTIAL_GROWTH | N90: 49.5695 | O90: 7.2368 | P90: -9.0491 | Q90: -27.1501 | R90: 20.4861 | S90: -26.2248 | T90: 13.9323 | U90: 32.1143 | V90: 5.7958 | W90: -8.0131 | X90: 31.4667 | Y90: 2.5693 | Z90: -39.8154 | AA90: 1.862 | AB90: 16.129 | AC90: -1.9444 | AD90: -2.7384 | AE90: 10.2913 | AF90: 44.2782 | AG90: 8.1757 | AH90: -1.8613 | AI90: -18.046 | AJ90: 29.0323 | AK90: 24.837 | AL90: 1.9155 | AM90: -1.1961 | AN90: 5.8798 | AO90: 4.6141 | AP90: -6.4012 | AQ90: -14.9291 | AR90: -14.4608 | AS90: -5.043 | AT90: -1.8709 | AU90: 10.1476 | AV90: 19.0955
L91: Net Change In Cash | M91: NET_CHANGE_IN_CASH_SEQ_GROWTH | N91: -155.1167 | O91: — | P91: -307.6923 | Q91: — | R91: — | S91: -190.4762 | T91: — | U91: — | V91: -12.7273 | W91: -343.75 | X91: — | Y91: — | Z91: -170.2495 | AA91: — | AB91: — | AC91: — | AD91: 33.7278 | AE91: -194.2478 | AF91: — | AG91: -161.1842 | AH91: — | AI91: 19.6013 | AJ91: -26.9444 | AK91: -293.5361 | AL91: — | AM91: -19300 | AN91: — | AO91: -153.2468 | AP91: — | AQ91: — | AR91: — | AS91: -78.1182 | AT91: 2071 | AU91: -140.9949 | AV91: —
L92: Free Cash Flow | M92: FREE_CASH_FLOW_SEQUENTIAL_GROWTH | N92: -202.2727 | O92: — | P92: — | Q92: — | R92: -5200 | S92: — | T92: 132.4742 | U92: -8.8692 | V92: -47.2019 | W92: 99.5392 | X92: -210.6236 | Y92: — | Z92: — | AA92: — | AB92: — | AC92: -642.5532 | AD92: — | AE92: -106.25 | AF92: — | AG92: -1.9093 | AH92: 185.6448 | AI92: -47.7853 | AJ92: 131.8108 | AK92: -15.9747 | AL92: -49.33 | AM92: 57.686 | AN92: -6.2893 | AO92: -9.6197 | AP92: -20.4208 | AQ92: 122.7061 | AR92: 102.2346 | AS92: 10.2555 | AT92: -17.4131 | AU92: 25.4456 | AV92: 5.3809
L93: Cash Flow to Firm | M93: CF_TO_FIRM_SEQUENTIAL_GROWTH | N93: — | O93: — | P93: -9.3578 | Q93: — | R93: — | S93: — | T93: 33.0147 | U93: 15.2637 | V93: -7.6995 | W93: 16.394 | X93: -27.2717 | Y93: -9.3432 | Z93: -12.7258 | AA93: 8.4837 | AB93: 21.3293 | AC93: -22.395 | AD93: 57.7382 | AE93: -18.9131 | AF93: 66.4511 | AG93: 4.779 | AH93: 32.4957 | AI93: -26.04 | AJ93: 50.1543 | AK93: 6.5545 | AL93: -14.0165 | AM93: 9.831 | AN93: 1.7239 | AO93: 0.6279 | AP93: -8.3022 | AQ93: — | AR93: — | AS93: 5.5828 | AT93: -10.7219 | AU93: 16.7964 | AV93: 9.5494
L94: Free Cash Flow to Firm | M94: FCF_TO_FIRM_SEQUENTIAL_GROWTH | N94: — | O94: — | P94: — | Q94: — | R94: — | S94: — | T94: 73.0784 | U94: -8.0246 | V94: -34.4903 | W94: 94.6433 | X94: -116.2681 | Y94: — | Z94: — | AA94: 45.8919 | AB94: 41.8409 | AC94: -88.4367 | AD94: 1713.8476 | AE94: -61.7966 | AF94: 160.4462 | AG94: -3.1976 | AH94: 122.6573 | AI94: -35.2864 | AJ94: 81.0944 | AK94: -12.5271 | AL94: -37.7477 | AM94: 36.7211 | AN94: -5.5999 | AO94: -7.251 | AP94: -12.5404 | AQ94: — | AR94: — | AS94: 11.0568 | AT94: -14.6206 | AU94: 20.1624 | AV94: 5.1195
L95: Source: Bloomberg | N95: Right click to show data transparency (not supported for all values)

Sheet IS
A1: CSX Corp (CSX US) - BBG Adjusted
A3: In Millions of USD except Per Share | C3: FY 2018 | D3: FY 2019 | E3: FY 2020 | F3: FY 2021 | G3: FY 2022 | H3: Last 12M | I3: FY 2023 Est | J3: FY 2024 Est
A4: 12 Months Ending | C4: 12/31/2018 | D4: 12/31/2019 | E4: 12/31/2020 | F4: 12/31/2021 | G4: 12/31/2022 | H4: 09/30/2023 | I4: 12/31/2023 | J4: 12/31/2024
A5: Revenue | B5: SALES_REV_TURN | C5: 12250 | D5: 11937 | E5: 10583 | F5: 12522 | G5: 14853 | H5: 14707 | I5: 14614.154 | J5: 14995.846
A6: + Sales & Services Revenue | B6: IS_SALES_AND_SERVICES_REVENUES | C6: 11668 | D6: 10809 | E6: 9810 | F6: 11120 | G6: 12430 | H6: 12692
A7: + Other Revenue | B7: IS_OTHER_REVENUE | C7: 582 | D7: 1128 | E7: 773 | F7: 1402 | G7: 2423 | H7: 2015
A8: Gross Profit | B8: GROSS_PROFIT | C8: — | D8: — | E8: — | F8: — | G8: — | I8: 5557.1782 | J8: 5787.6468
A9: + Other Operating Income | B9: IS_OTHER_OPER_INC | C9: 96 | D9: 0 | E9: 0 | F9: 0 | G9: 0 | H9: 0
A10: - Operating Expenses | B10: IS_OPERATING_EXPN | C10: 7631 | D10: 7101 | E10: 6256 | F10: 7382 | G10: 9068 | H10: 9088
A11: + Research & Development | B11: IS_OPERATING_EXPENSES_RD | C11: 0 | D11: 0 | E11: 0 | F11: 0 | G11: 0
A12: + Depreciation & Amortization | B12: IS_DEPRECIATION_AND_AMORTIZATION | C12: 1331 | D12: 1349 | E12: 1383 | F12: 1420 | G12: 1500 | H12: 1587
A13: + Other Operating Expense | B13: IS_OTHER_OPERATING_EXPENSES | C13: 6300 | D13: 5752 | E13: 4873 | F13: 5962 | G13: 7568 | H13: 7501
A14: Operating Income (Loss) | B14: IS_OPER_INC | C14: 4715 | D14: 4836 | E14: 4327 | F14: 5140 | G14: 5785 | H14: 5619 | I14: 5555.68 | J14: 5758.5
A15: - Non-Operating (Income) Loss | B15: IS_NONOP_INCOME_LOSS | C15: 565 | D15: 649 | E15: 735 | F15: 643 | G15: 609 | H15: 654
A16: + Interest Expense, Net | B16: IS_NET_INTEREST_EXPENSE | C16: 607 | D16: 689 | E16: 754 | F16: 722 | G16: 742
A17: + Interest Expense | B17: IS_INT_EXPENSE | C17: 639 | D17: 737 | E17: 754 | F17: 722 | G17: 742 | H17: 804
A18: - Interest Income | B18: IS_INT_INC | C18: 32 | D18: 48 | E18: 0 | F18: 0 | G18: 0
A19: + Foreign Exch (Gain) Loss | B19: IS_FOREIGN_EXCH_LOSS | C19: 0 | D19: 0 | E19: 0 | F19: 0 | G19: 0
A20: + Other Non-Op (Income) Loss | B20: IS_OTHER_NON_OPERATING_INC_LOSS | C20: -42 | D20: -40 | E20: -19 | F20: -79 | G20: -133 | H20: -150
A21: Pretax Income (Loss), Adjusted | B21: PRETAX_INC | C21: 4150 | D21: 4187 | E21: 3592 | F21: 4497 | G21: 5176 | H21: 4965 | I21: 4886.12 | J21: 5064.36
A22: - Abnormal Losses (Gains) | B22: IS_ABNORMAL_ITEM | C22: -154 | D22: -129 | E22: -35 | F22: -454 | G22: -238 | H22: -81
A23: + Disposal of Assets | B23: IS_GAIN_LOSS_DISPOSAL_ASSETS | C23: -154 | D23: -151 | E23: -35 | F23: -454 | G23: -238 | H23: -81
A24: + Early Extinguishment of Debt | B24: IS_G_L_ON_EXT_DBT_OR_SETTLE_DBT | C24: — | D24: — | E24: — | F24: — | G24: —
A25: + Asset Write-Down | B25: IS_IMPAIRMENT_ASSETS | C25: — | D25: 22 | E25: — | F25: — | G25: —
A26: + Restructuring | B26: IS_RESTRUCTURING_EXPENSES | C26: — | D26: — | E26: — | F26: — | G26: —
A27: + Other Abnormal Items | B27: IS_OTHER_ONE_TIME_ITEMS | C27: — | D27: — | E27: — | F27: — | G27: —
A28: Pretax Income (Loss), GAAP | B28: PRETAX_INC | C28: 4304 | D28: 4316 | E28: 3627 | F28: 4951 | G28: 5414 | H28: 5046 | I28: 4886.12 | J28: 5064.36
A29: - Income Tax Expense (Benefit) | B29: IS_INC_TAX_EXP | C29: 995 | D29: 985 | E29: 862 | F29: 1170 | G29: 1248 | H29: 1199
A30: + Current Income Tax | B30: IS_CURRENT_INCOME_TAX_BENEFIT | C30: 716 | D30: 712 | E30: 682 | F30: 1003 | G30: 1131
A31: + Deferred Income Tax | B31: IS_DEFERRED_INCOME_TAX_BENEFIT | C31: 279 | D31: 273 | E31: 180 | F31: 167 | G31: 117
A32: + Tax Allowance/Credit | B32: IS_TAX_VALN_ALLOWNCE_CREDITS | C32: — | D32: — | E32: — | F32: — | G32: —
A33: Income (Loss) from Cont Ops | B33: IS_INC_BEF_XO_ITEM | C33: 3309 | D33: 3331 | E33: 2765 | F33: 3781 | G33: 4166 | H33: 3847 | I33: 3699.095 | J33: 3857.476
A34: - Net Extraordinary Losses (Gains) | B34: XO_GL_NET_OF_TAX | C34: 0 | D34: 0 | E34: 0 | F34: 0 | G34: 0 | H34: 0
A35: + Discontinued Operations | B35: IS_DISCONTINUED_OPERATIONS | C35: 0 | D35: 0 | E35: 0 | F35: 0 | G35: 0 | H35: 0
A36: + XO & Accounting Changes | B36: EXTRAORD_ITEMS_ACCOUNTING_CHANGS | C36: 0 | D36: 0 | E36: 0 | F36: 0 | G36: 0 | H36: 0
A37: Income (Loss) Incl. MI | B37: NI_INCLUDING_MINORITY_INT_RATIO | C37: 3309 | D37: 3331 | E37: 2765 | F37: 3781 | G37: 4166 | H37: 3847
A38: Net Income, GAAP | B38: NET_INCOME | C38: 3309 | D38: 3331 | E38: 2765 | F38: 3781 | G38: 4166 | H38: 3847 | I38: 3699.095 | J38: 3857.476
A39: - Preferred Dividends | B39: IS_TOT_CASH_PFD_DVD | C39: 0 | D39: 0 | E39: 0 | F39: 0 | G39: 0 | H39: 0
A40: - Other Adjustments | B40: OTHER_ADJUSTMENTS | C40: 1 | D40: 0 | E40: 0 | F40: 0 | G40: 0 | H40: 0
A41: Net Income Avail to Common, GAAP | B41: EARN_FOR_COMMON | C41: 3308 | D41: 3331 | E41: 2765 | F41: 3781 | G41: 4166 | H41: 3847 | I41: 3699.095 | J41: 3857.476
A43: Net Income Avail to Common, Adj | B43: EARN_FOR_COMMON | C43: 3200.34 | D43: 3198.09 | E43: 2737.35 | F43: 3378.34 | G43: 3907.98 | H43: 3750.01 | I43: 3695.192 | J43: 3837.577
A44: Net Abnormal Losses (Gains) | B44: IS_NET_ABNORMAL_ITEMS | C44: -107.66 | D44: -132.91 | E44: -27.65 | F44: -402.66 | G44: -258.02 | H44: -96.99
A45: Net Extraordinary Losses (Gains) | B45: XO_GL_NET_OF_TAX | C45: 0 | D45: 0 | E45: 0 | F45: 0 | G45: 0 | H45: 0
A47: Basic Weighted Avg Shares | B47: IS_AVG_NUM_SH_FOR_EPS | C47: 2571 | D47: 2389 | E47: 6900 | F47: 2250 | G47: 2136 | H47: 1994
A48: Basic EPS, GAAP | B48: IS_EPS | C48: 1.2867 | D48: 1.39 | E48: 0.4 | F48: 1.68 | G48: 1.95 | H48: 1.88 | I48: 1.833 | J48: 1.989
A49: Basic EPS from Cont Ops, GAAP | B49: IS_EARN_BEF_XO_ITEMS_PER_SH | C49: 1.2867 | D49: 1.39 | E49: 0.4 | F49: 1.68 | G49: 1.95 | H49: 1.88 | I49: 1.833 | J49: 1.989
A50: Basic EPS from Cont Ops, Adjusted | B50: IS_BASIC_EPS_CONT_OPS | C50: 1.2448 | D50: 1.3387 | E50: 0.3967 | F50: 1.5015 | G50: 1.8296 | H50: 1.839304 | I50: 1.833 | J50: 1.984
A52: Diluted Weighted Avg Shares | B52: IS_SH_FOR_DILUTED_EPS | C52: 2583 | D52: 2395 | E52: 6915 | F52: 2255 | G52: 2141 | H52: 1999
A53: Diluted EPS, GAAP | B53: IS_DILUTED_EPS | C53: 1.28 | D53: 1.39 | E53: 0.4 | F53: 1.68 | G53: 1.95 | H53: 1.88 | I53: 1.833 | J53: 1.989
A54: Diluted EPS from Cont Ops, GAAP | B54: IS_DIL_EPS_BEF_XO | C54: 1.28 | D54: 1.39 | E54: 0.4 | F54: 1.68 | G54: 1.95 | H54: 1.88 | I54: 1.833 | J54: 1.989
A55: Diluted EPS from Cont Ops, Adjusted | B55: IS_DIL_EPS_CONT_OPS | C55: 1.2383 | D55: 1.3345 | E55: 0.396 | F55: 1.5014 | G55: 1.8295 | H55: 1.83146 | I55: 1.833 | J55: 1.984
A57: Reference Items
A58: Accounting Standard | B58: ACCOUNTING_STANDARD | C58: US GAAP | D58: US GAAP | E58: US GAAP | F58: US GAAP | G58: US GAAP
A59: EBITDA | B59: EBITDA | C59: 6046 | D59: 6269 | E59: 5792 | F59: 6649 | G59: 7394 | H59: 7206 | I59: 7149.182 | J59: 7417.5
A60: EBITDA Margin (T12M) | B60: EBITDA_MARGIN | C60: 49.3551 | D60: 52.5174 | E60: 54.7293 | F60: 53.0985 | G60: 49.7812 | H60: 48.997076 | I60: 48.919575 | J60: 49.463698
A61: EBITA | B61: EBITA | C61: 4715 | D61: 4920 | E61: 4409 | F61: 5229 | G61: 5894
A62: EBIT | B62: EBIT | C62: 4715 | D62: 4836 | E62: 4327 | F62: 5140 | G62: 5785 | H62: 5619 | I62: 5555.68 | J62: 5758.5
A63: Gross Margin | B63: GROSS_MARGIN | C63: — | D63: — | E63: — | F63: — | G63: — | I63: 38.026 | J63: 38.595
A64: Operating Margin | B64: OPER_MARGIN | C64: 38.4898 | D64: 40.5127 | E64: 40.8863 | F64: 41.0478 | G64: 38.9484 | H64: 38.206296 | I64: 38.015748 | J64: 38.400634
A65: Profit Margin | B65: PROF_MARGIN | C65: 26.1334 | D65: 26.7914 | E65: 25.8655 | F65: 26.9792 | G65: 26.311 | H65: 25.49813 | I65: 25.285022 | J65: 25.590934
A66: Sales per Employee | B66: ACTUAL_SALES_PER_EMPL | C66: 544444.44 | D66: 568428.57 | E66: 548853.85 | F66: 598594.58 | G66: 658903.38 | H66: 646997.52
A67: Dividends per Share | B67: EQY_DPS | C67: 0.2933 | D67: 0.96 | E67: 0.116 | F67: 0.372 | G67: 0.4 | H67: 0.43 | I67: 0.442 | J67: 0.468
A68: Total Cash Common Dividends | B68: IS_TOT_CASH_COM_DVD | C68: 751 | D68: 2293.44 | E68: 800.4 | F68: 837 | G68: 854.4 | H68: 875.98
A69: Personnel Expenses | B69: IS_PERSONNEL_EXP | C69: 2738 | D69: 2616 | E69: 2275 | F69: 2550 | G69: 2861 | H69: 2942
A70: Depreciation Expense | B70: IS_DEPR_EXP | C70: 1331 | D70: 1349 | E70: 1383 | F70: 1420 | G70: 1500
A71: Rental Expense | B71: BS_CURR_RENTAL_EXPENSE | C71: 66 | D71: 84 | E71: 82 | F71: 89 | G71: 109
A72: Source: Bloomberg | C72: Right click to show data transparency (not supported for all values)

Sheet BS
A1: CSX Corp (CSX US) - Standardized
A3: In Millions of USD except Per Share | C3: FY 2018 | D3: FY 2019 | E3: FY 2020 | F3: FY 2021 | G3: FY 2022
A4: 12 Months Ending | C4: 12/31/2018 | D4: 12/31/2019 | E4: 12/31/2020 | F4: 12/31/2021 | G4: 12/31/2022
A5: Total Assets
A6: + Cash, Cash Equivalents & STI | B6: CASH_CASH_EQTY_STI_DETAILED | C6: 1111 | D6: 1954 | E6: 3131 | F6: 2316 | G6: 2087
A7: + Cash & Cash Equivalents | B7: BS_CASH_NEAR_CASH_ITEM | C7: 858 | D7: 958 | E7: 3129 | F7: 2239 | G7: 1958
A8: + ST Investments | B8: BS_MKT_SEC_OTHER_ST_INVEST | C8: 253 | D8: 996 | E8: 2 | F8: 77 | G8: 129
A9: + Accounts & Notes Receiv | B9: BS_ACCT_NOTE_RCV | C9: 1010 | D9: 986 | E9: 912 | F9: 1148 | G9: 1313
A10: + Accounts Receivable, Net | B10: BS_ACCTS_REC_EXCL_NOTES_REC | C10: 1010 | D10: 986 | E10: 912 | F10: 1148 | G10: 1313
A11: + Notes Receivable, Net | B11: NOTES_RECEIVABLE | C11: 0 | D11: 0 | E11: 0 | F11: 0 | G11: 0
A12: + Inventories | B12: BS_INVENTORIES | C12: 263 | D12: 261 | E12: 302 | F12: 339 | G12: 341
A13: + Other ST Assets | B13: OTHER_CURRENT_ASSETS_DETAILED | C13: 181 | D13: 77 | E13: 96 | F13: 70 | G13: 108
A14: + Derivative & Hedging Assets | B14: BS_DERIV_HEDGING_ASST_ST | C14: 0 | D14: 0 | E14: 0 | F14: 0 | G14: 0
A15: + Misc ST Assets | B15: BS_OTHER_CUR_ASSET_LESS_PREPAY | C15: 181 | D15: 77 | E15: 96 | F15: 70 | G15: 108
A16: Total Current Assets | B16: BS_CUR_ASSET_REPORT | C16: 2565 | D16: 3278 | E16: 4441 | F16: 3873 | G16: 3849
A17: + Property, Plant & Equip, Net | B17: BS_NET_FIX_ASSET | C17: 31998 | D17: 32700 | E17: 32916 | F17: 33516 | G17: 34747
... A30: Total Assets | B30: BS_TOT_ASSET | C30: 36729 | D30: 38257 | E30: 39793 | F30: 40531 | G30: 41912
A32: Liabilities & Shareholders' Equity
A33: + Payables & Accruals | B33: ACCT_PAYABLE_ACCRUALS_DETAILED | C33: 1718 | D33: 1701 | E33: 1454 | F33: 1845 | G33: 2092
A34: + Accounts Payable | B34: BS_ACCT_PAYABLE | C34: 949 | D34: 1043 | E34: 809 | F34: 963 | G34: 1130
A35: + Accrued Taxes | B35: BS_TAXES_PAYABLE | C35: 106 | D35: 69 | E35: 73 | F35: 134 | G35: 111
A36: + Interest & Dividends Payable | B36: INTEREST_DIVIDENDS_PAYABLE | C36: 0 | D36: 0 | E36: 0 | F36: 0 | G36: 0
A37: + Other Payables & Accruals | B37: BS_ACCRUAL | C37: 663 | D37: 589 | E37: 572 | F37: 748 | G37: 851
A38: + ST Debt | B38: BS_ST_BORROW | C38: 18 | D38: 302 | E38: 446 | F38: 245 | G38: 220
A39: + ST Borrowings | B39: SHORT_TERM_DEBT_DETAILED | C39: 0 | D39: 0 | E39: 0 | F39: 0 | G39: 0
A40: + ST Lease Liabilities | B40: ST_CAPITALIZED_LEASE_LIABILITIES | C40: 0 | D40: 57 | E40: 45 | F40: 64 | G40: 69
A41: + ST Finance Leases | B41: ST_CAPITAL_LEASE_OBLIGATIONS | C41: 0 | D41: 0 | E41: — | F41: — | G41: —
A42: + ST Operating Leases | B42: BS_ST_OPERATING_LEASE_LIABS | C42: — | D42: 57 | E42: 45 | F42: 64 | G42: 69
A43: + Current Portion of LT Debt | B43: BS_CURR_PORTION_LT_DEBT | C43: 18 | D43: 245 | E43: 401 | F43: 181 | G43: 151
A44: + Other ST Liabilities | B44: OTHER_CURRENT_LIABS_SUB_DETAILED | C44: 179 | D44: 148 | E44: 119 | F44: 143 | G44: 159
A45: + Deferred Revenue | B45: ST_DEFERRED_REVENUE | C45: 0 | D45: 0 | E45: 0 | F45: 0 | G45: 0
A46: + Derivatives & Hedging | B46: BS_DERIV_HEDGING_LIAB_ST | C46: 0 | D46: 0 | E46: 0 | F46: 0 | G46: 0
A47: + Misc ST Liabilities | B47: OTHER_CURRENT_LIABS_DETAILED | C47: 179 | D47: 148 | E47: 119 | F47: 143 | G47: 159
A48: Total Current Liabilities | B48: BS_CUR_LIAB | C48: 1915 | D48: 2151 | E48: 2019 | F48: 2233 | G48: 2471
A49: + LT Debt | B49: BS_LT_BORROW | C49: 14739 | D49: 16486 | E49: 16759 | F49: 16663 | G49: 18384
A50: + LT Borrowings | B50: LONG_TERM_BORROWINGS_DETAILED | C50: 14735 | D50: 15989 | E50: 16301 | F50: 16138 | G50: 17867
A51: + LT Lease Liabilities | B51: LT_CAPITALIZED_LEASE_LIABILITIES | C51: 4 | D51: 497 | E51: 458 | F51: 525 | G51: 517
A52: + LT Finance Leases | B52: LT_CAPITAL_LEASE_OBLIGATIONS | C52: 4 | D52: 4 | E52: 3 | F52: 47 | G52: 29
A53: + LT Operating Leases | B53: BS_LT_OPERATING_LEASE_LIABS | C53: — | D53: 493 | E53: 455 | F53: 478 | G53: 488
A54: + Other LT Liabilities | B54: OTHER_NONCUR_LIABS_SUB_DETAILED | C54: 7495 | D54: 7757 | E54: 7905 | F54: 8135 | G54: 8432
A55: + Accrued Liabilities | B55: BS_ACCRUED_LIABILITIES | C55: 211 | D55: 205 | E55: 224 | F55: 250 | G55: 292
A56: + Pension Liabilities | B56: PENSION_LIABILITIES | C56: 408 | D56: 402 | E56: 349 | F56: 244 | G56: 188
A57: + Deferred Revenue | B57: LT_DEFERRED_REVENUE | C57: 0 | D57: 0 | E57: 0 | F57: 0 | G57: 0
A58: + Deferred Tax Liabilities | B58: BS_DEFERRED_TAX_LIABILITIES_LT | C58: 6690 | D58: 6961 | E58: 7168 | F58: 7383 | G58: 7569
A59: + Derivatives & Hedging | B59: BS_DERIV_HEDGING_LIAB_LT | C59: 0 | D59: 0 | E59: 0 | F59: 0 | G59: 0
A60: + Misc LT Liabilities | B60: OTHER_NONCURRENT_LIABS_DETAILED | C60: 186 | D60: 189 | E60: 164 | F60: 258 | G60: 383
A61: Total Noncurrent Liabilities | B61: NON_CUR_LIAB | C61: 22234 | D61: 24243 | E61: 24664 | F61: 24798 | G61: 26816
A62: Total Liabilities | B62: BS_TOT_LIAB2 | C62: 24149 | D62: 26394 | E62: 26683 | F62: 27031 | G62: 29287
A63: + Preferred Equity and Hybrid Capital | B63: PFD_EQTY_HYBRID_CAPITAL | C63: 0 | D63: 0 | E63: 0 | F63: 0 | G63: 0
A64: + Share Capital & APIC | B64: BS_SH_CAP_AND_APIC | C64: 1067 | D64: 1119 | E64: 2440 | F64: 2268 | G64: 2640
A65: + Common Stock | B65: BS_COMMON_STOCK | C65: 818.18 | D65: 773.471 | E65: 2288 | F65: 2202 | G65: 2066
... A73: Total Liabilities & Equity | B73: TOT_LIAB_AND_EQY | C73: 36729 | D73: 38257 | E73: 39793 | F73: 40531 | G73: 41912
A75: Reference Items
A76: Accounting Standard | B76: ACCOUNTING_STANDARD | C76: US GAAP | D76: US GAAP | E76: US GAAP | F76: US GAAP | G76: US GAAP
A77: Shares Outstanding | B77: BS_SH_OUT | C77: 2454.54 | D77: 2320.413 | E77: 6862.761 | F77: 2201.787 | G77: 2066.367
A78: Number of Treasury Shares | B78: BS_NUM_OF_TSY_SH | C78: 0 | D78: 0 | E78: 0 | F78: 0 | G78: 0
A79: Pension Obligations | B79: BS_PENSION_RSRV | C79: 408 | D79: 402 | E79: 349 | F79: 244 | G79: 188
A80: Future Minimum Operating Lease Obligations | B80: BS_FUTURE_MIN_OPER_LEASE_OBLIG | C80: 1556 | D80: 1444 | E80: 1369 | F80: 1390 | G80: 1386
A81: Capital Leases - Total | B81: BS_TOTAL_CAPITAL_LEASES | C81: 4 | D81: 4 | E81: 3 | F81: 47 | G81: 29
A82: Options Granted During Period | B82: BS_OPTIONS_GRANTED | C82: 3.027 | D82: 3.561 | E82: 4.017 | F82: 2.005 | G82: 1.726
A83: Options Outstanding at Period End | B83: BS_OPTIONS_OUTSTANDING | C83: 14.019 | D83: 11.385 | E83: 12.651 | F83: 12.512 | G83: 13.4
A84: Net Debt | B84: NET_DEBT | C84: 13646 | D84: 14834 | E84: 14074 | F84: 14592 | G84: 16517
A85: Net Debt to Equity | B85: NET_DEBT_TO_SHRHLDR_EQTY | C85: 108.4738 | D85: 125.0443 | E85: 107.3532 | F85: 108.0889 | G85: 130.8277
A86: Tangible Common Equity Ratio | B86: TCE_RATIO | C86: 34.2046 | D86: 30.9695 | E86: 32.8165 | F86: 32.5324 | G86: 29.2514
A87: Current Ratio | B87: CUR_RATIO | C87: 1.3394 | D87: 1.5239 | E87: 2.1996 | F87: 1.7344 | G87: 1.5577
A88: Number of Employees | B88: NUM_OF_EMPLOYEES | C88: 22500 | D88: 21000 | E88: 19282 | F88: 20919 | G88: 22542
A89: Source: Bloomberg | C89: Right click to show data transparency (not supported for all values)

Sheet CF
A1: CSX Corp (CSX US) - Standardized
A3: In Millions of USD except Per Share | C3: FY 2018 | D3: FY 2019 | E3: FY 2020 | F3: FY 2021 | G3: FY 2022 | H3: Last 12M
A4: 12 Months Ending | C4: 12/31/2018 | D4: 12/31/2019 | E4: 12/31/2020 | F4: 12/31/2021 | G4: 12/31/2022 | H4: 09/30/2023
A5: Cash from Operating Activities
A6: + Net Income | B6: CF_NET_INC | C6: 3309 | D6: 3331 | E6: 2765 | F6: 3781 | G6: 4166 | H6: 3847
A7: + Depreciation & Amortization | B7: CF_DEPR_AMORT | C7: 1331 | D7: 1349 | E7: 1383 | F7: 1420 | G7: 1500 | H7: 1587
A8: + Non-Cash Items | B8: NON_CASH_ITEMS_DETAILED | C8: -7 | D8: 53 | E8: 113 | F8: -275 | G8: -138 | H8: 126
A9: + Deferred Income Taxes | B9: CF_DEF_INC_TAX | C9: 279 | D9: 273 | E9: 180 | F9: 167 | G9: 117 | H9: 103
A10: + Other Non-Cash Adj | B10: OTHER_NON_CASH_ADJ_LESS_DETAILED | C10: -286 | D10: -220 | E10: -67 | F10: -442 | G10: -255 | H10: 23
A11: + Chg in Non-Cash Work Cap | B11: CF_CHNG_NON_CASH_WORK_CAP | C11: 8 | D11: 117 | E11: 2 | F11: 173 | G11: 91 | H11: -147
A12: + (Inc) Dec in Accts Receiv | B12: CF_ACCT_RCV_UNBILLED_REV | C12: -46 | D12: 45 | E12: 83 | F12: -141 | G12: -101 | H12: -23
A13: + (Inc) Dec in Inventories | B13: CF_CHANGE_IN_INVENTORIES | C13: 0 | D13: 0 | E13: 0 | F13: 0 | G13: 0 | H13: 0
A14: + Inc (Dec) in Accts Payable | B14: CF_CHANGE_IN_ACCOUNTS_PAYABLE | C14: 104 | D14: 98 | E14: -20 | F14: 128 | G14: 140 | H14: 26
A15: + Inc (Dec) in Other | B15: INC_DEC_IN_OT_OP_AST_LIAB_DETAIL | C15: -50 | D15: -26 | E15: -61 | F15: 186 | G15: 52 | H15: -150
A16: + Net Cash From Disc Ops | B16: CF_NET_CASH_DISCONT_OPS_OPER | C16: 0 | D16: 0 | E16: 0 | F16: 0 | G16: 0 | H16: 0
A17: Cash from Operating Activities | B17: CF_CASH_FROM_OPER | C17: 4641 | D17: 4850 | E17: 4263 | F17: 5099 | G17: 5619 | H17: 5413
A19: Cash from Investing Activities
A20: + Change in Fixed & Intang | B20: FIXED_INTANG_ASST_CHANGE | C20: -1426 | D20: -1403 | E20: -1570 | F20: -1262 | G20: -1887 | H20: -2056
A21: + Disp in Fixed & Intang | B21: DISPOSAL_OF_FIXED_INTANG | C21: 319 | D21: 254 | E21: 56 | F21: 529 | G21: 246 | H21: 230
A22: + Disp of Fixed Prod Assets | B22: CF_DISPOSAL_OF_FIXED_PROD_ASSETS | C22: 319 | D22: 254 | E22: 56 | F22: 529 | G22: 246 | H22: 230
A23: + Disp of Intangible Assets | B23: CF_DISPOSAL_OF_INTANGIBLE_ASSETS | C23: 0 | D23: 0 | E23: 0 | F23: 0 | G23: 0 | H23: 0
A24: + Acq of Fixed & Intang | B24: ACQUIS_OF_FIXED_INTANG | C24: -1745 | D24: -1657 | E24: -1626 | F24: -1791 | G24: -2133 | H24: -2286
A25: + Acq of Fixed Prod Assets | B25: CF_PURCHASE_OF_FIXED_PROD_ASSETS | C25: -1745 | D25: -1657 | E25: -1626 | F25: -1791 | G25: -2133 | H25: -2286
A26: + Acq of Intangible Assets | B26: CF_ACQUISITION_OF_INTANG_ASSETS | C26: 0 | D26: 0 | E26: 0 | F26: 0 | G26: 0 | H26: 0
A27: + Net Change in LT Investment | B27: NET_CHG_IN_LT_INVEST_DETAILED | C27: 0 | D27: 0 | E27: 0 | F27: 0 | G27: 0 | H27: 0
A28: + Dec in LT Investment | B28: CF_DECR_INVEST | C28: 0 | D28: 0 | E28: 0 | F28: 0 | G28: 0 | H28: 0
A29: + Inc in LT Investment | B29: CF_INCR_INVEST | C29: 0 | D29: 0 | E29: 0 | F29: 0 | G29: 0 | H29: 0
A30: + Net Cash From Acq & Div | B30: CF_NT_CSH_RCVD_PD_FOR_ACQUIS_DIV | C30: 0 | D30: 0 | E30: 0 | F30: -541 | G30: -227 | H30: -35
A31: + Cash from Divestitures | B31: CF_CASH_FOR_DIVESTITURES | C31: 0 | D31: 0 | E31: 0 | F31: 0 | G31: 0 | H31: 0
... A36: Cash from Investing Activities | B36: CF_CASH_FROM_INV_ACT | C36: -1684 | D36: -2102 | E36: -649 | F36: -1877 | G36: -2131 | H36: -2042
A38: Cash from Financing Activities
A39: + Dividends Paid | B39: CF_DVD_PAID | C39: -751 | D39: -763 | E39: -797 | F39: -839 | G39: -852 | H39: -873
A40: + Cash From (Repayment) Debt | B40: PROC_FR_REPAYMNTS_BOR_DETAILED | C40: 2981 | D40: 1482 | E40: 255 | F40: -426 | G40: 1814 | H40: 442
A41: + Cash From (Repay) ST Debt | B41: CF_NET_CHG_ST_DEBT_CPTL_LEAS | C41: 0 | D41: 0 | E41: 0 | F41: 0 | G41: 0 | H41: 0
A42: + Cash From LT Debt | B42: CF_LT_DEBT_CAP_LEAS_PROCEEDS | C42: 3000 | D42: 2000 | E42: 1000 | F42: 0 | G42: 2000 | H42: 600
A43: + Repayments of LT Debt | B43: CF_LT_DEBT_CAP_LEAS_PAYMENT | C43: -19 | D43: -518 | E43: -745 | F43: -426 | G43: -186 | H43: -158
A44: + Cash (Repurchase) of Equity | B44: NET_CAP_STOCK | C44: -4671 | D44: -3373 | E44: -867 | F44: -2886 | G44: -4731 | H44: -3922
A45: + Increase in Capital Stock | B45: CF_INCR_CAP_STOCK | C45: 0 | D45: 0 | E45: 0 | F45: 0 | G45: 0 | H45: 0
A46: + Decrease in Capital Stock | B46: CF_DECR_CAP_STOCK | C46: -4671 | D46: -3373 | E46: -867 | F46: -2886 | G46: -4731 | H46: -3922
A47: + Other Financing Activities | B47: OTHER_FIN_AND_DEC_CAP | C47: -59 | D47: 6 | E47: -34 | F47: 39 | G47: 0 | H47: 31
A48: + Net Cash From Disc Ops | B48: CF_NET_CASH_DISCONTINUED_OPS_FIN | C48: 0 | D48: 0 | E48: 0 | F48: 0 | G48: 0 | H48: 0
A49: Cash from Financing Activities | B49: CFF_ACTIVITIES_DETAILED | C49: -2500 | D49: -2648 | E49: -1443 | F49: -4112 | G49: -3769 | H49: -4322
A51: Effect of Foreign Exchange Rates | B51: CF_EFFECT_FOREIGN_EXCHANGES | C51: 0 | D51: 0 | E51: 0 | F51: 0 | G51: 0 | H51: 0
A53: Net Changes in Cash | B53: CF_NET_CHNG_CASH | C53: 457 | D53: 100 | E53: 2171 | F53: -890 | G53: -281 | H53: -951
A55: Cash Paid for Taxes | B55: CF_CASH_PAID_FOR_TAX | C55: 814 | D55: 691 | E55: 664 | F55: 931 | G55: 1167
A56: Cash Paid for Interest | B56: CF_ACT_CASH_PAID_FOR_INT_DEBT | C56: 614 | D56: 717 | E56: 750 | F56: 718 | G56: 729
A58: Reference Items
A59: EBITDA | B59: EBITDA | C59: 6200 | D59: 6398 | E59: 5827 | F59: 7103 | G59: 7632 | H59: 7287
A60: Trailing 12M EBITDA Margin | B60: EBITDA_MARGIN | C60: 50.6122 | D60: 53.5981 | E60: 55.06 | F60: 56.7242 | G60: 51.3836 | H60: 49.547834
A61: Net Cash Paid for Acquisitions | B61: CF_NET_CASH_PAID_FOR_AQUIS | C61: — | D61: 0 | E61: 0 | F61: 541 | G61: 227 | H61: 35
A62: Free Cash Flow | B62: CF_FREE_CASH_FLOW | C62: 2896 | D62: 3193 | E62: 2637 | F62: 3308 | G62: 3486 | H62: 3127
A63: Free Cash Flow to Firm | B63: CF_FREE_CASH_FLOW_FIRM | C63: 3387.2758 | D63: 3761.8014 | E63: 3211.8029 | F63: 3859.3799 | G63: 4056.959 | H63: 3739.6004
A64: Free Cash Flow to Equity | B64: FREE_CASH_FLOW_EQUITY | C64: 6196 | D64: 4929 | E64: 2948 | F64: 3411 | G64: 5546 | H64: 3799
A65: Free Cash Flow per Basic Share | B65: FREE_CASH_FLOW_PER_SH | C65: 1.1264 | D65: 1.3365 | E65: 0.3822 | F65: 1.4702 | G65: 1.632 | H65: 1.5374861
A66: Price to Free Cash Flow | B66: PX_TO_FREE_CASH_FLOW | C66: 18.3858 | D66: 18.0466 | E66: 79.1524 | F66: 25.5744 | G66: 18.9826 | H66: 21.021328
A67: Cash Flow to Net Income | B67: CASH_FLOW_TO_NET_INC | C67: 1.4025 | D67: 1.456 | E67: 1.5418 | F67: 1.3486 | G67: 1.3488 | H67: 1.8510638
A68: Source: Bloomberg | C68: Right click to show data transparency (not supported for all values)

Sheet Graphs
D3: Terminal Growth Rate
D4: {=DCF!P24:T24} -> 0.01 | E4: 0.015 | F4: 0.02 | G4: 0.025 | H4: 0.03
B5: WACC | C5: {=DCF!O25:O29} -> 0.053452554 | D5: {=DCF!P25:T29} -> 9.7% / $246.09 | E5: 25.9% / $282.28 | F5: 46.8% / $329.27 | G5: 75.1% / $392.79 | H5: 115.5% / $483.38
C6: 0.048452554 | D6: 25.2% / $280.78 | E6: 46.0% / $327.56 | F6: 74.2% / $390.77 | G6: 114.4% / $480.94 | H6: 176.4% / $619.97
C7: 0.043452554 | D7: 45.3% / $325.84 | E7: 73.3% / $388.75 | F7: 113.3% / $478.49 | G7: 175.0% / $616.86 | H7: 282.6% / $858.08
C8: 0.038452554 | D8: 72.4% / $386.74 | E8: 112.3% / $476.04 | F8: 173.7% / $613.75 | G8: 280.7% / $853.82 | H8: 514.4% / $1377.90
C9: 0.033452554 | D9: 111.2% / $473.60 | E9: 172.3% / $610.64 | F9: 278.8% / $849.55 | G9: 511.3% / $1371.11 | H9: 1417.5% / $3403.34
H12: Std stock/Std S&P | I12: 3Y
H13: beta | I13: return
E14: {=I14:I22/100} -> 0.00033 | G14: CSX | H14: 0.986 | I14: 0.033 | J14: =DCF!$F$25+H14*$I$21 -> 0.192 | L14: =I14-J14 -> -0.159
E15: 0.00077 | G15: UNP | H15: 0.983 | I15: 0.077 | J15: =DCF!$F$25+H15*$I$21 -> 0.19155 | L15: =I15-J15 -> -0.11455
E16: -0.00052 | G16: CRN CN | H16: 0.84 | I16: -0.052 | J16: =DCF!$F$25+H16*$I$21 -> 0.1701 | L16: =I16-J16 -> -0.2221
E17: -0.00091 | G17: CP Cn | H17: 0.901 | I17: -0.091 | J17: =DCF!$F$25+H17*$I$21 -> 0.17925 | L17: =I17-J17 -> -0.27025
E18: -0.00123 | G18: NSC US | H18: 1.012 | I18: -0.123 | J18: =DCF!$F$25+H18*$I$21 -> 0.1959 | L18: =I18-J18 -> -0.3189
E19: 0
E20: 0
E21: 0.0015 | G21: S&P | H21: 1 | I21: 0.15
E22: 0.0001932 | G22: US 10Y | H22: 0 | I22: 0.01932
G23: CAPM
G24: E(r)=rf+B*marketpremium
B27: Merchandise | C27: 55.5
B28: Intermodal | C28: 15.5
B29: Trucking | C29: 6.5
B30: Other | C30: 6.1 | P30: 1 | Q30: 5 | R30: 42 | S30: =R30-Q30 -> 37
B31: Coal | C31: 16.4 | P31: 2 | Q31: 16 | R31: 37 | S31: =R31-Q31 -> 21
P32: 3 | Q32: 18.54 | R32: 25 | S32: =R32-Q32 -> 6.46
P33: 4 | Q33: 4 | R33: 42 | S33: =R33-Q33 -> 38
P34: 5 | Q34: 4 | R34: 30 | S34: =R34-Q34 -> 26
P35: 6 | Q35: 6 | R35: 45 | S35: =R35-Q35 -> 39
P36: 7 | Q36: 3 | R36: 38 | S36: =R36-Q36 -> 35
Q37: {=Q30:Q36/100} -> 0.05 | S37: {=S30:S36/100} -> 0.37
Q38: 0.16 | S38: 0.21
Q39: 0.1854 | S39: 0.0646
Q40: 0.04 | S40: 0.38
Q41: 0.04 | S41: 0.26
Q42: 0.06 | S42: 0.39
Q43: 0.03 | S43: 0.35
E47: China | F47: 12.5 | G47: 24 | H47: 32.5
E48: North America | F48: 15 | G48: 17 | H48: 23
E49: India | F49: 4 | G49: 9 | H49: 13.5
E50: Europe | F50: 7 | G50: 9 | H50: 12
E51: Russia | F51: 5.5 | G51: 7.5 | H51: 8
E52: Japan | F52: 3 | G52: 2.5 | H52: 3.5

Sheet Ratio
A1: CSX Corp (CSX US) - By Measure
A3: In Millions of USD except Per Share | C3: FY 2013 | E3: FY 2014 | G3: FY 2015 | I3: FY 2016 | K3: FY 2017 | M3: FY 2018 | O3: FY 2019 | Q3: FY 2020 | S3: FY 2021 | U3: FY 2022
A4: 12 Months Ending | C4: 12/27/2013 | E4: 12/26/2014 | G4: 12/25/2015 | I4: 12/30/2016 | K4: 12/31/2017 | M4: 12/31/2018 | O4: 12/31/2019 | Q4: 12/31/2020 | S4: 12/31/2021 | U4: 12/31/2022
A5: Revenue | C5: 12026 | D5: 1 | E5: 12669 | F5: 1 | G5: 11811 | H5: 1 | I5: 11069 | J5: 1 | K5: 11408 | L5: 1 | M5: 12250 | N5: 1 | O5: 11937 | P5: 1 | Q5: 10583 | R5: 1 | S5: 12522 | T5: 1 | U5: 14853 | V5: 1
A6: Merchandise | C6: 7037 | D6: 0.58514884 | E6: 7608 | F6: 0.60052096 | G6: 7271 | H6: 0.61561256 | I6: 7142 | J6: 0.6452254 | K6: 7068 | L6: 0.61956522 | M6: 7491 | N6: 0.6115102 | O6: 7589 | P6: 0.63575438 | Q6: 7076 | R6: 0.66861948 | S6: 7539 | T6: 0.60206037 | U6: 8239 | V6: 0.55470275
A7: Chemicals | C7: 1896 | D7: 0.15765841 | E7: 2178 | F7: 0.1719157 | G7: 2284 | H7: 0.19337905 | I7: 2191 | J7: 0.19794019 | K7: 2210 | L7: 0.1937237 | M7: 2339 | N7: 0.19093878 | O7: 2349 | P7: 0.19678311 | Q7: 2309 | R7: 0.2181801 | S7: 2421 | T7: 0.19333972 | U7: 2584 | V7: 0.17397159
A8: Agriculture & Food Product | C8: — | E8: — | G8: 1345 | H8: 0.11387689 | I8: 1286 | J8: 0.11618032 | K8: 1262 | L8: 0.11062412 | M8: 1306 | N8: 0.10661224 | O8: 1410 | P8: 0.11812013 | Q8: 1386 | R8: 0.13096475 | S8: 1461 | T8: 0.11667465 | U8: 1664 | V8: 0.11203124
A9: Automotive | C9: 1217 | D9: 0.10119741 | E9: 1213 | F9: 0.095745521 | G9: 1175 | H9: 0.099483532 | I9: 1261 | J9: 0.11392176 | K9: 1195 | L9: 0.10475105 | M9: 1267 | N9: 0.10342857 | O9: 1236 | P9: 0.1035436 | Q9: 920 | R9: 0.086931872 | S9: 886 | T9: 0.07075547 | U9: 1054 | V9: 0.070962095
A10: Forest Products | C10: 775 | D10: 0.064443705 | E10: 819 | F10: 0.064645986 | G10: 796 | H10: 0.067394801 | I10: 773 | J10: 0.069834673 | K10: 755 | L10: 0.066181627 | M10: 850 | N10: 0.069387755 | O10: 870 | P10: 0.072882634 | Q10: 834 | R10: 0.078805632 | S10: 918 | T10: 0.073310973 | U10: 996 | V10: 0.06705716
A11: Metal & Equipment | C11: — | E11: — | G11: 723 | H11: 0.061214122 | I11: 704 | J11: 0.063601048 | K11: 703 | L11: 0.061623422 | M11: 769 | N11: 0.06277551 | O11: 742 | P11: 0.062159672 | Q11: 675 | R11: 0.063781536 | S11: 796 | T11: 0.06356812 | U11: 828 | V11: 0.055746314
A12: Minerals | C12: 432 | D12: 0.035922169 | E12: 459 | F12: 0.036230168 | G12: 459 | H12: 0.038862078 | I12: 464 | J12: 0.041918873 | K12: 477 | L12: 0.041812763 | M12: 518 | N12: 0.042285714 | O12: 559 | P12: 0.046829187 | Q12: 538 | R12: 0.050836247 | S12: 587 | T12: 0.046877496 | U12: 658 | V12: 0.044300815
A13: Fertilizers | C13: 527 | D13: 0.04382172 | E13: 534 | F13: 0.04215013 | G13: 489 | H13: 0.041402083 | I13: 463 | J13: 0.04182853 | K13: 466 | L13: 0.040848527 | M13: 442 | N13: 0.036081633 | O13: 423 | P13: 0.035436039 | Q13: 414 | R13: 0.039119342 | S13: 470 | T13: 0.03753394 | U13: 455 | V13: 0.030633542
A14: Housing and Construction | C14: 1471 | D14: 0.12231831 | E14: 1587 | F14: 0.1252664 | G14: 1255 | H14: 0.10625688 | I14: — | K14: — | M14: — | O14: — | Q14: — | S14: — | U14: —
A15: Waste & Equipment | C15: 264 | D15: 0.021952436 | E15: 309 | F15: 0.024390244 | G15: — | I15: — | K15: — | M15: — | O15: — | Q15: — | S15: — | U15: —
A16: Agricultural | C16: 1809 | D16: 0.15042408 | E16: 1929 | F16: 0.15226143 | G16: 1834 | H16: 0.15527898 | I16: — | K16: — | M16: — | O16: — | Q16: — | S16: — | U16: —
A17: Food and Consumer | C17: 269 | D17: 0.022368202 | E17: 265 | F17: 0.020917199 | G17: — | I17: — | K17: — | M17: — | O17: — | Q17: — | S17: — | U17: —
A18: Agriculture Products | C18: 1013 | D18: 0.084234159 | E18: 1130 | F18: 0.089194096 | G18: — | I18: — | K18: — | M18: — | O18: — | Q18: — | S18: — | U18: —
A19: Industrial | C19: 3757 | D19: 0.31240645 | E19: 4092 | F19: 0.32299313 | G19: 4182 | H19: 0.35407671 | I19: — | K19: — | M19: — | O19: — | Q19: — | S19: — | U19: —
A20: Metals | C20: 644 | D20: 0.05355064 | E20: 701 | F20: 0.055331913 | G20: — | I20: — | K20: — | M20: — | O20: — | Q20: — | S20: — | U20: —
A21: Coal | C21: 2895 | D21: 0.24072842 | E21: 2849 | F21: 0.22487963 | G21: 2300 | H21: 0.19473372 | I21: 1833 | J21: 0.16559761 | K21: 2107 | L21: 0.18469495 | M21: 2246 | N21: 0.18334694 | O21: 2070 | P21: 0.1734104 | Q21: 1397 | R21: 0.13200416 | S21: 1790 | T21: 0.14294841 | U21: 2434 | V21: 0.16387262
A22: Intermodal | C22: 1697 | D22: 0.14111093 | E22: 1790 | F22: 0.14128976 | G22: 1762 | H22: 0.14918297 | I22: 1726 | J22: 0.15593098 | K22: 1799 | L22: 0.15769635 | M22: 1931 | N22: 0.15763265 | O22: 1760 | P22: 0.14744073 | Q22: 1702 | R22: 0.16082396 | S22: 2039 | T22: 0.16283341 | U22: 2306 | V22: 0.15525483
A23: Trucking | C23: — | E23: — | G23: — | I23: — | K23: — | M23: — | O23: 0 | Q23: 0 | S23: 410 | T23: 0.032742373 | U23: 966 | V23: 0.065037366
A24: Other | C24: 397 | D24: 0.033011808 | E24: 422 | F24: 0.033309653 | G24: 478 | H24: 0.040470748 | I24: 368 | J24: 0.033246002 | K24: 434 | L24: 0.038043478 | M24: 582 | N24: 0.047510204 | O24: 518 | P24: 0.043394488 | Q24: 408 | R24: 0.038552395 | S24: 744 | T24: 0.059415429 | U24: 908 | V24: 0.061132431
A25: Sales Volume | C25: — | E25: — | G25: — | I25: — | K25: — | M25: — | O25: — | Q25: 5892000 | R25: 1 | S25: 6253000 | T25: 1 | U25: 6218000 | V25: 1
A26: Intermodal | C26: — | E26: — | G26: — | I26: — | K26: — | M26: — | O26: — | Q26: 2720000 | R26: 0.46164291 | S26: 2976000 | T26: 0.47593155 | U26: 2963000 | V26: 0.47651978
A27: Merchandise | C27: — | E27: — | G27: — | I27: — | K27: — | M27: — | O27: — | Q27: 2535000 | R27: 0.4302444 | S27: 2571000 | T27: 0.41116264 | U27: 2558000 | V27: 0.4113863
A28: Chemicals | C28: — | E28: — | G28: — | I28: — | K28: — | M28: — | O28: — | Q28: 664000 | R28: 0.11269518 | S28: 659000 | T28: 0.10538941 | U28: 641000 | V28: 0.10308781
A29: Agriculture & Food Product | C29: — | E29: — | G29: — | I29: — | K29: — | M29: — | O29: — | Q29: 463000 | R29: 0.078581127 | S29: 467000 | T29: 0.074684152 | U29: 481000 | V29: 0.077356063
A30: Automotive | C30: — | E30: — | G30: — | I30: — | K30: — | M30: — | O30: — | Q30: 344000 | R30: 0.05838425 | S30: 318000 | T30: 0.050855589 | U30: 338000 | V30: 0.054358315
A31: Minerals | C31: — | E31: — | G31: — | I31: — | K31: — | M31: — | O31: — | Q31: 321000 | R31: 0.054480652 | S31: 325000 | T31: 0.051975052 | U31: 337000 | V31: 0.054197491
A32: Forest Products | C32: — | E32: — | G32: — | I32: — | K32: — | M32: — | O32: — | Q32: 278000 | R32: 0.047182621 | S32: 296000 | T32: 0.047337278 | U32: 291000 | V32: 0.046799614
A33: Metal & Equipment | C33: — | E33: — | G33: — | I33: — | K33: — | M33: — | O33: — | Q33: 239000 | R33: 0.040563476 | S33: 277000 | T33: 0.044298737 | U33: 267000 | V33: 0.042939852
A34: Fertilizers | C34: — | E34: — | G34: — | I34: — | K34: — | M34: — | O34: — | Q34: 226000 | R34: 0.038357094 | S34: 229000 | T34: 0.036622421 | U34: 203000 | V34: 0.032647153
A35: Coal | C35: — | E35: — | G35: — | I35: — | K35: — | M35: — | O35: — | Q35: 637000 | R35: 0.1081127 | S35: 706000 | T35: 0.11290581 | U35: 697000 | V35: 0.11209392
A36: Trucking | C36: — | E36: — | G36: — | I36: — | K36: — | M36: — | O36: — | Q36: 0 | S36: 0 | U36: 0
A37: Other | C37: — | E37: — | G37: — | I37: — | K37: — | M37: — | O37: — | Q37: 0 | S37: 0 | U37: 0
A38: Revenue Per Unit | C38: — | E38: — | G38: — | I38: — | K38: — | M38: — | O38: — | Q38: — | S38: — | U38: —
A39: Coal | C39: 2423 | E39: 2258 | G39: 2164 | I39: 2187 | K39: 2464 | M39: 2532 | O39: 2456 | Q39: 2193 | S39: 2535 | U39: 3492
A40: Merchandise | C40: 2548 | E40: 2595 | G40: 2542 | I40: 2549 | K40: 2616 | M40: 2774 | O40: 2803 | Q40: 2791 | S40: 2932 | U40: 3221
A41: Chemicals | C41: 3564 | E41: 3513 | G41: 3146 | I41: 3130 | K41: 3289 | M41: 3465 | O41: 3507 | Q41: 3477 | S41: 3674 | U41: 4031
A42: Agriculture & Food Product | C42: — | E42: — | G42: 2674 | I42: 2696 | K42: 2780 | M42: 2922 | O42: 3006 | Q42: 2994 | S42: 3128 | U42: 3459
A43: Forest Products | C43: 2601 | E43: 2668 | G43: 2745 | I43: 2821 | K43: 2860 | M43: 2982 | O43: 3049 | Q43: 3000 | S43: 3101 | U43: 3423
A44: Automotive | C44: 2817 | E44: 2789 | G44: 2611 | I44: 2616 | K44: 2615 | M44: 2737 | O44: 2711 | Q44: 2674 | S44: 2786 | U44: 3118
A45: Metal & Equipment | C45: — | E45: — | G45: 2546 | I45: 2718 | K45: 2746 | M45: 2880 | O45: 2988 | Q45: 2824 | S45: 2874 | U45: 3101
A46: Fertilizers | C46: 1612 | E46: 1618 | G46: 1625 | I46: 1543 | K46: 1601 | M46: 1782 | O46: 1774 | Q46: 1832 | S46: 2052 | U46: 2241
A47: Minerals | C47: 1571 | E47: 1567 | G47: 1500 | I47: 1497 | K47: 1549 | M47: 1644 | O47: 1642 | Q47: 1676 | S47: 1806 | U47: 1953
A48: Waste & Equipment | C48: 1760 | E48: 1956 | G48: — | I48: — | K48: — | M48: — | O48: — | Q48: — | S48: — | U48: —
A49: Metals | C49: 2458 | E49: 2540 | G49: — | I49: — | K49: — | M49: — | O49: — | Q49: — | S49: — | U49: —
A50: Food and Consumer | C50: 2802 | E50: 2819 | G50: — | I50: — | K50: — | M50: — | O50: — | Q50: — | S50: — | U50: —
A51: Agriculture Products | C51: 2597 | E51: 2697 | G51: — | I51: — | K51: — | M51: — | O51: — | Q51: — | S51: — | U51: —
A52: Intermodal | C52: 657 | E52: 656 | G52: 621 | I52: 614 | K52: 633 | M52: 667 | O52: 659 | Q52: 626 | S52: 685 | U52: 778
A53: Trucking | C53: — | E53: — | G53: — | I53: — | K53: — | M53: — | O53: — | Q53: 0 | S53: 0 | U53: 0
A54: Other | C54: 0 | E54: 0 | G54: 0 | I54: 0 | K54: 0 | M54: 0 | O54: 0 | Q54: 0 | S54: 0 | U54: 0
A55: Revenue Per Unit Growth % | C55: — | E55: — | G55: — | I55: — | K55: — | M55: — | O55: — | Q55: — | S55: — | U55: —
A56: Coal | C56: -2 | E56: -7 | G56: -4 | I56: 1 | K56: 13 | M56: 3 | O56: -3 | Q56: -11 | S56: 16 | U56: 38
A57: Intermodal | C57: 1 | E57: 0 | G57: -5 | I57: -1 | K57: 3 | M57: 5 | O57: -1 | Q57: -5 | S57: 9 | U57: 14
A58: Merchandise | C58: 2 | E58: 2 | G58: -2 | I58: 0 | K58: 3 | M58: 6 | O58: 1 | Q58: 0 | S58: 5 | U58: 10
A59: Automotive | C59: 4 | E59: -1 | G59: -6 | I59: 0 | K59: 0 | M59: 5 | O59: -1 | Q59: -1 | S59: 4 | U59: 12
A60: Agriculture & Food Product | C60: — | E60: — | G60: — | I60: 1 | K60: 3 | M60: 5 | O60: 3 | Q60: 0 | S60: 4 | U60: 11
A61: Chemicals | C61: 0 | E61: -1 | G61: -4 | I61: -1 | K61: 5 | M61: 5 | O61: 1 | Q61: -1 | S61: 6 | U61: 10
A62: Forest Products | C62: 3 | E62: 3 | G62: 3 | I62: 3 | K62: 1 | M62: 4 | O62: 2 | Q62: 0 | S62: 3 | U62: 10
A63: Fertilizers | C63: 1 | E63: 0 | G63: 0 | I63: -5 | K63: 4 | M63: 11 | O63: 0 | Q63: 2 | S63: 12 | U63: 9
A64: Minerals | C64: 4 | E64: 0 | G64: -4 | I64: 0 | K64: 3 | M64: 6 | O64: 0 | Q64: 1 | S64: 8 | U64: 8
A65: Metal & Equipment | C65: — | E65: — | G65: — | I65: 7 | K65: 1 | M65: 5 | O65: 4 | Q65: -5 | S65: 2 | U65: 8
A66: Waste & Equipment | C66: -7 | E66: 11 | G66: 4 | I66: — | K66: — | M66: — | O66: — | Q66: — | S66: — | U66: —
A67: Metals | C67: 2 | E67: 3 | G67: 1 | I67: — | K67: — | M67: — | O67: — | Q67: — | S67: — | U67: —
A68: Food and Consumer | C68: 3 | E68: 1 | G68: -1 | I68: — | K68: — | M68: — | O68: — | Q68: — | S68: — | U68: —
A69: Agriculture Products | C69: 2 | E69: 4 | G69: -2 | I69: — | K69: — | M69: — | O69: — | Q69: — | S69: — | U69: —
A70: Trucking | C70: — | E70: — | G70: — | I70: — | K70: — | M70: — | O70: — | Q70: — | S70: 0 | U70: 0
A71: Other | C71: 0 | E71: 0 | G71: 0 | I71: 0 | K71: 0 | M71: 0 | O71: 0 | Q71: 0 | S71: 0 | U71: 0
A72: Revenue Growth % | C72: — | E72: — | G72: — | I72: — | K72: — | M72: — | O72: — | Q72: — | S72: — | U72: —
A73: Trucking | C73: — | E73: — | G73: — | I73: — | K73: — | M73: — | O73: — | Q73: — | S73: 0 | U73: 136
A74: Coal | C74: -9 | E74: -2 | G74: -19 | I74: -20 | K74: 15 | M74: 7 | O74: -8 | Q74: -33 | S74: 28 | U74: 36
A75: Other | C75: 23 | E75: 6 | G75: 13 | I75: -23 | K75: 18 | M75: 34 | O75: -11 | Q75: -21 | S75: 82 | U75: 22
A76: Intermodal | C76: 6 | E76: 5 | G76: -2 | I76: -2 | K76: 4 | M76: 7 | O76: -9 | Q76: -3 | S76: 20 | U76: 13
A77: Merchandise | C77: 6 | E77: 8 | G77: -4 | I77: -2 | K77: -1 | M77: 6 | O77: 1 | Q77: -7 | S77: 7 | U77: 9
A78: Automotive | C78: 5 | E78: 0 | G78: -3 | I78: 7 | K78: -5 | M78: 6 | O78: -2 | Q78: -26 | S78: -4 | U78: 19
A79: Agriculture & Food Product | C79: — | E79: — | G79: — | I79: -4 | K79: -2 | M79: 3 | O79: 8 | Q79: -2 | S79: 5 | U79: 14
A80: Minerals | C80: 6 | E80: 6 | G80: 2 | I80: 1 | K80: 3 | M80: 9 | O80: 6 | Q80: -4 | S80: 9 | U80: 12
A81: Forest Products | C81: 7 | E81: 6 | G81: -3 | I81: -3 | K81: -2 | M81: 13 | O81: 3 | Q81: -4 | S81: 10 | U81: 8
A82: Chemicals | C82: 13 | E82: 15 | G82: -4 | I82: -4 | K82: 1 | M82: 6 | O82: 0 | Q82: -2 | S82: 5 | U82: 7
A83: Metal & Equipment | C83: — | E83: — | G83: — | I83: -3 | K83: 0 | M83: 9 | O83: -4 | Q83: -9 | S83: 18 | U83: 4
A84: Fertilizers | C84: 3 | E84: 1 | G84: -8 | I84: -5 | K84: 1 | M84: -5 | O84: -2 | Q84: -2 | S84: 14 | U84: -3
A85: Waste & Equipment | C85: 1 | E85: 17 | G85: 0 | I85: — | K85: — | M85: — | O85: — | Q85: — | S85: — | U85: —
A86: Metals | C86: 1 | E86: 9 | G86: -15 | I86: — | K86: — | M86: — | O86: — | Q86: — | S86: — | U86: —
A87: Food and Consumer | C87: -1 | E87: -1 | G87: -3 | I87: — | K87: — | M87: — | O87: — | Q87: — | S87: — | U87: —
A88: Agriculture Products | C88: 1 | E88: 12 | G88: -4 | I88: — | K88: — | M88: — | O88: — | Q88: — | S88: — | U88: —
A89: Transportation Fuel | C89: — | E89: — | G89: — | I89: 713 | J89: 1 | K89: 864 | L89: 1 | M89: 1046 | N89: 1 | O89: 906 | P89: 1 | Q89: 541 | R89: 1 | S89: 913 | T89: 1 | U89: 1626 | V89: 1
A90: Locomotive | C90: — | E90: — | G90: — | I90: 647 | J90: 0.90743338 | K90: 785 | L90: 0.90856481 | M90: 967 | N90: 0.92447419 | O90: 823 | P90: 0.90838852 | Q90: 496 | R90: 0.9168207 | S90: 807 | T90: 0.88389923 | U90: 1381 | V90: 0.84932349
A91: Non - Locomotive | C91: — | E91: — | G91: — | I91: 66 | J91: 0.09256662 | K91: 79 | L91: 0.091435185 | M91: 79 | N91: 0.075525813 | O91: 83 | P91: 0.091611479 | Q91: 45 | R91: 0.083179298 | S91: 106 | T91: 0.11610077 | U91: 245 | V91: 0.15067651
A92: Sales Change - Volume % | C92: — | E92: — | G92: — | I92: — | K92: — | M92: — | O92: — | Q92: — | S92: — | U92: —
A93: Trucking | C93: — | E93: — | G93: — | I93: — | K93: — | M93: — | O93: — | Q93: — | S93: 0 | U93: 0
A94: Other | C94: 0 | E94: 0 | G94: 0 | I94: 0 | K94: 0 | M94: 0 | O94: 0 | Q94: 0 | S94: 0 | U94: 0
A95: Intermodal | C95: 5 | E95: 6 | G95: 4 | I95: -1 | K95: 1 | M95: 2 | O95: -8 | Q95: 2 | S95: 9 | U95: 0
A96: Coal | C96: -7 | E96: 6 | G96: -16 | I96: -21 | K96: 2 | M96: 4 | O96: -5 | Q96: -24 | S96: 11 | U96: -1
A97: Merchandise | C97: 4 | E97: 6 | G97: -2 | I97: -2 | K97: -4 | M97: 0 | O97: 0 | Q97: -6 | S97: 1 | U97: -1
A98: Automotive | C98: 2 | E98: 1 | G98: 3 | I98: 7 | K98: -5 | M98: 1 | O98: -2 | Q98: -25 | S98: -8 | U98: 6
A99: Minerals | C99: 2 | E99: 7 | G99: 6 | I99: 1 | K99: -1 | M99: 2 | O99: 6 | Q99: -5 | S99: 1 | U99: 4
A100: Agriculture & Food Product | C100: — | E100: — | G100: — | I100: -5 | K100: -5 | M100: -2 | O100: 5 | Q100: -1 | S100: 1 | U100: 3
A101: Forest Products | C101: 4 | E101: 3 | G101: -6 | I101: -6 | K101: -4 | M101: 8 | O101: 1 | Q101: -5 | S101: 6 | U101: -2
...
